Workbook

Sheet 26414_編集版
A1: =IF(ISODD(INT((B$1 - '特殊配信マスタ'!$A$1)/7)), "隔週B", "隔週A") -> 隔週A | B1: 46126 | G1: =B1+1 -> 46127 | L1: =G1+1 -> 46128 | Q1: =L1+1 -> 46129 | V1: =Q1+1 -> 46130 | AA1: =V1+1 -> 46131 | AF1: =AA1+1 -> 46132
A2: =MOD(INT((B$1 - '特殊配信マスタ'!$A$1)/7), 3) + 1 -> 1 | B2: メルマガ内容 | C2: 通数 | D2: 設定者 | E2: 確認者 | F2: 計 | G2: メルマガ内容 | H2: 通数 | I2: 設定者 | J2: 確認者 | K2: 計 | L2: メルマガ内容 | M2: 通数 | N2: 設定者 | O2: 確認者 | P2: 計 | Q2: メルマガ内容 | R2: 通数 | S2: 設定者 | T2: 確認者 | U2: 計 | V2: メルマガ内容 | W2: 通数 | X2: 設定者 | Y2: 確認者 | Z2: 計 | AA2: メルマガ内容 | AB2: 通数 | AC2: 設定者 | AD2: 確認者 | AE2: 計 | AF2: メルマガ内容 | AG2: 通数 | AH2: 設定者 | AI2: 確認者 | AJ2: 計
A3: 8 | B3: =IFERROR(__xludf.DUMMYFUNCTION("IFERROR(LET( day, TEXT(B$1, ""ddd""), hour, LOOKUP(2, 1/($A3<>""""), $A3), type_A, $A$1, list_data, IFERROR(FILTER({'リスト'!$E$4:$F142, 'リスト'!$O$4:$P142}, ('リスト'!$A$4:$A142=day)*('リスト'!$B$4:$B142=hour)*(('リスト'!$G$4:$G142=""毎週配信"")+('リスト'!$G$4:$G142="&"type_A))), {"""","""","""",""""}), new_data, IFERROR(FILTER({'新規'!$E$2:$F142, '新規'!$O$2:$P142}, ('新規'!$A$2:$A142=B$1)*('新規'!$B$2:$B142=hour)), {"""","""","""",""""}), special_data, IFERROR(FILTER({'特殊配信マスタ'!$E$2:$F142, '特殊配信マスタ'!$O$2:$P142}, ('特殊配信マスタ"&"'!$A$2:$A142=day)*('特殊配信マスタ'!$B$2:$B142=hour)*('特殊配信マスタ'!$R$2:$R142='特殊配信マスタ'!$S$2:$S142)), {"""","""","""",""""}), combined, VSTACK(list_data, new_data, special_data), FILTER(combined, INDEX(combined, , 1)<>"""", INDEX(combined, , 1)<>0) ), """")"),"関西_自己PR不要_リモート未経験_事務") -> 関西_自己PR不要_リモート未経験_事務 | C3: =IFERROR(__xludf.DUMMYFUNCTION("""COMPUTED_VALUE"""),0.2) -> 0.2 | D3: =IFERROR(__xludf.DUMMYFUNCTION("""COMPUTED_VALUE"""),"R") -> R | F3: =SUM(C3:C12) -> 10.8 | G3: =IFERROR(__xludf.DUMMYFUNCTION("IFERROR(LET( day, TEXT(G$1, ""ddd""), hour, LOOKUP(2, 1/($A3<>""""), $A3), type_A, $A$1, list_data, IFERROR(FILTER({'リスト'!$E$4:$F142, 'リスト'!$O$4:$P142}, ('リスト'!$A$4:$A142=day)*('リスト'!$B$4:$B142=hour)*(('リスト'!$G$4:$G142=""毎週配信"")+('リスト'!$G$4:$G142="&"type_A))), {"""","""","""",""""}), new_data, IFERROR(FILTER({'新規'!$E$2:$F142, '新規'!$O$2:$P142}, ('新規'!$A$2:$A142=G$1)*('新規'!$B$2:$B142=hour)), {"""","""","""",""""}), special_data, IFERROR(FILTER({'特殊配信マスタ'!$E$2:$F142, '特殊配信マスタ'!$O$2:$P142}, ('特殊配信マスタ"&"'!$A$2:$A142=day)*('特殊配信マスタ'!$B$2:$B142=hour)*('特殊配信マスタ'!$R$2:$R142='特殊配信マスタ'!$S$2:$S142)), {"""","""","""",""""}), combined, VSTACK(list_data, new_data, special_data), FILTER(combined, INDEX(combined, , 1)<>"""", INDEX(combined, , 1)<>0) ), """")"),"★求人特集(35歳未満) A") -> ★求人特集(35歳未満) A | H3: =IFERROR(__xludf.DUMMYFUNCTION("""COMPUTED_VALUE"""),7.0) -> 7 | I3: =IFERROR(__xludf.DUMMYFUNCTION("""COMPUTED_VALUE"""),"平") -> 平 | J3: =IFERROR(__xludf.DUMMYFUNCTION("""COMPUTED_VALUE"""),"荒") -> 荒 | K3: =SUM(H3:H12) -> 7.5 | L3: =IFERROR(__xludf.DUMMYFUNCTION("IFERROR(LET( day, TEXT(L$1, ""ddd""), hour, LOOKUP(2, 1/($A3<>""""), $A3), type_A, $A$1, list_data, IFERROR(FILTER({'リスト'!$E$4:$F142, 'リスト'!$O$4:$P142}, ('リスト'!$A$4:$A142=day)*('リスト'!$B$4:$B142=hour)*(('リスト'!$G$4:$G142=""毎週配信"")+('リスト'!$G$4:$G142="&"type_A))), {"""","""","""",""""}), new_data, IFERROR(FILTER({'新規'!$E$2:$F142, '新規'!$O$2:$P142}, ('新規'!$A$2:$A142=L$1)*('新規'!$B$2:$B142=hour)), {"""","""","""",""""}), special_data, IFERROR(FILTER({'特殊配信マスタ'!$E$2:$F142, '特殊配信マスタ'!$O$2:$P142}, ('特殊配信マスタ"&"'!$A$2:$A142=day)*('特殊配信マスタ'!$B$2:$B142=hour)*('特殊配信マスタ'!$R$2:$R142='特殊配信マスタ'!$S$2:$S142)), {"""","""","""",""""}), combined, VSTACK(list_data, new_data, special_data), FILTER(combined, INDEX(combined, , 1)<>"""", INDEX(combined, , 1)<>0) ), """")"),"年収500万以上_未経験歓迎") -> 年収500万以上_未経験歓迎 | M3: =IFERROR(__xludf.DUMMYFUNCTION("""COMPUTED_VALUE"""),0.6) -> 0.6 | N3: =IFERROR(__xludf.DUMMYFUNCTION("""COMPUTED_VALUE"""),"R") -> R | P3: =SUM(M3:M12) -> 5.6 | Q3: =IFERROR(__xludf.DUMMYFUNCTION("IFERROR(LET( day, TEXT(Q$1, ""ddd""), hour, LOOKUP(2, 1/($A3<>""""), $A3), type_A, $A$1, list_data, IFERROR(FILTER({'リスト'!$E$4:$F142, 'リスト'!$O$4:$P142}, ('リスト'!$A$4:$A142=day)*('リスト'!$B$4:$B142=hour)*(('リスト'!$G$4:$G142=""毎週配信"")+('リスト'!$G$4:$G142="&"type_A))), {"""","""","""",""""}), new_data, IFERROR(FILTER({'新規'!$E$2:$F142, '新規'!$O$2:$P142}, ('新規'!$A$2:$A142=Q$1)*('新規'!$B$2:$B142=hour)), {"""","""","""",""""}), special_data, IFERROR(FILTER({'特殊配信マスタ'!$E$2:$F142, '特殊配信マスタ'!$O$2:$P142}, ('特殊配信マスタ"&"'!$A$2:$A142=day)*('特殊配信マスタ'!$B$2:$B142=hour)*('特殊配信マスタ'!$R$2:$R142='特殊配信マスタ'!$S$2:$S142)), {"""","""","""",""""}), combined, VSTACK(list_data, new_data, special_data), FILTER(combined, INDEX(combined, , 1)<>"""", INDEX(combined, , 1)<>0) ), """")"),"データ入力×リモートOK") -> データ入力×リモートOK | R3: =IFERROR(__xludf.DUMMYFUNCTION("""COMPUTED_VALUE"""),1.8) -> 1.8 | S3: =IFERROR(__xludf.DUMMYFUNCTION("""COMPUTED_VALUE"""),"R") -> R | U3: =SUM(R3:R12) -> 9.2 | V3: =IFERROR(__xludf.DUMMYFUNCTION("IFERROR(LET( day, TEXT(V$1, ""ddd""), hour, LOOKUP(2, 1/($A3<>""""), $A3), type_A, $A$1, list_data, IFERROR(FILTER({'リスト'!$E$4:$F142, 'リスト'!$O$4:$P142}, ('リスト'!$A$4:$A142=day)*('リスト'!$B$4:$B142=hour)*(('リスト'!$G$4:$G142=""毎週配信"")+('リスト'!$G$4:$G142="&"type_A))), {"""","""","""",""""}), new_data, IFERROR(FILTER({'新規'!$E$2:$F142, '新規'!$O$2:$P142}, ('新規'!$A$2:$A142=V$1)*('新規'!$B$2:$B142=hour)), {"""","""","""",""""}), special_data, IFERROR(FILTER({'特殊配信マスタ'!$E$2:$F142, '特殊配信マスタ'!$O$2:$P142}, ('特殊配信マスタ"&"'!$A$2:$A142=day)*('特殊配信マスタ'!$B$2:$B142=hour)*('特殊配信マスタ'!$R$2:$R142='特殊配信マスタ'!$S$2:$S142)), {"""","""","""",""""}), combined, VSTACK(list_data, new_data, special_data), FILTER(combined, INDEX(combined, , 1)<>"""", INDEX(combined, , 1)<>0) ), """")"),"★求人特集(35歳未満） B") -> ★求人特集(35歳未満） B | W3: =IFERROR(__xludf.DUMMYFUNCTION("""COMPUTED_VALUE"""),7.0) -> 7 | X3: =IFERROR(__xludf.DUMMYFUNCTION("""COMPUTED_VALUE"""),"平") -> 平 | Y3: =IFERROR(__xludf.DUMMYFUNCTION("""COMPUTED_VALUE"""),"荒") -> 荒 | Z3: =SUM(W3:W12) -> 7.1 | AA3: =IFERROR(__xludf.DUMMYFUNCTION("IFERROR(LET( day, TEXT(AA$1, ""ddd""), hour, LOOKUP(2, 1/($A3<>""""), $A3), type_A, $A$1, list_data, IFERROR(FILTER({'リスト'!$E$4:$F142, 'リスト'!$O$4:$P142}, ('リスト'!$A$4:$A142=day)*('リスト'!$B$4:$B142=hour)*(('リスト'!$G$4:$G142=""毎週配信"")+('リスト'!$G$4:$G142"&"=type_A))), {"""","""","""",""""}), new_data, IFERROR(FILTER({'新規'!$E$2:$F142, '新規'!$O$2:$P142}, ('新規'!$A$2:$A142=AA$1)*('新規'!$B$2:$B142=hour)), {"""","""","""",""""}), special_data, IFERROR(FILTER({'特殊配信マスタ'!$E$2:$F142, '特殊配信マスタ'!$O$2:$P142}, ('特殊配信マ"&"スタ'!$A$2:$A142=day)*('特殊配信マスタ'!$B$2:$B142=hour)*('特殊配信マスタ'!$R$2:$R142='特殊配信マスタ'!$S$2:$S142)), {"""","""","""",""""}), combined, VSTACK(list_data, new_data, special_data), FILTER(combined, INDEX(combined, , 1)<>"""", INDEX(combined, , 1)<>0) ), """")"),"40代再就職") -> 40代再就職 | AB3: =IFERROR(__xludf.DUMMYFUNCTION("""COMPUTED_VALUE"""),0.9) -> 0.9 | AC3: =IFERROR(__xludf.DUMMYFUNCTION("""COMPUTED_VALUE"""),"R") -> R | AE3: =SUM(AB3:AB12) -> 2 | AF3: =IFERROR(__xludf.DUMMYFUNCTION("IFERROR(LET( day, TEXT(AF$1, ""ddd""), hour, LOOKUP(2, 1/($A3<>""""), $A3), type_A, $A$1, list_data, IFERROR(FILTER({'リスト'!$E$4:$F142, 'リスト'!$O$4:$P142}, ('リスト'!$A$4:$A142=day)*('リスト'!$B$4:$B142=hour)*(('リスト'!$G$4:$G142=""毎週配信"")+('リスト'!$G$4:$G142"&"=type_A))), {"""","""","""",""""}), new_data, IFERROR(FILTER({'新規'!$E$2:$F142, '新規'!$O$2:$P142}, ('新規'!$A$2:$A142=AF$1)*('新規'!$B$2:$B142=hour)), {"""","""","""",""""}), special_data, IFERROR(FILTER({'特殊配信マスタ'!$E$2:$F142, '特殊配信マスタ'!$O$2:$P142}, ('特殊配信マ"&"スタ'!$A$2:$A142=day)*('特殊配信マスタ'!$B$2:$B142=hour)*('特殊配信マスタ'!$R$2:$R142='特殊配信マスタ'!$S$2:$S142)), {"""","""","""",""""}), combined, VSTACK(list_data, new_data, special_data), FILTER(combined, INDEX(combined, , 1)<>"""", INDEX(combined, , 1)<>0) ), """")"),"◇掲載終了前+UP_35歳以上 B") -> ◇掲載終了前+UP_35歳以上 B | AG3: =IFERROR(__xludf.DUMMYFUNCTION("""COMPUTED_VALUE"""),1.0) -> 1 | AH3: =IFERROR(__xludf.DUMMYFUNCTION("""COMPUTED_VALUE"""),"内") -> 内 | AI3: =IFERROR(__xludf.DUMMYFUNCTION("""COMPUTED_VALUE"""),"荒") -> 荒 | AJ3: =SUM(AG3:AG12) -> 8.9
B4: =IFERROR(__xludf.DUMMYFUNCTION("""COMPUTED_VALUE"""),"応募から1日_好条件営業ランキング") -> 応募から1日_好条件営業ランキング | C4: =IFERROR(__xludf.DUMMYFUNCTION("""COMPUTED_VALUE"""),0.1) -> 0.1 | D4: =IFERROR(__xludf.DUMMYFUNCTION("""COMPUTED_VALUE"""),"R") -> R | G4: =IFERROR(__xludf.DUMMYFUNCTION("""COMPUTED_VALUE"""),"50代事務") -> 50代事務 | H4: =IFERROR(__xludf.DUMMYFUNCTION("""COMPUTED_VALUE"""),0.4) -> 0.4 | I4: =IFERROR(__xludf.DUMMYFUNCTION("""COMPUTED_VALUE"""),"部") -> 部 | J4: =IFERROR(__xludf.DUMMYFUNCTION("""COMPUTED_VALUE"""),"石") -> 石 | L4: =IFERROR(__xludf.DUMMYFUNCTION("""COMPUTED_VALUE"""),"応募から1日_好条件営業ランキング") -> 応募から1日_好条件営業ランキング | M4: =IFERROR(__xludf.DUMMYFUNCTION("""COMPUTED_VALUE"""),0.1) -> 0.1 | N4: =IFERROR(__xludf.DUMMYFUNCTION("""COMPUTED_VALUE"""),"R") -> R | Q4: =IFERROR(__xludf.DUMMYFUNCTION("""COMPUTED_VALUE"""),"フルリモート×好条件") -> フルリモート×好条件 | R4: =IFERROR(__xludf.DUMMYFUNCTION("""COMPUTED_VALUE"""),5.7) -> 5.7 | S4: =IFERROR(__xludf.DUMMYFUNCTION("""COMPUTED_VALUE"""),"部") -> 部 | T4: =IFERROR(__xludf.DUMMYFUNCTION("""COMPUTED_VALUE"""),"石") -> 石 | V4: =IFERROR(__xludf.DUMMYFUNCTION("""COMPUTED_VALUE"""),"応募から1日_好条件営業ランキング") -> 応募から1日_好条件営業ランキング | W4: =IFERROR(__xludf.DUMMYFUNCTION("""COMPUTED_VALUE"""),0.1) -> 0.1 | X4: =IFERROR(__xludf.DUMMYFUNCTION("""COMPUTED_VALUE"""),"R") -> R | AA4: =IFERROR(__xludf.DUMMYFUNCTION("""COMPUTED_VALUE"""),"40代再就職_関西") -> 40代再就職_関西 | AB4: =IFERROR(__xludf.DUMMYFUNCTION("""COMPUTED_VALUE"""),0.4) -> 0.4 | AC4: =IFERROR(__xludf.DUMMYFUNCTION("""COMPUTED_VALUE"""),"R") -> R | AF4: =IFERROR(__xludf.DUMMYFUNCTION("""COMPUTED_VALUE"""),"◇掲載終了前+UP_関西 B") -> ◇掲載終了前+UP_関西 B | AG4: =IFERROR(__xludf.DUMMYFUNCTION("""COMPUTED_VALUE"""),1.0) -> 1 | AH4: =IFERROR(__xludf.DUMMYFUNCTION("""COMPUTED_VALUE"""),"内") -> 内 | AI4: =IFERROR(__xludf.DUMMYFUNCTION("""COMPUTED_VALUE"""),"荒") -> 荒
B5: =IFERROR(__xludf.DUMMYFUNCTION("""COMPUTED_VALUE"""),"快適な在宅ワーク") -> 快適な在宅ワーク | C5: =IFERROR(__xludf.DUMMYFUNCTION("""COMPUTED_VALUE"""),4.3) -> 4.3 | D5: =IFERROR(__xludf.DUMMYFUNCTION("""COMPUTED_VALUE"""),"石") -> 石 | E5: =IFERROR(__xludf.DUMMYFUNCTION("""COMPUTED_VALUE"""),"部") -> 部 | G5: =IFERROR(__xludf.DUMMYFUNCTION("""COMPUTED_VALUE"""),"応募から1日_好条件営業ランキング") -> 応募から1日_好条件営業ランキング | H5: =IFERROR(__xludf.DUMMYFUNCTION("""COMPUTED_VALUE"""),0.1) -> 0.1 | I5: =IFERROR(__xludf.DUMMYFUNCTION("""COMPUTED_VALUE"""),"R") -> R | L5: =IFERROR(__xludf.DUMMYFUNCTION("""COMPUTED_VALUE"""),"新着_クリエイティブ") -> 新着_クリエイティブ | M5: =IFERROR(__xludf.DUMMYFUNCTION("""COMPUTED_VALUE"""),0.4) -> 0.4 | N5: =IFERROR(__xludf.DUMMYFUNCTION("""COMPUTED_VALUE"""),"R") -> R | Q5: =IFERROR(__xludf.DUMMYFUNCTION("""COMPUTED_VALUE"""),"応募から1日_好条件営業ランキング") -> 応募から1日_好条件営業ランキング | R5: =IFERROR(__xludf.DUMMYFUNCTION("""COMPUTED_VALUE"""),0.1) -> 0.1 | S5: =IFERROR(__xludf.DUMMYFUNCTION("""COMPUTED_VALUE"""),"R") -> R | AA5: =IFERROR(__xludf.DUMMYFUNCTION("""COMPUTED_VALUE"""),"応募から1日_好条件営業ランキング") -> 応募から1日_好条件営業ランキング | AB5: =IFERROR(__xludf.DUMMYFUNCTION("""COMPUTED_VALUE"""),0.1) -> 0.1 | AC5: =IFERROR(__xludf.DUMMYFUNCTION("""COMPUTED_VALUE"""),"R") -> R | AF5: =IFERROR(__xludf.DUMMYFUNCTION("""COMPUTED_VALUE"""),"webデザイナー×未経験歓迎_希望") -> webデザイナー×未経験歓迎_希望 | AG5: =IFERROR(__xludf.DUMMYFUNCTION("""COMPUTED_VALUE"""),0.6) -> 0.6 | AH5: =IFERROR(__xludf.DUMMYFUNCTION("""COMPUTED_VALUE"""),"R") -> R
B6: =IFERROR(__xludf.DUMMYFUNCTION("""COMPUTED_VALUE"""),"推し活_残業なし_休日120日以上_月給30万以上") -> 推し活_残業なし_休日120日以上_月給30万以上 | C6: =IFERROR(__xludf.DUMMYFUNCTION("""COMPUTED_VALUE"""),1.2) -> 1.2 | D6: =IFERROR(__xludf.DUMMYFUNCTION("""COMPUTED_VALUE"""),"R") -> R | L6: =IFERROR(__xludf.DUMMYFUNCTION("""COMPUTED_VALUE"""),"新着_企画営業") -> 新着_企画営業 | M6: =IFERROR(__xludf.DUMMYFUNCTION("""COMPUTED_VALUE"""),0.9) -> 0.9 | N6: =IFERROR(__xludf.DUMMYFUNCTION("""COMPUTED_VALUE"""),"R") -> R | Q6: =IFERROR(__xludf.DUMMYFUNCTION("""COMPUTED_VALUE"""),"既婚者") -> 既婚者 | R6: =IFERROR(__xludf.DUMMYFUNCTION("""COMPUTED_VALUE"""),0.4) -> 0.4 | S6: =IFERROR(__xludf.DUMMYFUNCTION("""COMPUTED_VALUE"""),"R") -> R | AA6: =IFERROR(__xludf.DUMMYFUNCTION("""COMPUTED_VALUE"""),"人気検索KW_事務系希望") -> 人気検索KW_事務系希望 | AB6: =IFERROR(__xludf.DUMMYFUNCTION("""COMPUTED_VALUE"""),0.6) -> 0.6 | AC6: =IFERROR(__xludf.DUMMYFUNCTION("""COMPUTED_VALUE"""),"R") -> R | AF6: =IFERROR(__xludf.DUMMYFUNCTION("""COMPUTED_VALUE"""),"応募から1日_好条件営業ランキング") -> 応募から1日_好条件営業ランキング | AG6: =IFERROR(__xludf.DUMMYFUNCTION("""COMPUTED_VALUE"""),0.1) -> 0.1 | AH6: =IFERROR(__xludf.DUMMYFUNCTION("""COMPUTED_VALUE"""),"R") -> R
B7: =IFERROR(__xludf.DUMMYFUNCTION("""COMPUTED_VALUE"""),"◇ポジションマッチ A1") -> ◇ポジションマッチ A1 | C7: =IFERROR(__xludf.DUMMYFUNCTION("""COMPUTED_VALUE"""),2.5) -> 2.5 | D7: =IFERROR(__xludf.DUMMYFUNCTION("""COMPUTED_VALUE"""),"内") -> 内 | E7: =IFERROR(__xludf.DUMMYFUNCTION("""COMPUTED_VALUE"""),"平") -> 平 | L7: =IFERROR(__xludf.DUMMYFUNCTION("""COMPUTED_VALUE"""),"新着_経理") -> 新着_経理 | M7: =IFERROR(__xludf.DUMMYFUNCTION("""COMPUTED_VALUE"""),0.5) -> 0.5 | N7: =IFERROR(__xludf.DUMMYFUNCTION("""COMPUTED_VALUE"""),"R") -> R | Q7: =IFERROR(__xludf.DUMMYFUNCTION("""COMPUTED_VALUE"""),"梅田で働く") -> 梅田で働く | R7: =IFERROR(__xludf.DUMMYFUNCTION("""COMPUTED_VALUE"""),0.8) -> 0.8 | S7: =IFERROR(__xludf.DUMMYFUNCTION("""COMPUTED_VALUE"""),"R") -> R | AF7: =IFERROR(__xludf.DUMMYFUNCTION("""COMPUTED_VALUE"""),"高収入_リモート_営業") -> 高収入_リモート_営業 | AG7: =IFERROR(__xludf.DUMMYFUNCTION("""COMPUTED_VALUE"""),1.2) -> 1.2 | AH7: =IFERROR(__xludf.DUMMYFUNCTION("""COMPUTED_VALUE"""),"R") -> R
B8: =IFERROR(__xludf.DUMMYFUNCTION("""COMPUTED_VALUE"""),"◇ポジションマッチ_36歳以上 A1") -> ◇ポジションマッチ_36歳以上 A1 | C8: =IFERROR(__xludf.DUMMYFUNCTION("""COMPUTED_VALUE"""),2.5) -> 2.5 | D8: =IFERROR(__xludf.DUMMYFUNCTION("""COMPUTED_VALUE"""),"内") -> 内 | E8: =IFERROR(__xludf.DUMMYFUNCTION("""COMPUTED_VALUE"""),"平") -> 平 | L8: =IFERROR(__xludf.DUMMYFUNCTION("""COMPUTED_VALUE"""),"新着_事務") -> 新着_事務 | M8: =IFERROR(__xludf.DUMMYFUNCTION("""COMPUTED_VALUE"""),2.5) -> 2.5 | N8: =IFERROR(__xludf.DUMMYFUNCTION("""COMPUTED_VALUE"""),"R") -> R | Q8: =IFERROR(__xludf.DUMMYFUNCTION("""COMPUTED_VALUE"""),"未婚者") -> 未婚者 | R8: =IFERROR(__xludf.DUMMYFUNCTION("""COMPUTED_VALUE"""),0.4) -> 0.4 | S8: =IFERROR(__xludf.DUMMYFUNCTION("""COMPUTED_VALUE"""),"R") -> R | AF8: =IFERROR(__xludf.DUMMYFUNCTION("""COMPUTED_VALUE"""),"高収入_リモート_事務") -> 高収入_リモート_事務 | AG8: =IFERROR(__xludf.DUMMYFUNCTION("""COMPUTED_VALUE"""),3.0) -> 3 | AH8: =IFERROR(__xludf.DUMMYFUNCTION("""COMPUTED_VALUE"""),"R") -> R
L9: =IFERROR(__xludf.DUMMYFUNCTION("""COMPUTED_VALUE"""),"新着_人事") -> 新着_人事 | M9: =IFERROR(__xludf.DUMMYFUNCTION("""COMPUTED_VALUE"""),0.6) -> 0.6 | N9: =IFERROR(__xludf.DUMMYFUNCTION("""COMPUTED_VALUE"""),"R") -> R | AF9: =IFERROR(__xludf.DUMMYFUNCTION("""COMPUTED_VALUE"""),"◇掲載終了前+UP B") -> ◇掲載終了前+UP B | AG9: =IFERROR(__xludf.DUMMYFUNCTION("""COMPUTED_VALUE"""),2.0) -> 2 | AH9: =IFERROR(__xludf.DUMMYFUNCTION("""COMPUTED_VALUE"""),"内") -> 内 | AI9: =IFERROR(__xludf.DUMMYFUNCTION("""COMPUTED_VALUE"""),"荒") -> 荒
A13: =A3+1 -> 9 | B13: =IFERROR(__xludf.DUMMYFUNCTION("IFERROR(LET( day, TEXT(B$1, ""ddd""), hour, LOOKUP(2, 1/($A13<>""""), $A13), type_A, $A$1, list_data, IFERROR(FILTER({'リスト'!$E$4:$F142, 'リスト'!$O$4:$P142}, ('リスト'!$A$4:$A142=day)*('リスト'!$B$4:$B142=hour)*(('リスト'!$G$4:$G142=""毎週配信"")+('リスト'!$G$4:$G14"&"2=type_A))), {"""","""","""",""""}), new_data, IFERROR(FILTER({'新規'!$E$2:$F142, '新規'!$O$2:$P142}, ('新規'!$A$2:$A142=B$1)*('新規'!$B$2:$B142=hour)), {"""","""","""",""""}), special_data, IFERROR(FILTER({'特殊配信マスタ'!$E$2:$F142, '特殊配信マスタ'!$O$2:$P142}, ('特殊配信マ"&"スタ'!$A$2:$A142=day)*('特殊配信マスタ'!$B$2:$B142=hour)*('特殊配信マスタ'!$R$2:$R142='特殊配信マスタ'!$S$2:$S142)), {"""","""","""",""""}), combined, VSTACK(list_data, new_data, special_data), FILTER(combined, INDEX(combined, , 1)<>"""", INDEX(combined, , 1)<>0) ), """")"),"ランキング_クリエイティブ（Web）_希望") -> ランキング_クリエイティブ（Web）_希望 | C13: =IFERROR(__xludf.DUMMYFUNCTION("""COMPUTED_VALUE"""),0.5) -> 0.5 | D13: =IFERROR(__xludf.DUMMYFUNCTION("""COMPUTED_VALUE"""),"R") -> R | F13: =SUM(C13:C22) -> 2.5 | G13: =IFERROR(__xludf.DUMMYFUNCTION("IFERROR(LET( day, TEXT(G$1, ""ddd""), hour, LOOKUP(2, 1/($A13<>""""), $A13), type_A, $A$1, list_data, IFERROR(FILTER({'リスト'!$E$4:$F142, 'リスト'!$O$4:$P142}, ('リスト'!$A$4:$A142=day)*('リスト'!$B$4:$B142=hour)*(('リスト'!$G$4:$G142=""毎週配信"")+('リスト'!$G$4:$G14"&"2=type_A))), {"""","""","""",""""}), new_data, IFERROR(FILTER({'新規'!$E$2:$F142, '新規'!$O$2:$P142}, ('新規'!$A$2:$A142=G$1)*('新規'!$B$2:$B142=hour)), {"""","""","""",""""}), special_data, IFERROR(FILTER({'特殊配信マスタ'!$E$2:$F142, '特殊配信マスタ'!$O$2:$P142}, ('特殊配信マ"&"スタ'!$A$2:$A142=day)*('特殊配信マスタ'!$B$2:$B142=hour)*('特殊配信マスタ'!$R$2:$R142='特殊配信マスタ'!$S$2:$S142)), {"""","""","""",""""}), combined, VSTACK(list_data, new_data, special_data), FILTER(combined, INDEX(combined, , 1)<>"""", INDEX(combined, , 1)<>0) ), """")"),"ランキング_エンジニア（IT系）_希望") -> ランキング_エンジニア（IT系）_希望 | H13: =IFERROR(__xludf.DUMMYFUNCTION("""COMPUTED_VALUE"""),0.3) -> 0.3 | I13: =IFERROR(__xludf.DUMMYFUNCTION("""COMPUTED_VALUE"""),"R") -> R | K13: =SUM(H13:H22) -> 3.8 | L13: =IFERROR(__xludf.DUMMYFUNCTION("IFERROR(LET( day, TEXT(L$1, ""ddd""), hour, LOOKUP(2, 1/($A13<>""""), $A13), type_A, $A$1, list_data, IFERROR(FILTER({'リスト'!$E$4:$F142, 'リスト'!$O$4:$P142}, ('リスト'!$A$4:$A142=day)*('リスト'!$B$4:$B142=hour)*(('リスト'!$G$4:$G142=""毎週配信"")+('リスト'!$G$4:$G14"&"2=type_A))), {"""","""","""",""""}), new_data, IFERROR(FILTER({'新規'!$E$2:$F142, '新規'!$O$2:$P142}, ('新規'!$A$2:$A142=L$1)*('新規'!$B$2:$B142=hour)), {"""","""","""",""""}), special_data, IFERROR(FILTER({'特殊配信マスタ'!$E$2:$F142, '特殊配信マスタ'!$O$2:$P142}, ('特殊配信マ"&"スタ'!$A$2:$A142=day)*('特殊配信マスタ'!$B$2:$B142=hour)*('特殊配信マスタ'!$R$2:$R142='特殊配信マスタ'!$S$2:$S142)), {"""","""","""",""""}), combined, VSTACK(list_data, new_data, special_data), FILTER(combined, INDEX(combined, , 1)<>"""", INDEX(combined, , 1)<>0) ), """")"),"ランキング_営業（BtoB）_希望") -> ランキング_営業（BtoB）_希望 | M13: =IFERROR(__xludf.DUMMYFUNCTION("""COMPUTED_VALUE"""),0.3) -> 0.3 | N13: =IFERROR(__xludf.DUMMYFUNCTION("""COMPUTED_VALUE"""),"R") -> R | P13: =SUM(M13:M22) -> 2.3 | Q13: =IFERROR(__xludf.DUMMYFUNCTION("IFERROR(LET( day, TEXT(Q$1, ""ddd""), hour, LOOKUP(2, 1/($A13<>""""), $A13), type_A, $A$1, list_data, IFERROR(FILTER({'リスト'!$E$4:$F142, 'リスト'!$O$4:$P142}, ('リスト'!$A$4:$A142=day)*('リスト'!$B$4:$B142=hour)*(('リスト'!$G$4:$G142=""毎週配信"")+('リスト'!$G$4:$G14"&"2=type_A))), {"""","""","""",""""}), new_data, IFERROR(FILTER({'新規'!$E$2:$F142, '新規'!$O$2:$P142}, ('新規'!$A$2:$A142=Q$1)*('新規'!$B$2:$B142=hour)), {"""","""","""",""""}), special_data, IFERROR(FILTER({'特殊配信マスタ'!$E$2:$F142, '特殊配信マスタ'!$O$2:$P142}, ('特殊配信マ"&"スタ'!$A$2:$A142=day)*('特殊配信マスタ'!$B$2:$B142=hour)*('特殊配信マスタ'!$R$2:$R142='特殊配信マスタ'!$S$2:$S142)), {"""","""","""",""""}), combined, VSTACK(list_data, new_data, special_data), FILTER(combined, INDEX(combined, , 1)<>"""", INDEX(combined, , 1)<>0) ), """")"),"40~60代活躍中") -> 40~60代活躍中 | R13: =IFERROR(__xludf.DUMMYFUNCTION("""COMPUTED_VALUE"""),1.5) -> 1.5 | S13: =IFERROR(__xludf.DUMMYFUNCTION("""COMPUTED_VALUE"""),"石") -> 石 | T13: =IFERROR(__xludf.DUMMYFUNCTION("""COMPUTED_VALUE"""),"武") -> 武 | U13: =SUM(R13:R22) -> 1.9 | V13: =IFERROR(__xludf.DUMMYFUNCTION("IFERROR(LET( day, TEXT(V$1, ""ddd""), hour, LOOKUP(2, 1/($A13<>""""), $A13), type_A, $A$1, list_data, IFERROR(FILTER({'リスト'!$E$4:$F142, 'リスト'!$O$4:$P142}, ('リスト'!$A$4:$A142=day)*('リスト'!$B$4:$B142=hour)*(('リスト'!$G$4:$G142=""毎週配信"")+('リスト'!$G$4:$G14"&"2=type_A))), {"""","""","""",""""}), new_data, IFERROR(FILTER({'新規'!$E$2:$F142, '新規'!$O$2:$P142}, ('新規'!$A$2:$A142=V$1)*('新規'!$B$2:$B142=hour)), {"""","""","""",""""}), special_data, IFERROR(FILTER({'特殊配信マスタ'!$E$2:$F142, '特殊配信マスタ'!$O$2:$P142}, ('特殊配信マ"&"スタ'!$A$2:$A142=day)*('特殊配信マスタ'!$B$2:$B142=hour)*('特殊配信マスタ'!$R$2:$R142='特殊配信マスタ'!$S$2:$S142)), {"""","""","""",""""}), combined, VSTACK(list_data, new_data, special_data), FILTER(combined, INDEX(combined, , 1)<>"""", INDEX(combined, , 1)<>0) ), """")"),"NPS取得アンケート") -> NPS取得アンケート | W13: =IFERROR(__xludf.DUMMYFUNCTION("""COMPUTED_VALUE"""),0.3) -> 0.3 | X13: =IFERROR(__xludf.DUMMYFUNCTION("""COMPUTED_VALUE"""),"R") -> R | Z13: =SUM(W13:W22) -> 2.4 | AA13: =IFERROR(__xludf.DUMMYFUNCTION("IFERROR(LET( day, TEXT(AA$1, ""ddd""), hour, LOOKUP(2, 1/($A13<>""""), $A13), type_A, $A$1, list_data, IFERROR(FILTER({'リスト'!$E$4:$F142, 'リスト'!$O$4:$P142}, ('リスト'!$A$4:$A142=day)*('リスト'!$B$4:$B142=hour)*(('リスト'!$G$4:$G142=""毎週配信"")+('リスト'!$G$4:$G1"&"42=type_A))), {"""","""","""",""""}), new_data, IFERROR(FILTER({'新規'!$E$2:$F142, '新規'!$O$2:$P142}, ('新規'!$A$2:$A142=AA$1)*('新規'!$B$2:$B142=hour)), {"""","""","""",""""}), special_data, IFERROR(FILTER({'特殊配信マスタ'!$E$2:$F142, '特殊配信マスタ'!$O$2:$P142}, ('特殊配"&"信マスタ'!$A$2:$A142=day)*('特殊配信マスタ'!$B$2:$B142=hour)*('特殊配信マスタ'!$R$2:$R142='特殊配信マスタ'!$S$2:$S142)), {"""","""","""",""""}), combined, VSTACK(list_data, new_data, special_data), FILTER(combined, INDEX(combined, , 1)<>"""", INDEX(combined, , 1)<>0) ), """")"),"これから人気×エンジニア") -> これから人気×エンジニア | AB13: =IFERROR(__xludf.DUMMYFUNCTION("""COMPUTED_VALUE"""),0.2) -> 0.2 | AC13: =IFERROR(__xludf.DUMMYFUNCTION("""COMPUTED_VALUE"""),"R") -> R | AE13: =SUM(AB13:AB22) -> 5.8 | AF13: =IFERROR(__xludf.DUMMYFUNCTION("IFERROR(LET( day, TEXT(AF$1, ""ddd""), hour, LOOKUP(2, 1/($A13<>""""), $A13), type_A, $A$1, list_data, IFERROR(FILTER({'リスト'!$E$4:$F142, 'リスト'!$O$4:$P142}, ('リスト'!$A$4:$A142=day)*('リスト'!$B$4:$B142=hour)*(('リスト'!$G$4:$G142=""毎週配信"")+('リスト'!$G$4:$G1"&"42=type_A))), {"""","""","""",""""}), new_data, IFERROR(FILTER({'新規'!$E$2:$F142, '新規'!$O$2:$P142}, ('新規'!$A$2:$A142=AF$1)*('新規'!$B$2:$B142=hour)), {"""","""","""",""""}), special_data, IFERROR(FILTER({'特殊配信マスタ'!$E$2:$F142, '特殊配信マスタ'!$O$2:$P142}, ('特殊配"&"信マスタ'!$A$2:$A142=day)*('特殊配信マスタ'!$B$2:$B142=hour)*('特殊配信マスタ'!$R$2:$R142='特殊配信マスタ'!$S$2:$S142)), {"""","""","""",""""}), combined, VSTACK(list_data, new_data, special_data), FILTER(combined, INDEX(combined, , 1)<>"""", INDEX(combined, , 1)<>0) ), """")"),"年収600万円以上") -> 年収600万円以上 | AG13: =IFERROR(__xludf.DUMMYFUNCTION("""COMPUTED_VALUE"""),0.3) -> 0.3 | AH13: =IFERROR(__xludf.DUMMYFUNCTION("""COMPUTED_VALUE"""),"R") -> R | AJ13: =SUM(AG13:AG22) -> 1.9
B14: =IFERROR(__xludf.DUMMYFUNCTION("""COMPUTED_VALUE"""),"ランキング_営業（マーケ）_希望") -> ランキング_営業（マーケ）_希望 | C14: =IFERROR(__xludf.DUMMYFUNCTION("""COMPUTED_VALUE"""),0.5) -> 0.5 | D14: =IFERROR(__xludf.DUMMYFUNCTION("""COMPUTED_VALUE"""),"R") -> R | G14: =IFERROR(__xludf.DUMMYFUNCTION("""COMPUTED_VALUE"""),"ランキング_クリエイティブ（その他）_希望") -> ランキング_クリエイティブ（その他）_希望 | H14: =IFERROR(__xludf.DUMMYFUNCTION("""COMPUTED_VALUE"""),0.4) -> 0.4 | I14: =IFERROR(__xludf.DUMMYFUNCTION("""COMPUTED_VALUE"""),"R") -> R | L14: =IFERROR(__xludf.DUMMYFUNCTION("""COMPUTED_VALUE"""),"ランキング_事務（秘書）_希望") -> ランキング_事務（秘書）_希望 | M14: =IFERROR(__xludf.DUMMYFUNCTION("""COMPUTED_VALUE"""),0.9) -> 0.9 | N14: =IFERROR(__xludf.DUMMYFUNCTION("""COMPUTED_VALUE"""),"R") -> R | Q14: =IFERROR(__xludf.DUMMYFUNCTION("""COMPUTED_VALUE"""),"ランキング_事務（経理）_希望") -> ランキング_事務（経理）_希望 | R14: =IFERROR(__xludf.DUMMYFUNCTION("""COMPUTED_VALUE"""),0.4) -> 0.4 | S14: =IFERROR(__xludf.DUMMYFUNCTION("""COMPUTED_VALUE"""),"R") -> R | V14: =IFERROR(__xludf.DUMMYFUNCTION("""COMPUTED_VALUE"""),"単独求人訴求メルマガ_A") -> 単独求人訴求メルマガ_A | W14: =IFERROR(__xludf.DUMMYFUNCTION("""COMPUTED_VALUE"""),2.1) -> 2.1 | X14: =IFERROR(__xludf.DUMMYFUNCTION("""COMPUTED_VALUE"""),"武") -> 武 | Y14: =IFERROR(__xludf.DUMMYFUNCTION("""COMPUTED_VALUE"""),"部") -> 部 | AA14: =IFERROR(__xludf.DUMMYFUNCTION("""COMPUTED_VALUE"""),"これから人気×リモート") -> これから人気×リモート | AB14: =IFERROR(__xludf.DUMMYFUNCTION("""COMPUTED_VALUE"""),0.6) -> 0.6 | AC14: =IFERROR(__xludf.DUMMYFUNCTION("""COMPUTED_VALUE"""),"R") -> R | AF14: =IFERROR(__xludf.DUMMYFUNCTION("""COMPUTED_VALUE"""),"ランキング_事務（広報）_希望") -> ランキング_事務（広報）_希望 | AG14: =IFERROR(__xludf.DUMMYFUNCTION("""COMPUTED_VALUE"""),0.3) -> 0.3 | AH14: =IFERROR(__xludf.DUMMYFUNCTION("""COMPUTED_VALUE"""),"R") -> R
B15: =IFERROR(__xludf.DUMMYFUNCTION("""COMPUTED_VALUE"""),"ランキング_事務（一般事務）_希望") -> ランキング_事務（一般事務）_希望 | C15: =IFERROR(__xludf.DUMMYFUNCTION("""COMPUTED_VALUE"""),1.5) -> 1.5 | D15: =IFERROR(__xludf.DUMMYFUNCTION("""COMPUTED_VALUE"""),"R") -> R | G15: =IFERROR(__xludf.DUMMYFUNCTION("""COMPUTED_VALUE"""),"ランキング_営業（その他）_希望") -> ランキング_営業（その他）_希望 | H15: =IFERROR(__xludf.DUMMYFUNCTION("""COMPUTED_VALUE"""),0.4) -> 0.4 | I15: =IFERROR(__xludf.DUMMYFUNCTION("""COMPUTED_VALUE"""),"R") -> R | L15: =IFERROR(__xludf.DUMMYFUNCTION("""COMPUTED_VALUE"""),"関西限定求人特集") -> 関西限定求人特集 | M15: =IFERROR(__xludf.DUMMYFUNCTION("""COMPUTED_VALUE"""),1.1) -> 1.1 | N15: =IFERROR(__xludf.DUMMYFUNCTION("""COMPUTED_VALUE"""),"R") -> R | AA15: =IFERROR(__xludf.DUMMYFUNCTION("""COMPUTED_VALUE"""),"これから人気×リモート×営業") -> これから人気×リモート×営業 | AB15: =IFERROR(__xludf.DUMMYFUNCTION("""COMPUTED_VALUE"""),0.3) -> 0.3 | AC15: =IFERROR(__xludf.DUMMYFUNCTION("""COMPUTED_VALUE"""),"R") -> R | AF15: =IFERROR(__xludf.DUMMYFUNCTION("""COMPUTED_VALUE"""),"直近新規登録会員向け") -> 直近新規登録会員向け | AG15: =IFERROR(__xludf.DUMMYFUNCTION("""COMPUTED_VALUE"""),1.3) -> 1.3 | AH15: =IFERROR(__xludf.DUMMYFUNCTION("""COMPUTED_VALUE"""),"R") -> R
G16: =IFERROR(__xludf.DUMMYFUNCTION("""COMPUTED_VALUE"""),"ランキング_事務（営業事務）_希望") -> ランキング_事務（営業事務）_希望 | H16: =IFERROR(__xludf.DUMMYFUNCTION("""COMPUTED_VALUE"""),1.0) -> 1 | I16: =IFERROR(__xludf.DUMMYFUNCTION("""COMPUTED_VALUE"""),"R") -> R | AA16: =IFERROR(__xludf.DUMMYFUNCTION("""COMPUTED_VALUE"""),"これから人気×販サ") -> これから人気×販サ | AB16: =IFERROR(__xludf.DUMMYFUNCTION("""COMPUTED_VALUE"""),0.2) -> 0.2 | AC16: =IFERROR(__xludf.DUMMYFUNCTION("""COMPUTED_VALUE"""),"R") -> R
G17: =IFERROR(__xludf.DUMMYFUNCTION("""COMPUTED_VALUE"""),"裁量労働制") -> 裁量労働制 | H17: =IFERROR(__xludf.DUMMYFUNCTION("""COMPUTED_VALUE"""),1.1) -> 1.1 | I17: =IFERROR(__xludf.DUMMYFUNCTION("""COMPUTED_VALUE"""),"R") -> R | AA17: =IFERROR(__xludf.DUMMYFUNCTION("""COMPUTED_VALUE"""),"応募ランキング C") -> 応募ランキング C | AB17: =IFERROR(__xludf.DUMMYFUNCTION("""COMPUTED_VALUE"""),4.5) -> 4.5 | AC17: =IFERROR(__xludf.DUMMYFUNCTION("""COMPUTED_VALUE"""),"R") -> R
G18: =IFERROR(__xludf.DUMMYFUNCTION("""COMPUTED_VALUE"""),"時短×リモート") -> 時短×リモート | H18: =IFERROR(__xludf.DUMMYFUNCTION("""COMPUTED_VALUE"""),0.6) -> 0.6 | I18: =IFERROR(__xludf.DUMMYFUNCTION("""COMPUTED_VALUE"""),"R") -> R
A23: =A13+1 -> 10 | B23: =IFERROR(__xludf.DUMMYFUNCTION("IFERROR(LET( day, TEXT(B$1, ""ddd""), hour, LOOKUP(2, 1/($A23<>""""), $A23), type_A, $A$1, list_data, IFERROR(FILTER({'リスト'!$E$4:$F142, 'リスト'!$O$4:$P142}, ('リスト'!$A$4:$A142=day)*('リスト'!$B$4:$B142=hour)*(('リスト'!$G$4:$G142=""毎週配信"")+('リスト'!$G$4:$G14"&"2=type_A))), {"""","""","""",""""}), new_data, IFERROR(FILTER({'新規'!$E$2:$F142, '新規'!$O$2:$P142}, ('新規'!$A$2:$A142=B$1)*('新規'!$B$2:$B142=hour)), {"""","""","""",""""}), special_data, IFERROR(FILTER({'特殊配信マスタ'!$E$2:$F142, '特殊配信マスタ'!$O$2:$P142}, ('特殊配信マ"&"スタ'!$A$2:$A142=day)*('特殊配信マスタ'!$B$2:$B142=hour)*('特殊配信マスタ'!$R$2:$R142='特殊配信マスタ'!$S$2:$S142)), {"""","""","""",""""}), combined, VSTACK(list_data, new_data, special_data), FILTER(combined, INDEX(combined, , 1)<>"""", INDEX(combined, , 1)<>0) ), """")"),"事務_販サ経験者向け_東京") -> 事務_販サ経験者向け_東京 | C23: =IFERROR(__xludf.DUMMYFUNCTION("""COMPUTED_VALUE"""),0.4) -> 0.4 | D23: =IFERROR(__xludf.DUMMYFUNCTION("""COMPUTED_VALUE"""),"R") -> R | F23: =SUM(C23:C32) -> 2.9 | G23: =IFERROR(__xludf.DUMMYFUNCTION("IFERROR(LET( day, TEXT(G$1, ""ddd""), hour, LOOKUP(2, 1/($A23<>""""), $A23), type_A, $A$1, list_data, IFERROR(FILTER({'リスト'!$E$4:$F142, 'リスト'!$O$4:$P142}, ('リスト'!$A$4:$A142=day)*('リスト'!$B$4:$B142=hour)*(('リスト'!$G$4:$G142=""毎週配信"")+('リスト'!$G$4:$G14"&"2=type_A))), {"""","""","""",""""}), new_data, IFERROR(FILTER({'新規'!$E$2:$F142, '新規'!$O$2:$P142}, ('新規'!$A$2:$A142=G$1)*('新規'!$B$2:$B142=hour)), {"""","""","""",""""}), special_data, IFERROR(FILTER({'特殊配信マスタ'!$E$2:$F142, '特殊配信マスタ'!$O$2:$P142}, ('特殊配信マ"&"スタ'!$A$2:$A142=day)*('特殊配信マスタ'!$B$2:$B142=hour)*('特殊配信マスタ'!$R$2:$R142='特殊配信マスタ'!$S$2:$S142)), {"""","""","""",""""}), combined, VSTACK(list_data, new_data, special_data), FILTER(combined, INDEX(combined, , 1)<>"""", INDEX(combined, , 1)<>0) ), """")"),"40代未経験_正社員") -> 40代未経験_正社員 | H23: =IFERROR(__xludf.DUMMYFUNCTION("""COMPUTED_VALUE"""),2.3) -> 2.3 | I23: =IFERROR(__xludf.DUMMYFUNCTION("""COMPUTED_VALUE"""),"R") -> R | K23: =SUM(H23:H32) -> 3.9 | L23: =IFERROR(__xludf.DUMMYFUNCTION("IFERROR(LET( day, TEXT(L$1, ""ddd""), hour, LOOKUP(2, 1/($A23<>""""), $A23), type_A, $A$1, list_data, IFERROR(FILTER({'リスト'!$E$4:$F142, 'リスト'!$O$4:$P142}, ('リスト'!$A$4:$A142=day)*('リスト'!$B$4:$B142=hour)*(('リスト'!$G$4:$G142=""毎週配信"")+('リスト'!$G$4:$G14"&"2=type_A))), {"""","""","""",""""}), new_data, IFERROR(FILTER({'新規'!$E$2:$F142, '新規'!$O$2:$P142}, ('新規'!$A$2:$A142=L$1)*('新規'!$B$2:$B142=hour)), {"""","""","""",""""}), special_data, IFERROR(FILTER({'特殊配信マスタ'!$E$2:$F142, '特殊配信マスタ'!$O$2:$P142}, ('特殊配信マ"&"スタ'!$A$2:$A142=day)*('特殊配信マスタ'!$B$2:$B142=hour)*('特殊配信マスタ'!$R$2:$R142='特殊配信マスタ'!$S$2:$S142)), {"""","""","""",""""}), combined, VSTACK(list_data, new_data, special_data), FILTER(combined, INDEX(combined, , 1)<>"""", INDEX(combined, , 1)<>0) ), """")"),"フルリモートランキング") -> フルリモートランキング | M23: =IFERROR(__xludf.DUMMYFUNCTION("""COMPUTED_VALUE"""),0.5) -> 0.5 | N23: =IFERROR(__xludf.DUMMYFUNCTION("""COMPUTED_VALUE"""),"R") -> R | P23: =SUM(M23:M32) -> 6.9 | Q23: =IFERROR(__xludf.DUMMYFUNCTION("IFERROR(LET( day, TEXT(Q$1, ""ddd""), hour, LOOKUP(2, 1/($A23<>""""), $A23), type_A, $A$1, list_data, IFERROR(FILTER({'リスト'!$E$4:$F142, 'リスト'!$O$4:$P142}, ('リスト'!$A$4:$A142=day)*('リスト'!$B$4:$B142=hour)*(('リスト'!$G$4:$G142=""毎週配信"")+('リスト'!$G$4:$G14"&"2=type_A))), {"""","""","""",""""}), new_data, IFERROR(FILTER({'新規'!$E$2:$F142, '新規'!$O$2:$P142}, ('新規'!$A$2:$A142=Q$1)*('新規'!$B$2:$B142=hour)), {"""","""","""",""""}), special_data, IFERROR(FILTER({'特殊配信マスタ'!$E$2:$F142, '特殊配信マスタ'!$O$2:$P142}, ('特殊配信マ"&"スタ'!$A$2:$A142=day)*('特殊配信マスタ'!$B$2:$B142=hour)*('特殊配信マスタ'!$R$2:$R142='特殊配信マスタ'!$S$2:$S142)), {"""","""","""",""""}), combined, VSTACK(list_data, new_data, special_data), FILTER(combined, INDEX(combined, , 1)<>"""", INDEX(combined, , 1)<>0) ), """")"),"子育手当") -> 子育手当 | R23: =IFERROR(__xludf.DUMMYFUNCTION("""COMPUTED_VALUE"""),0.6) -> 0.6 | S23: =IFERROR(__xludf.DUMMYFUNCTION("""COMPUTED_VALUE"""),"R") -> R | U23: =SUM(R23:R32) -> 0.6 | V23: =IFERROR(__xludf.DUMMYFUNCTION("IFERROR(LET( day, TEXT(V$1, ""ddd""), hour, LOOKUP(2, 1/($A23<>""""), $A23), type_A, $A$1, list_data, IFERROR(FILTER({'リスト'!$E$4:$F142, 'リスト'!$O$4:$P142}, ('リスト'!$A$4:$A142=day)*('リスト'!$B$4:$B142=hour)*(('リスト'!$G$4:$G142=""毎週配信"")+('リスト'!$G$4:$G14"&"2=type_A))), {"""","""","""",""""}), new_data, IFERROR(FILTER({'新規'!$E$2:$F142, '新規'!$O$2:$P142}, ('新規'!$A$2:$A142=V$1)*('新規'!$B$2:$B142=hour)), {"""","""","""",""""}), special_data, IFERROR(FILTER({'特殊配信マスタ'!$E$2:$F142, '特殊配信マスタ'!$O$2:$P142}, ('特殊配信マ"&"スタ'!$A$2:$A142=day)*('特殊配信マスタ'!$B$2:$B142=hour)*('特殊配信マスタ'!$R$2:$R142='特殊配信マスタ'!$S$2:$S142)), {"""","""","""",""""}), combined, VSTACK(list_data, new_data, special_data), FILTER(combined, INDEX(combined, , 1)<>"""", INDEX(combined, , 1)<>0) ), """")"),"検討中ランキング_事務") -> 検討中ランキング_事務 | W23: =IFERROR(__xludf.DUMMYFUNCTION("""COMPUTED_VALUE"""),0.9) -> 0.9 | X23: =IFERROR(__xludf.DUMMYFUNCTION("""COMPUTED_VALUE"""),"R") -> R | Z23: =SUM(W23:W32) -> 2.9 | AA23: =IFERROR(__xludf.DUMMYFUNCTION("IFERROR(LET( day, TEXT(AA$1, ""ddd""), hour, LOOKUP(2, 1/($A23<>""""), $A23), type_A, $A$1, list_data, IFERROR(FILTER({'リスト'!$E$4:$F142, 'リスト'!$O$4:$P142}, ('リスト'!$A$4:$A142=day)*('リスト'!$B$4:$B142=hour)*(('リスト'!$G$4:$G142=""毎週配信"")+('リスト'!$G$4:$G1"&"42=type_A))), {"""","""","""",""""}), new_data, IFERROR(FILTER({'新規'!$E$2:$F142, '新規'!$O$2:$P142}, ('新規'!$A$2:$A142=AA$1)*('新規'!$B$2:$B142=hour)), {"""","""","""",""""}), special_data, IFERROR(FILTER({'特殊配信マスタ'!$E$2:$F142, '特殊配信マスタ'!$O$2:$P142}, ('特殊配"&"信マスタ'!$A$2:$A142=day)*('特殊配信マスタ'!$B$2:$B142=hour)*('特殊配信マスタ'!$R$2:$R142='特殊配信マスタ'!$S$2:$S142)), {"""","""","""",""""}), combined, VSTACK(list_data, new_data, special_data), FILTER(combined, INDEX(combined, , 1)<>"""", INDEX(combined, , 1)<>0) ), """")"),"語学を活かせる") -> 語学を活かせる | AB23: =IFERROR(__xludf.DUMMYFUNCTION("""COMPUTED_VALUE"""),0.4) -> 0.4 | AC23: =IFERROR(__xludf.DUMMYFUNCTION("""COMPUTED_VALUE"""),"R") -> R | AE23: =SUM(AB23:AB32) -> 0.4 | AF23: =IFERROR(__xludf.DUMMYFUNCTION("IFERROR(LET( day, TEXT(AF$1, ""ddd""), hour, LOOKUP(2, 1/($A23<>""""), $A23), type_A, $A$1, list_data, IFERROR(FILTER({'リスト'!$E$4:$F142, 'リスト'!$O$4:$P142}, ('リスト'!$A$4:$A142=day)*('リスト'!$B$4:$B142=hour)*(('リスト'!$G$4:$G142=""毎週配信"")+('リスト'!$G$4:$G1"&"42=type_A))), {"""","""","""",""""}), new_data, IFERROR(FILTER({'新規'!$E$2:$F142, '新規'!$O$2:$P142}, ('新規'!$A$2:$A142=AF$1)*('新規'!$B$2:$B142=hour)), {"""","""","""",""""}), special_data, IFERROR(FILTER({'特殊配信マスタ'!$E$2:$F142, '特殊配信マスタ'!$O$2:$P142}, ('特殊配"&"信マスタ'!$A$2:$A142=day)*('特殊配信マスタ'!$B$2:$B142=hour)*('特殊配信マスタ'!$R$2:$R142='特殊配信マスタ'!$S$2:$S142)), {"""","""","""",""""}), combined, VSTACK(list_data, new_data, special_data), FILTER(combined, INDEX(combined, , 1)<>"""", INDEX(combined, , 1)<>0) ), """")"),"☆TP部_事務_希望地") -> ☆TP部_事務_希望地 | AG23: =IFERROR(__xludf.DUMMYFUNCTION("""COMPUTED_VALUE"""),3.6) -> 3.6 | AH23: =IFERROR(__xludf.DUMMYFUNCTION("""COMPUTED_VALUE"""),"部") -> 部 | AI23: =IFERROR(__xludf.DUMMYFUNCTION("""COMPUTED_VALUE"""),"石") -> 石 | AJ23: =SUM(AG23:AG32) -> 3.6
B24: =IFERROR(__xludf.DUMMYFUNCTION("""COMPUTED_VALUE"""),"面接1回") -> 面接1回 | C24: =IFERROR(__xludf.DUMMYFUNCTION("""COMPUTED_VALUE"""),1.5) -> 1.5 | D24: =IFERROR(__xludf.DUMMYFUNCTION("""COMPUTED_VALUE"""),"R") -> R | G24: =IFERROR(__xludf.DUMMYFUNCTION("""COMPUTED_VALUE"""),"子育て支援") -> 子育て支援 | H24: =IFERROR(__xludf.DUMMYFUNCTION("""COMPUTED_VALUE"""),0.6) -> 0.6 | I24: =IFERROR(__xludf.DUMMYFUNCTION("""COMPUTED_VALUE"""),"R") -> R | L24: =IFERROR(__xludf.DUMMYFUNCTION("""COMPUTED_VALUE"""),"経験活かせる_営業") -> 経験活かせる_営業 | M24: =IFERROR(__xludf.DUMMYFUNCTION("""COMPUTED_VALUE"""),0.6) -> 0.6 | N24: =IFERROR(__xludf.DUMMYFUNCTION("""COMPUTED_VALUE"""),"R") -> R | V24: =IFERROR(__xludf.DUMMYFUNCTION("""COMPUTED_VALUE"""),"JAD特集") -> JAD特集 | W24: =IFERROR(__xludf.DUMMYFUNCTION("""COMPUTED_VALUE"""),2.0) -> 2
B25: =IFERROR(__xludf.DUMMYFUNCTION("""COMPUTED_VALUE"""),"面接1回_35歳以上") -> 面接1回_35歳以上 | C25: =IFERROR(__xludf.DUMMYFUNCTION("""COMPUTED_VALUE"""),1.0) -> 1 | D25: =IFERROR(__xludf.DUMMYFUNCTION("""COMPUTED_VALUE"""),"R") -> R | G25: =IFERROR(__xludf.DUMMYFUNCTION("""COMPUTED_VALUE"""),"趣味・興味メルマガ_A") -> 趣味・興味メルマガ_A | H25: =IFERROR(__xludf.DUMMYFUNCTION("""COMPUTED_VALUE"""),1.0) -> 1 | I25: =IFERROR(__xludf.DUMMYFUNCTION("""COMPUTED_VALUE"""),"R") -> R | L25: =IFERROR(__xludf.DUMMYFUNCTION("""COMPUTED_VALUE"""),"経験活かせる_事務") -> 経験活かせる_事務 | M25: =IFERROR(__xludf.DUMMYFUNCTION("""COMPUTED_VALUE"""),1.4) -> 1.4 | N25: =IFERROR(__xludf.DUMMYFUNCTION("""COMPUTED_VALUE"""),"R") -> R
L26: =IFERROR(__xludf.DUMMYFUNCTION("""COMPUTED_VALUE"""),"副業OK") -> 副業OK | M26: =IFERROR(__xludf.DUMMYFUNCTION("""COMPUTED_VALUE"""),4.4) -> 4.4 | N26: =IFERROR(__xludf.DUMMYFUNCTION("""COMPUTED_VALUE"""),"R") -> R
A33: =A23+1 -> 11 | B33: =IFERROR(__xludf.DUMMYFUNCTION("IFERROR(LET( day, TEXT(B$1, ""ddd""), hour, LOOKUP(2, 1/($A33<>""""), $A33), type_A, $A$1, list_data, IFERROR(FILTER({'リスト'!$E$4:$F142, 'リスト'!$O$4:$P142}, ('リスト'!$A$4:$A142=day)*('リスト'!$B$4:$B142=hour)*(('リスト'!$G$4:$G142=""毎週配信"")+('リスト'!$G$4:$G14"&"2=type_A))), {"""","""","""",""""}), new_data, IFERROR(FILTER({'新規'!$E$2:$F142, '新規'!$O$2:$P142}, ('新規'!$A$2:$A142=B$1)*('新規'!$B$2:$B142=hour)), {"""","""","""",""""}), special_data, IFERROR(FILTER({'特殊配信マスタ'!$E$2:$F142, '特殊配信マスタ'!$O$2:$P142}, ('特殊配信マ"&"スタ'!$A$2:$A142=day)*('特殊配信マスタ'!$B$2:$B142=hour)*('特殊配信マスタ'!$R$2:$R142='特殊配信マスタ'!$S$2:$S142)), {"""","""","""",""""}), combined, VSTACK(list_data, new_data, special_data), FILTER(combined, INDEX(combined, , 1)<>"""", INDEX(combined, , 1)<>0) ), """")"),"事務（経理）_希望") -> 事務（経理）_希望 | C33: =IFERROR(__xludf.DUMMYFUNCTION("""COMPUTED_VALUE"""),0.5) -> 0.5 | D33: =IFERROR(__xludf.DUMMYFUNCTION("""COMPUTED_VALUE"""),"R") -> R | F33: =SUM(C33:C42) -> 0.5 | G33: =IFERROR(__xludf.DUMMYFUNCTION("IFERROR(LET( day, TEXT(G$1, ""ddd""), hour, LOOKUP(2, 1/($A33<>""""), $A33), type_A, $A$1, list_data, IFERROR(FILTER({'リスト'!$E$4:$F142, 'リスト'!$O$4:$P142}, ('リスト'!$A$4:$A142=day)*('リスト'!$B$4:$B142=hour)*(('リスト'!$G$4:$G142=""毎週配信"")+('リスト'!$G$4:$G14"&"2=type_A))), {"""","""","""",""""}), new_data, IFERROR(FILTER({'新規'!$E$2:$F142, '新規'!$O$2:$P142}, ('新規'!$A$2:$A142=G$1)*('新規'!$B$2:$B142=hour)), {"""","""","""",""""}), special_data, IFERROR(FILTER({'特殊配信マスタ'!$E$2:$F142, '特殊配信マスタ'!$O$2:$P142}, ('特殊配信マ"&"スタ'!$A$2:$A142=day)*('特殊配信マスタ'!$B$2:$B142=hour)*('特殊配信マスタ'!$R$2:$R142='特殊配信マスタ'!$S$2:$S142)), {"""","""","""",""""}), combined, VSTACK(list_data, new_data, special_data), FILTER(combined, INDEX(combined, , 1)<>"""", INDEX(combined, , 1)<>0) ), """")"),"事務（総務・人事）_希望") -> 事務（総務・人事）_希望 | H33: =IFERROR(__xludf.DUMMYFUNCTION("""COMPUTED_VALUE"""),1.1) -> 1.1 | I33: =IFERROR(__xludf.DUMMYFUNCTION("""COMPUTED_VALUE"""),"R") -> R | K33: =SUM(H33:H42) -> 1.1 | L33: =IFERROR(__xludf.DUMMYFUNCTION("IFERROR(LET( day, TEXT(L$1, ""ddd""), hour, LOOKUP(2, 1/($A33<>""""), $A33), type_A, $A$1, list_data, IFERROR(FILTER({'リスト'!$E$4:$F142, 'リスト'!$O$4:$P142}, ('リスト'!$A$4:$A142=day)*('リスト'!$B$4:$B142=hour)*(('リスト'!$G$4:$G142=""毎週配信"")+('リスト'!$G$4:$G14"&"2=type_A))), {"""","""","""",""""}), new_data, IFERROR(FILTER({'新規'!$E$2:$F142, '新規'!$O$2:$P142}, ('新規'!$A$2:$A142=L$1)*('新規'!$B$2:$B142=hour)), {"""","""","""",""""}), special_data, IFERROR(FILTER({'特殊配信マスタ'!$E$2:$F142, '特殊配信マスタ'!$O$2:$P142}, ('特殊配信マ"&"スタ'!$A$2:$A142=day)*('特殊配信マスタ'!$B$2:$B142=hour)*('特殊配信マスタ'!$R$2:$R142='特殊配信マスタ'!$S$2:$S142)), {"""","""","""",""""}), combined, VSTACK(list_data, new_data, special_data), FILTER(combined, INDEX(combined, , 1)<>"""", INDEX(combined, , 1)<>0) ), """")"),"クリエイティブ（Web）_希望") -> クリエイティブ（Web）_希望 | M33: =IFERROR(__xludf.DUMMYFUNCTION("""COMPUTED_VALUE"""),0.4) -> 0.4 | N33: =IFERROR(__xludf.DUMMYFUNCTION("""COMPUTED_VALUE"""),"R") -> R | P33: =SUM(M33:M42) -> 2.9 | Q33: =IFERROR(__xludf.DUMMYFUNCTION("IFERROR(LET( day, TEXT(Q$1, ""ddd""), hour, LOOKUP(2, 1/($A33<>""""), $A33), type_A, $A$1, list_data, IFERROR(FILTER({'リスト'!$E$4:$F142, 'リスト'!$O$4:$P142}, ('リスト'!$A$4:$A142=day)*('リスト'!$B$4:$B142=hour)*(('リスト'!$G$4:$G142=""毎週配信"")+('リスト'!$G$4:$G14"&"2=type_A))), {"""","""","""",""""}), new_data, IFERROR(FILTER({'新規'!$E$2:$F142, '新規'!$O$2:$P142}, ('新規'!$A$2:$A142=Q$1)*('新規'!$B$2:$B142=hour)), {"""","""","""",""""}), special_data, IFERROR(FILTER({'特殊配信マスタ'!$E$2:$F142, '特殊配信マスタ'!$O$2:$P142}, ('特殊配信マ"&"スタ'!$A$2:$A142=day)*('特殊配信マスタ'!$B$2:$B142=hour)*('特殊配信マスタ'!$R$2:$R142='特殊配信マスタ'!$S$2:$S142)), {"""","""","""",""""}), combined, VSTACK(list_data, new_data, special_data), FILTER(combined, INDEX(combined, , 1)<>"""", INDEX(combined, , 1)<>0) ), """")"),"クリエイティブ（その他）_希望") -> クリエイティブ（その他）_希望 | R33: =IFERROR(__xludf.DUMMYFUNCTION("""COMPUTED_VALUE"""),0.3) -> 0.3 | S33: =IFERROR(__xludf.DUMMYFUNCTION("""COMPUTED_VALUE"""),"R") -> R | U33: =SUM(R33:R42) -> 6.5 | V33: =IFERROR(__xludf.DUMMYFUNCTION("IFERROR(LET( day, TEXT(V$1, ""ddd""), hour, LOOKUP(2, 1/($A33<>""""), $A33), type_A, $A$1, list_data, IFERROR(FILTER({'リスト'!$E$4:$F142, 'リスト'!$O$4:$P142}, ('リスト'!$A$4:$A142=day)*('リスト'!$B$4:$B142=hour)*(('リスト'!$G$4:$G142=""毎週配信"")+('リスト'!$G$4:$G14"&"2=type_A))), {"""","""","""",""""}), new_data, IFERROR(FILTER({'新規'!$E$2:$F142, '新規'!$O$2:$P142}, ('新規'!$A$2:$A142=V$1)*('新規'!$B$2:$B142=hour)), {"""","""","""",""""}), special_data, IFERROR(FILTER({'特殊配信マスタ'!$E$2:$F142, '特殊配信マスタ'!$O$2:$P142}, ('特殊配信マ"&"スタ'!$A$2:$A142=day)*('特殊配信マスタ'!$B$2:$B142=hour)*('特殊配信マスタ'!$R$2:$R142='特殊配信マスタ'!$S$2:$S142)), {"""","""","""",""""}), combined, VSTACK(list_data, new_data, special_data), FILTER(combined, INDEX(combined, , 1)<>"""", INDEX(combined, , 1)<>0) ), """")"),"フレックス_ランキング") -> フレックス_ランキング | W33: =IFERROR(__xludf.DUMMYFUNCTION("""COMPUTED_VALUE"""),2.0) -> 2 | X33: =IFERROR(__xludf.DUMMYFUNCTION("""COMPUTED_VALUE"""),"石") -> 石 | Y33: =IFERROR(__xludf.DUMMYFUNCTION("""COMPUTED_VALUE"""),"福") -> 福 | Z33: =SUM(W33:W42) -> 2 | AA33: =IFERROR(__xludf.DUMMYFUNCTION("IFERROR(LET( day, TEXT(AA$1, ""ddd""), hour, LOOKUP(2, 1/($A33<>""""), $A33), type_A, $A$1, list_data, IFERROR(FILTER({'リスト'!$E$4:$F142, 'リスト'!$O$4:$P142}, ('リスト'!$A$4:$A142=day)*('リスト'!$B$4:$B142=hour)*(('リスト'!$G$4:$G142=""毎週配信"")+('リスト'!$G$4:$G1"&"42=type_A))), {"""","""","""",""""}), new_data, IFERROR(FILTER({'新規'!$E$2:$F142, '新規'!$O$2:$P142}, ('新規'!$A$2:$A142=AA$1)*('新規'!$B$2:$B142=hour)), {"""","""","""",""""}), special_data, IFERROR(FILTER({'特殊配信マスタ'!$E$2:$F142, '特殊配信マスタ'!$O$2:$P142}, ('特殊配"&"信マスタ'!$A$2:$A142=day)*('特殊配信マスタ'!$B$2:$B142=hour)*('特殊配信マスタ'!$R$2:$R142='特殊配信マスタ'!$S$2:$S142)), {"""","""","""",""""}), combined, VSTACK(list_data, new_data, special_data), FILTER(combined, INDEX(combined, , 1)<>"""", INDEX(combined, , 1)<>0) ), """")"),"関西単独求人メルマガ_B") -> 関西単独求人メルマガ_B | AB33: =IFERROR(__xludf.DUMMYFUNCTION("""COMPUTED_VALUE"""),0.7) -> 0.7 | AC33: =IFERROR(__xludf.DUMMYFUNCTION("""COMPUTED_VALUE"""),"武") -> 武 | AD33: =IFERROR(__xludf.DUMMYFUNCTION("""COMPUTED_VALUE"""),"部") -> 部 | AE33: =SUM(AB33:AB42) -> 1.7 | AF33: =IFERROR(__xludf.DUMMYFUNCTION("IFERROR(LET( day, TEXT(AF$1, ""ddd""), hour, LOOKUP(2, 1/($A33<>""""), $A33), type_A, $A$1, list_data, IFERROR(FILTER({'リスト'!$E$4:$F142, 'リスト'!$O$4:$P142}, ('リスト'!$A$4:$A142=day)*('リスト'!$B$4:$B142=hour)*(('リスト'!$G$4:$G142=""毎週配信"")+('リスト'!$G$4:$G1"&"42=type_A))), {"""","""","""",""""}), new_data, IFERROR(FILTER({'新規'!$E$2:$F142, '新規'!$O$2:$P142}, ('新規'!$A$2:$A142=AF$1)*('新規'!$B$2:$B142=hour)), {"""","""","""",""""}), special_data, IFERROR(FILTER({'特殊配信マスタ'!$E$2:$F142, '特殊配信マスタ'!$O$2:$P142}, ('特殊配"&"信マスタ'!$A$2:$A142=day)*('特殊配信マスタ'!$B$2:$B142=hour)*('特殊配信マスタ'!$R$2:$R142='特殊配信マスタ'!$S$2:$S142)), {"""","""","""",""""}), combined, VSTACK(list_data, new_data, special_data), FILTER(combined, INDEX(combined, , 1)<>"""", INDEX(combined, , 1)<>0) ), """")"),"クリエイティブ総合ランキング") -> クリエイティブ総合ランキング | AG33: =IFERROR(__xludf.DUMMYFUNCTION("""COMPUTED_VALUE"""),0.8) -> 0.8 | AH33: =IFERROR(__xludf.DUMMYFUNCTION("""COMPUTED_VALUE"""),"R") -> R | AJ33: =SUM(AG33:AG42) -> 1.5
L34: =IFERROR(__xludf.DUMMYFUNCTION("""COMPUTED_VALUE"""),"コロナ禍_事務_首都圏") -> コロナ禍_事務_首都圏 | M34: =IFERROR(__xludf.DUMMYFUNCTION("""COMPUTED_VALUE"""),2.5) -> 2.5 | N34: =IFERROR(__xludf.DUMMYFUNCTION("""COMPUTED_VALUE"""),"R") -> R | Q34: =IFERROR(__xludf.DUMMYFUNCTION("""COMPUTED_VALUE"""),"今週の人気求人ランキング") -> 今週の人気求人ランキング | R34: =IFERROR(__xludf.DUMMYFUNCTION("""COMPUTED_VALUE"""),5.7) -> 5.7 | S34: =IFERROR(__xludf.DUMMYFUNCTION("""COMPUTED_VALUE"""),"R") -> R | AA34: =IFERROR(__xludf.DUMMYFUNCTION("""COMPUTED_VALUE"""),"事務（営業事務）_希望") -> 事務（営業事務）_希望 | AB34: =IFERROR(__xludf.DUMMYFUNCTION("""COMPUTED_VALUE"""),1.0) -> 1 | AC34: =IFERROR(__xludf.DUMMYFUNCTION("""COMPUTED_VALUE"""),"R") -> R | AF34: =IFERROR(__xludf.DUMMYFUNCTION("""COMPUTED_VALUE"""),"関西_未経験リモート_事務") -> 関西_未経験リモート_事務 | AG34: =IFERROR(__xludf.DUMMYFUNCTION("""COMPUTED_VALUE"""),0.7) -> 0.7 | AH34: =IFERROR(__xludf.DUMMYFUNCTION("""COMPUTED_VALUE"""),"R") -> R
Q35: =IFERROR(__xludf.DUMMYFUNCTION("""COMPUTED_VALUE"""),"事務（広報）_希望") -> 事務（広報）_希望 | R35: =IFERROR(__xludf.DUMMYFUNCTION("""COMPUTED_VALUE"""),0.5) -> 0.5 | S35: =IFERROR(__xludf.DUMMYFUNCTION("""COMPUTED_VALUE"""),"R") -> R
A43: =A33+1 -> 12 | B43: =IFERROR(__xludf.DUMMYFUNCTION("IFERROR(LET( day, TEXT(B$1, ""ddd""), hour, LOOKUP(2, 1/($A43<>""""), $A43), type_A, $A$1, list_data, IFERROR(FILTER({'リスト'!$E$4:$F142, 'リスト'!$O$4:$P142}, ('リスト'!$A$4:$A142=day)*('リスト'!$B$4:$B142=hour)*(('リスト'!$G$4:$G142=""毎週配信"")+('リスト'!$G$4:$G14"&"2=type_A))), {"""","""","""",""""}), new_data, IFERROR(FILTER({'新規'!$E$2:$F142, '新規'!$O$2:$P142}, ('新規'!$A$2:$A142=B$1)*('新規'!$B$2:$B142=hour)), {"""","""","""",""""}), special_data, IFERROR(FILTER({'特殊配信マスタ'!$E$2:$F142, '特殊配信マスタ'!$O$2:$P142}, ('特殊配信マ"&"スタ'!$A$2:$A142=day)*('特殊配信マスタ'!$B$2:$B142=hour)*('特殊配信マスタ'!$R$2:$R142='特殊配信マスタ'!$S$2:$S142)), {"""","""","""",""""}), combined, VSTACK(list_data, new_data, special_data), FILTER(combined, INDEX(combined, , 1)<>"""", INDEX(combined, , 1)<>0) ), """")"),"★新着総合_首都圏 A") -> ★新着総合_首都圏 A | C43: =IFERROR(__xludf.DUMMYFUNCTION("""COMPUTED_VALUE"""),5.0) -> 5 | D43: =IFERROR(__xludf.DUMMYFUNCTION("""COMPUTED_VALUE"""),"荒") -> 荒 | E43: =IFERROR(__xludf.DUMMYFUNCTION("""COMPUTED_VALUE"""),"平") -> 平 | F43: =SUM(C43:C52) -> 10.4 | G43: =IFERROR(__xludf.DUMMYFUNCTION("IFERROR(LET( day, TEXT(G$1, ""ddd""), hour, LOOKUP(2, 1/($A43<>""""), $A43), type_A, $A$1, list_data, IFERROR(FILTER({'リスト'!$E$4:$F142, 'リスト'!$O$4:$P142}, ('リスト'!$A$4:$A142=day)*('リスト'!$B$4:$B142=hour)*(('リスト'!$G$4:$G142=""毎週配信"")+('リスト'!$G$4:$G14"&"2=type_A))), {"""","""","""",""""}), new_data, IFERROR(FILTER({'新規'!$E$2:$F142, '新規'!$O$2:$P142}, ('新規'!$A$2:$A142=G$1)*('新規'!$B$2:$B142=hour)), {"""","""","""",""""}), special_data, IFERROR(FILTER({'特殊配信マスタ'!$E$2:$F142, '特殊配信マスタ'!$O$2:$P142}, ('特殊配信マ"&"スタ'!$A$2:$A142=day)*('特殊配信マスタ'!$B$2:$B142=hour)*('特殊配信マスタ'!$R$2:$R142='特殊配信マスタ'!$S$2:$S142)), {"""","""","""",""""}), combined, VSTACK(list_data, new_data, special_data), FILTER(combined, INDEX(combined, , 1)<>"""", INDEX(combined, , 1)<>0) ), """")"),"自己PR不要_リモート未経験_事務") -> 自己PR不要_リモート未経験_事務 | H43: =IFERROR(__xludf.DUMMYFUNCTION("""COMPUTED_VALUE"""),2.5) -> 2.5 | I43: =IFERROR(__xludf.DUMMYFUNCTION("""COMPUTED_VALUE"""),"R") -> R | K43: =SUM(H43:H52) -> 6.7 | L43: =IFERROR(__xludf.DUMMYFUNCTION("IFERROR(LET( day, TEXT(L$1, ""ddd""), hour, LOOKUP(2, 1/($A43<>""""), $A43), type_A, $A$1, list_data, IFERROR(FILTER({'リスト'!$E$4:$F142, 'リスト'!$O$4:$P142}, ('リスト'!$A$4:$A142=day)*('リスト'!$B$4:$B142=hour)*(('リスト'!$G$4:$G142=""毎週配信"")+('リスト'!$G$4:$G14"&"2=type_A))), {"""","""","""",""""}), new_data, IFERROR(FILTER({'新規'!$E$2:$F142, '新規'!$O$2:$P142}, ('新規'!$A$2:$A142=L$1)*('新規'!$B$2:$B142=hour)), {"""","""","""",""""}), special_data, IFERROR(FILTER({'特殊配信マスタ'!$E$2:$F142, '特殊配信マスタ'!$O$2:$P142}, ('特殊配信マ"&"スタ'!$A$2:$A142=day)*('特殊配信マスタ'!$B$2:$B142=hour)*('特殊配信マスタ'!$R$2:$R142='特殊配信マスタ'!$S$2:$S142)), {"""","""","""",""""}), combined, VSTACK(list_data, new_data, special_data), FILTER(combined, INDEX(combined, , 1)<>"""", INDEX(combined, , 1)<>0) ), """")"),"応募ランキング B") -> 応募ランキング B | M43: =IFERROR(__xludf.DUMMYFUNCTION("""COMPUTED_VALUE"""),3.5) -> 3.5 | N43: =IFERROR(__xludf.DUMMYFUNCTION("""COMPUTED_VALUE"""),"R") -> R | P43: =SUM(M43:M52) -> 8.3 | Q43: =IFERROR(__xludf.DUMMYFUNCTION("IFERROR(LET( day, TEXT(Q$1, ""ddd""), hour, LOOKUP(2, 1/($A43<>""""), $A43), type_A, $A$1, list_data, IFERROR(FILTER({'リスト'!$E$4:$F142, 'リスト'!$O$4:$P142}, ('リスト'!$A$4:$A142=day)*('リスト'!$B$4:$B142=hour)*(('リスト'!$G$4:$G142=""毎週配信"")+('リスト'!$G$4:$G14"&"2=type_A))), {"""","""","""",""""}), new_data, IFERROR(FILTER({'新規'!$E$2:$F142, '新規'!$O$2:$P142}, ('新規'!$A$2:$A142=Q$1)*('新規'!$B$2:$B142=hour)), {"""","""","""",""""}), special_data, IFERROR(FILTER({'特殊配信マスタ'!$E$2:$F142, '特殊配信マスタ'!$O$2:$P142}, ('特殊配信マ"&"スタ'!$A$2:$A142=day)*('特殊配信マスタ'!$B$2:$B142=hour)*('特殊配信マスタ'!$R$2:$R142='特殊配信マスタ'!$S$2:$S142)), {"""","""","""",""""}), combined, VSTACK(list_data, new_data, special_data), FILTER(combined, INDEX(combined, , 1)<>"""", INDEX(combined, , 1)<>0) ), """")"),"★新着総合_首都圏 B") -> ★新着総合_首都圏 B | R43: =IFERROR(__xludf.DUMMYFUNCTION("""COMPUTED_VALUE"""),5.0) -> 5 | S43: =IFERROR(__xludf.DUMMYFUNCTION("""COMPUTED_VALUE"""),"荒") -> 荒 | T43: =IFERROR(__xludf.DUMMYFUNCTION("""COMPUTED_VALUE"""),"平") -> 平 | U43: =SUM(R43:R52) -> 10.4 | V43: =IFERROR(__xludf.DUMMYFUNCTION("IFERROR(LET( day, TEXT(V$1, ""ddd""), hour, LOOKUP(2, 1/($A43<>""""), $A43), type_A, $A$1, list_data, IFERROR(FILTER({'リスト'!$E$4:$F142, 'リスト'!$O$4:$P142}, ('リスト'!$A$4:$A142=day)*('リスト'!$B$4:$B142=hour)*(('リスト'!$G$4:$G142=""毎週配信"")+('リスト'!$G$4:$G14"&"2=type_A))), {"""","""","""",""""}), new_data, IFERROR(FILTER({'新規'!$E$2:$F142, '新規'!$O$2:$P142}, ('新規'!$A$2:$A142=V$1)*('新規'!$B$2:$B142=hour)), {"""","""","""",""""}), special_data, IFERROR(FILTER({'特殊配信マスタ'!$E$2:$F142, '特殊配信マスタ'!$O$2:$P142}, ('特殊配信マ"&"スタ'!$A$2:$A142=day)*('特殊配信マスタ'!$B$2:$B142=hour)*('特殊配信マスタ'!$R$2:$R142='特殊配信マスタ'!$S$2:$S142)), {"""","""","""",""""}), combined, VSTACK(list_data, new_data, special_data), FILTER(combined, INDEX(combined, , 1)<>"""", INDEX(combined, , 1)<>0) ), """")"),"高層ビルで働く_首都圏") -> 高層ビルで働く_首都圏 | W43: =IFERROR(__xludf.DUMMYFUNCTION("""COMPUTED_VALUE"""),1.6) -> 1.6 | X43: =IFERROR(__xludf.DUMMYFUNCTION("""COMPUTED_VALUE"""),"部") -> 部 | Y43: =IFERROR(__xludf.DUMMYFUNCTION("""COMPUTED_VALUE"""),"石") -> 石 | Z43: =SUM(W43:W52) -> 3.1 | AA43: =IFERROR(__xludf.DUMMYFUNCTION("IFERROR(LET( day, TEXT(AA$1, ""ddd""), hour, LOOKUP(2, 1/($A43<>""""), $A43), type_A, $A$1, list_data, IFERROR(FILTER({'リスト'!$E$4:$F142, 'リスト'!$O$4:$P142}, ('リスト'!$A$4:$A142=day)*('リスト'!$B$4:$B142=hour)*(('リスト'!$G$4:$G142=""毎週配信"")+('リスト'!$G$4:$G1"&"42=type_A))), {"""","""","""",""""}), new_data, IFERROR(FILTER({'新規'!$E$2:$F142, '新規'!$O$2:$P142}, ('新規'!$A$2:$A142=AA$1)*('新規'!$B$2:$B142=hour)), {"""","""","""",""""}), special_data, IFERROR(FILTER({'特殊配信マスタ'!$E$2:$F142, '特殊配信マスタ'!$O$2:$P142}, ('特殊配"&"信マスタ'!$A$2:$A142=day)*('特殊配信マスタ'!$B$2:$B142=hour)*('特殊配信マスタ'!$R$2:$R142='特殊配信マスタ'!$S$2:$S142)), {"""","""","""",""""}), combined, VSTACK(list_data, new_data, special_data), FILTER(combined, INDEX(combined, , 1)<>"""", INDEX(combined, , 1)<>0) ), """")"),"★ウキポリ[全]") -> ★ウキポリ[全] | AB43: =IFERROR(__xludf.DUMMYFUNCTION("""COMPUTED_VALUE"""),10.0) -> 10 | AC43: =IFERROR(__xludf.DUMMYFUNCTION("""COMPUTED_VALUE"""),"平") -> 平 | AD43: =IFERROR(__xludf.DUMMYFUNCTION("""COMPUTED_VALUE"""),"荒") -> 荒 | AE43: =SUM(AB43:AB52) -> 10 | AF43: =IFERROR(__xludf.DUMMYFUNCTION("IFERROR(LET( day, TEXT(AF$1, ""ddd""), hour, LOOKUP(2, 1/($A43<>""""), $A43), type_A, $A$1, list_data, IFERROR(FILTER({'リスト'!$E$4:$F142, 'リスト'!$O$4:$P142}, ('リスト'!$A$4:$A142=day)*('リスト'!$B$4:$B142=hour)*(('リスト'!$G$4:$G142=""毎週配信"")+('リスト'!$G$4:$G1"&"42=type_A))), {"""","""","""",""""}), new_data, IFERROR(FILTER({'新規'!$E$2:$F142, '新規'!$O$2:$P142}, ('新規'!$A$2:$A142=AF$1)*('新規'!$B$2:$B142=hour)), {"""","""","""",""""}), special_data, IFERROR(FILTER({'特殊配信マスタ'!$E$2:$F142, '特殊配信マスタ'!$O$2:$P142}, ('特殊配"&"信マスタ'!$A$2:$A142=day)*('特殊配信マスタ'!$B$2:$B142=hour)*('特殊配信マスタ'!$R$2:$R142='特殊配信マスタ'!$S$2:$S142)), {"""","""","""",""""}), combined, VSTACK(list_data, new_data, special_data), FILTER(combined, INDEX(combined, , 1)<>"""", INDEX(combined, , 1)<>0) ), """")"),"未経験OK_専門性の高い事務") -> 未経験OK_専門性の高い事務 | AG43: =IFERROR(__xludf.DUMMYFUNCTION("""COMPUTED_VALUE"""),1.4) -> 1.4 | AH43: =IFERROR(__xludf.DUMMYFUNCTION("""COMPUTED_VALUE"""),"部") -> 部 | AI43: =IFERROR(__xludf.DUMMYFUNCTION("""COMPUTED_VALUE"""),"石") -> 石 | AJ43: =SUM(AG43:AG52) -> 8.4
B44: =IFERROR(__xludf.DUMMYFUNCTION("""COMPUTED_VALUE"""),"★新着総合_西日本 A") -> ★新着総合_西日本 A | C44: =IFERROR(__xludf.DUMMYFUNCTION("""COMPUTED_VALUE"""),2.9) -> 2.9 | D44: =IFERROR(__xludf.DUMMYFUNCTION("""COMPUTED_VALUE"""),"荒") -> 荒 | E44: =IFERROR(__xludf.DUMMYFUNCTION("""COMPUTED_VALUE"""),"平") -> 平 | G44: =IFERROR(__xludf.DUMMYFUNCTION("""COMPUTED_VALUE"""),"自己PR不要_リモート未経験_営業") -> 自己PR不要_リモート未経験_営業 | H44: =IFERROR(__xludf.DUMMYFUNCTION("""COMPUTED_VALUE"""),0.3) -> 0.3 | I44: =IFERROR(__xludf.DUMMYFUNCTION("""COMPUTED_VALUE"""),"R") -> R | L44: =IFERROR(__xludf.DUMMYFUNCTION("""COMPUTED_VALUE"""),"応募ランキングB_全国") -> 応募ランキングB_全国 | M44: =IFERROR(__xludf.DUMMYFUNCTION("""COMPUTED_VALUE"""),3.4) -> 3.4 | N44: =IFERROR(__xludf.DUMMYFUNCTION("""COMPUTED_VALUE"""),"R") -> R | Q44: =IFERROR(__xludf.DUMMYFUNCTION("""COMPUTED_VALUE"""),"★新着総合_西日本 B") -> ★新着総合_西日本 B | R44: =IFERROR(__xludf.DUMMYFUNCTION("""COMPUTED_VALUE"""),2.9) -> 2.9 | S44: =IFERROR(__xludf.DUMMYFUNCTION("""COMPUTED_VALUE"""),"荒") -> 荒 | T44: =IFERROR(__xludf.DUMMYFUNCTION("""COMPUTED_VALUE"""),"平") -> 平 | V44: =IFERROR(__xludf.DUMMYFUNCTION("""COMPUTED_VALUE"""),"高層ビルで働く_大阪") -> 高層ビルで働く_大阪 | W44: =IFERROR(__xludf.DUMMYFUNCTION("""COMPUTED_VALUE"""),0.5) -> 0.5 | X44: =IFERROR(__xludf.DUMMYFUNCTION("""COMPUTED_VALUE"""),"部") -> 部 | Y44: =IFERROR(__xludf.DUMMYFUNCTION("""COMPUTED_VALUE"""),"石") -> 石 | AF44: =IFERROR(__xludf.DUMMYFUNCTION("""COMPUTED_VALUE"""),"★納品対策") -> ★納品対策 | AG44: =IFERROR(__xludf.DUMMYFUNCTION("""COMPUTED_VALUE"""),7.0) -> 7 | AH44: =IFERROR(__xludf.DUMMYFUNCTION("""COMPUTED_VALUE"""),"平") -> 平 | AI44: =IFERROR(__xludf.DUMMYFUNCTION("""COMPUTED_VALUE"""),"荒") -> 荒
B45: =IFERROR(__xludf.DUMMYFUNCTION("""COMPUTED_VALUE"""),"★新着総合_東海 A") -> ★新着総合_東海 A | C45: =IFERROR(__xludf.DUMMYFUNCTION("""COMPUTED_VALUE"""),1.0) -> 1 | D45: =IFERROR(__xludf.DUMMYFUNCTION("""COMPUTED_VALUE"""),"荒") -> 荒 | E45: =IFERROR(__xludf.DUMMYFUNCTION("""COMPUTED_VALUE"""),"平") -> 平 | G45: =IFERROR(__xludf.DUMMYFUNCTION("""COMPUTED_VALUE"""),"自己PR不要_残業無_未経験_販サ") -> 自己PR不要_残業無_未経験_販サ | H45: =IFERROR(__xludf.DUMMYFUNCTION("""COMPUTED_VALUE"""),0.3) -> 0.3 | I45: =IFERROR(__xludf.DUMMYFUNCTION("""COMPUTED_VALUE"""),"R") -> R | L45: =IFERROR(__xludf.DUMMYFUNCTION("""COMPUTED_VALUE"""),"丸の内・大手町・有楽町_残業少_事務 ") -> 丸の内・大手町・有楽町_残業少_事務 | M45: =IFERROR(__xludf.DUMMYFUNCTION("""COMPUTED_VALUE"""),0.9) -> 0.9 | N45: =IFERROR(__xludf.DUMMYFUNCTION("""COMPUTED_VALUE"""),"R") -> R | Q45: =IFERROR(__xludf.DUMMYFUNCTION("""COMPUTED_VALUE"""),"★新着総合_東海 B") -> ★新着総合_東海 B | R45: =IFERROR(__xludf.DUMMYFUNCTION("""COMPUTED_VALUE"""),1.0) -> 1 | S45: =IFERROR(__xludf.DUMMYFUNCTION("""COMPUTED_VALUE"""),"荒") -> 荒 | T45: =IFERROR(__xludf.DUMMYFUNCTION("""COMPUTED_VALUE"""),"平") -> 平 | V45: =IFERROR(__xludf.DUMMYFUNCTION("""COMPUTED_VALUE"""),"趣味・興味メルマガ_B") -> 趣味・興味メルマガ_B | W45: =IFERROR(__xludf.DUMMYFUNCTION("""COMPUTED_VALUE"""),1.0) -> 1 | X45: =IFERROR(__xludf.DUMMYFUNCTION("""COMPUTED_VALUE"""),"R") -> R
B46: =IFERROR(__xludf.DUMMYFUNCTION("""COMPUTED_VALUE"""),"★新着総合_北海道・東北 A") -> ★新着総合_北海道・東北 A | C46: =IFERROR(__xludf.DUMMYFUNCTION("""COMPUTED_VALUE"""),0.8) -> 0.8 | D46: =IFERROR(__xludf.DUMMYFUNCTION("""COMPUTED_VALUE"""),"荒") -> 荒 | E46: =IFERROR(__xludf.DUMMYFUNCTION("""COMPUTED_VALUE"""),"平") -> 平 | G46: =IFERROR(__xludf.DUMMYFUNCTION("""COMPUTED_VALUE"""),"自己PR不要_リモート未経験_エンジニア") -> 自己PR不要_リモート未経験_エンジニア | H46: =IFERROR(__xludf.DUMMYFUNCTION("""COMPUTED_VALUE"""),0.2) -> 0.2 | I46: =IFERROR(__xludf.DUMMYFUNCTION("""COMPUTED_VALUE"""),"R") -> R | L46: =IFERROR(__xludf.DUMMYFUNCTION("""COMPUTED_VALUE"""),"資格活かせる_簿記") -> 資格活かせる_簿記 | M46: =IFERROR(__xludf.DUMMYFUNCTION("""COMPUTED_VALUE"""),0.3) -> 0.3 | N46: =IFERROR(__xludf.DUMMYFUNCTION("""COMPUTED_VALUE"""),"R") -> R | Q46: =IFERROR(__xludf.DUMMYFUNCTION("""COMPUTED_VALUE"""),"★新着総合_北海道・東北 B") -> ★新着総合_北海道・東北 B | R46: =IFERROR(__xludf.DUMMYFUNCTION("""COMPUTED_VALUE"""),0.8) -> 0.8 | S46: =IFERROR(__xludf.DUMMYFUNCTION("""COMPUTED_VALUE"""),"荒") -> 荒 | T46: =IFERROR(__xludf.DUMMYFUNCTION("""COMPUTED_VALUE"""),"平") -> 平
B47: =IFERROR(__xludf.DUMMYFUNCTION("""COMPUTED_VALUE"""),"★新着総合_北関東・甲信越・北陸 A") -> ★新着総合_北関東・甲信越・北陸 A | C47: =IFERROR(__xludf.DUMMYFUNCTION("""COMPUTED_VALUE"""),0.7) -> 0.7 | D47: =IFERROR(__xludf.DUMMYFUNCTION("""COMPUTED_VALUE"""),"荒") -> 荒 | E47: =IFERROR(__xludf.DUMMYFUNCTION("""COMPUTED_VALUE"""),"平") -> 平 | G47: =IFERROR(__xludf.DUMMYFUNCTION("""COMPUTED_VALUE"""),"休日120日_就業中_関西") -> 休日120日_就業中_関西 | H47: =IFERROR(__xludf.DUMMYFUNCTION("""COMPUTED_VALUE"""),0.7) -> 0.7 | I47: =IFERROR(__xludf.DUMMYFUNCTION("""COMPUTED_VALUE"""),"R") -> R | L47: =IFERROR(__xludf.DUMMYFUNCTION("""COMPUTED_VALUE"""),"新規会員向け_自己PR不要_求人特集") -> 新規会員向け_自己PR不要_求人特集 | M47: =IFERROR(__xludf.DUMMYFUNCTION("""COMPUTED_VALUE"""),0.2) -> 0.2 | N47: =IFERROR(__xludf.DUMMYFUNCTION("""COMPUTED_VALUE"""),"R") -> R | Q47: =IFERROR(__xludf.DUMMYFUNCTION("""COMPUTED_VALUE"""),"★新着総合_北関東・甲信越・北陸 B") -> ★新着総合_北関東・甲信越・北陸 B | R47: =IFERROR(__xludf.DUMMYFUNCTION("""COMPUTED_VALUE"""),0.7) -> 0.7 | S47: =IFERROR(__xludf.DUMMYFUNCTION("""COMPUTED_VALUE"""),"荒") -> 荒 | T47: =IFERROR(__xludf.DUMMYFUNCTION("""COMPUTED_VALUE"""),"平") -> 平
G48: =IFERROR(__xludf.DUMMYFUNCTION("""COMPUTED_VALUE"""),"休日120日_未就業") -> 休日120日_未就業 | H48: =IFERROR(__xludf.DUMMYFUNCTION("""COMPUTED_VALUE"""),0.7) -> 0.7 | I48: =IFERROR(__xludf.DUMMYFUNCTION("""COMPUTED_VALUE"""),"R") -> R
G49: =IFERROR(__xludf.DUMMYFUNCTION("""COMPUTED_VALUE"""),"5月入社可能") -> 5月入社可能 | H49: =IFERROR(__xludf.DUMMYFUNCTION("""COMPUTED_VALUE"""),2.0) -> 2 | I49: =IFERROR(__xludf.DUMMYFUNCTION("""COMPUTED_VALUE"""),"石") -> 石 | J49: =IFERROR(__xludf.DUMMYFUNCTION("""COMPUTED_VALUE"""),"部") -> 部
A53: =A43+1 -> 13 | B53: =IFERROR(__xludf.DUMMYFUNCTION("IFERROR(LET( day, TEXT(B$1, ""ddd""), hour, LOOKUP(2, 1/($A53<>""""), $A53), type_A, $A$1, list_data, IFERROR(FILTER({'リスト'!$E$4:$F142, 'リスト'!$O$4:$P142}, ('リスト'!$A$4:$A142=day)*('リスト'!$B$4:$B142=hour)*(('リスト'!$G$4:$G142=""毎週配信"")+('リスト'!$G$4:$G14"&"2=type_A))), {"""","""","""",""""}), new_data, IFERROR(FILTER({'新規'!$E$2:$F142, '新規'!$O$2:$P142}, ('新規'!$A$2:$A142=B$1)*('新規'!$B$2:$B142=hour)), {"""","""","""",""""}), special_data, IFERROR(FILTER({'特殊配信マスタ'!$E$2:$F142, '特殊配信マスタ'!$O$2:$P142}, ('特殊配信マ"&"スタ'!$A$2:$A142=day)*('特殊配信マスタ'!$B$2:$B142=hour)*('特殊配信マスタ'!$R$2:$R142='特殊配信マスタ'!$S$2:$S142)), {"""","""","""",""""}), combined, VSTACK(list_data, new_data, special_data), FILTER(combined, INDEX(combined, , 1)<>"""", INDEX(combined, , 1)<>0) ), """")"),"") | F53: =SUM(C53:C62) -> 0 | G53: =IFERROR(__xludf.DUMMYFUNCTION("IFERROR(LET( day, TEXT(G$1, ""ddd""), hour, LOOKUP(2, 1/($A53<>""""), $A53), type_A, $A$1, list_data, IFERROR(FILTER({'リスト'!$E$4:$F142, 'リスト'!$O$4:$P142}, ('リスト'!$A$4:$A142=day)*('リスト'!$B$4:$B142=hour)*(('リスト'!$G$4:$G142=""毎週配信"")+('リスト'!$G$4:$G14"&"2=type_A))), {"""","""","""",""""}), new_data, IFERROR(FILTER({'新規'!$E$2:$F142, '新規'!$O$2:$P142}, ('新規'!$A$2:$A142=G$1)*('新規'!$B$2:$B142=hour)), {"""","""","""",""""}), special_data, IFERROR(FILTER({'特殊配信マスタ'!$E$2:$F142, '特殊配信マスタ'!$O$2:$P142}, ('特殊配信マ"&"スタ'!$A$2:$A142=day)*('特殊配信マスタ'!$B$2:$B142=hour)*('特殊配信マスタ'!$R$2:$R142='特殊配信マスタ'!$S$2:$S142)), {"""","""","""",""""}), combined, VSTACK(list_data, new_data, special_data), FILTER(combined, INDEX(combined, , 1)<>"""", INDEX(combined, , 1)<>0) ), """")"),"◇掲載終了前+UP A") -> ◇掲載終了前+UP A | H53: =IFERROR(__xludf.DUMMYFUNCTION("""COMPUTED_VALUE"""),2.5) -> 2.5 | I53: =IFERROR(__xludf.DUMMYFUNCTION("""COMPUTED_VALUE"""),"平") -> 平 | J53: =IFERROR(__xludf.DUMMYFUNCTION("""COMPUTED_VALUE"""),"内") -> 内 | K53: =SUM(H53:H62) -> 4.9 | L53: =IFERROR(__xludf.DUMMYFUNCTION("IFERROR(LET( day, TEXT(L$1, ""ddd""), hour, LOOKUP(2, 1/($A53<>""""), $A53), type_A, $A$1, list_data, IFERROR(FILTER({'リスト'!$E$4:$F142, 'リスト'!$O$4:$P142}, ('リスト'!$A$4:$A142=day)*('リスト'!$B$4:$B142=hour)*(('リスト'!$G$4:$G142=""毎週配信"")+('リスト'!$G$4:$G14"&"2=type_A))), {"""","""","""",""""}), new_data, IFERROR(FILTER({'新規'!$E$2:$F142, '新規'!$O$2:$P142}, ('新規'!$A$2:$A142=L$1)*('新規'!$B$2:$B142=hour)), {"""","""","""",""""}), special_data, IFERROR(FILTER({'特殊配信マスタ'!$E$2:$F142, '特殊配信マスタ'!$O$2:$P142}, ('特殊配信マ"&"スタ'!$A$2:$A142=day)*('特殊配信マスタ'!$B$2:$B142=hour)*('特殊配信マスタ'!$R$2:$R142='特殊配信マスタ'!$S$2:$S142)), {"""","""","""",""""}), combined, VSTACK(list_data, new_data, special_data), FILTER(combined, INDEX(combined, , 1)<>"""", INDEX(combined, , 1)<>0) ), """")"),"☆TP部_事務_現住所") -> ☆TP部_事務_現住所 | M53: =IFERROR(__xludf.DUMMYFUNCTION("""COMPUTED_VALUE"""),2.4) -> 2.4 | N53: =IFERROR(__xludf.DUMMYFUNCTION("""COMPUTED_VALUE"""),"部") -> 部 | O53: =IFERROR(__xludf.DUMMYFUNCTION("""COMPUTED_VALUE"""),"石") -> 石 | P53: =SUM(M53:M62) -> 2.4 | Q53: =IFERROR(__xludf.DUMMYFUNCTION("IFERROR(LET( day, TEXT(Q$1, ""ddd""), hour, LOOKUP(2, 1/($A53<>""""), $A53), type_A, $A$1, list_data, IFERROR(FILTER({'リスト'!$E$4:$F142, 'リスト'!$O$4:$P142}, ('リスト'!$A$4:$A142=day)*('リスト'!$B$4:$B142=hour)*(('リスト'!$G$4:$G142=""毎週配信"")+('リスト'!$G$4:$G14"&"2=type_A))), {"""","""","""",""""}), new_data, IFERROR(FILTER({'新規'!$E$2:$F142, '新規'!$O$2:$P142}, ('新規'!$A$2:$A142=Q$1)*('新規'!$B$2:$B142=hour)), {"""","""","""",""""}), special_data, IFERROR(FILTER({'特殊配信マスタ'!$E$2:$F142, '特殊配信マスタ'!$O$2:$P142}, ('特殊配信マ"&"スタ'!$A$2:$A142=day)*('特殊配信マスタ'!$B$2:$B142=hour)*('特殊配信マスタ'!$R$2:$R142='特殊配信マスタ'!$S$2:$S142)), {"""","""","""",""""}), combined, VSTACK(list_data, new_data, special_data), FILTER(combined, INDEX(combined, , 1)<>"""", INDEX(combined, , 1)<>0) ), """")"),"外部人気求人ランキング") -> 外部人気求人ランキング | R53: =IFERROR(__xludf.DUMMYFUNCTION("""COMPUTED_VALUE"""),1.4) -> 1.4 | S53: =IFERROR(__xludf.DUMMYFUNCTION("""COMPUTED_VALUE"""),"石") -> 石 | T53: =IFERROR(__xludf.DUMMYFUNCTION("""COMPUTED_VALUE"""),"部") -> 部 | U53: =SUM(R53:R62) -> 1.4 | V53: =IFERROR(__xludf.DUMMYFUNCTION("IFERROR(LET( day, TEXT(V$1, ""ddd""), hour, LOOKUP(2, 1/($A53<>""""), $A53), type_A, $A$1, list_data, IFERROR(FILTER({'リスト'!$E$4:$F142, 'リスト'!$O$4:$P142}, ('リスト'!$A$4:$A142=day)*('リスト'!$B$4:$B142=hour)*(('リスト'!$G$4:$G142=""毎週配信"")+('リスト'!$G$4:$G14"&"2=type_A))), {"""","""","""",""""}), new_data, IFERROR(FILTER({'新規'!$E$2:$F142, '新規'!$O$2:$P142}, ('新規'!$A$2:$A142=V$1)*('新規'!$B$2:$B142=hour)), {"""","""","""",""""}), special_data, IFERROR(FILTER({'特殊配信マスタ'!$E$2:$F142, '特殊配信マスタ'!$O$2:$P142}, ('特殊配信マ"&"スタ'!$A$2:$A142=day)*('特殊配信マスタ'!$B$2:$B142=hour)*('特殊配信マスタ'!$R$2:$R142='特殊配信マスタ'!$S$2:$S142)), {"""","""","""",""""}), combined, VSTACK(list_data, new_data, special_data), FILTER(combined, INDEX(combined, , 1)<>"""", INDEX(combined, , 1)<>0) ), """")"),"ランキング_営業（キャリアカウンセラー）_希望") -> ランキング_営業（キャリアカウンセラー）_希望 | W53: =IFERROR(__xludf.DUMMYFUNCTION("""COMPUTED_VALUE"""),0.3) -> 0.3 | X53: =IFERROR(__xludf.DUMMYFUNCTION("""COMPUTED_VALUE"""),"R") -> R | Z53: =SUM(W53:W62) -> 1.2 | AA53: =IFERROR(__xludf.DUMMYFUNCTION("IFERROR(LET( day, TEXT(AA$1, ""ddd""), hour, LOOKUP(2, 1/($A53<>""""), $A53), type_A, $A$1, list_data, IFERROR(FILTER({'リスト'!$E$4:$F142, 'リスト'!$O$4:$P142}, ('リスト'!$A$4:$A142=day)*('リスト'!$B$4:$B142=hour)*(('リスト'!$G$4:$G142=""毎週配信"")+('リスト'!$G$4:$G1"&"42=type_A))), {"""","""","""",""""}), new_data, IFERROR(FILTER({'新規'!$E$2:$F142, '新規'!$O$2:$P142}, ('新規'!$A$2:$A142=AA$1)*('新規'!$B$2:$B142=hour)), {"""","""","""",""""}), special_data, IFERROR(FILTER({'特殊配信マスタ'!$E$2:$F142, '特殊配信マスタ'!$O$2:$P142}, ('特殊配"&"信マスタ'!$A$2:$A142=day)*('特殊配信マスタ'!$B$2:$B142=hour)*('特殊配信マスタ'!$R$2:$R142='特殊配信マスタ'!$S$2:$S142)), {"""","""","""",""""}), combined, VSTACK(list_data, new_data, special_data), FILTER(combined, INDEX(combined, , 1)<>"""", INDEX(combined, , 1)<>0) ), """")"),"関西_フルリモート_求人特集") -> 関西_フルリモート_求人特集 | AB53: =IFERROR(__xludf.DUMMYFUNCTION("""COMPUTED_VALUE"""),1.6) -> 1.6 | AC53: =IFERROR(__xludf.DUMMYFUNCTION("""COMPUTED_VALUE"""),"部") -> 部 | AD53: =IFERROR(__xludf.DUMMYFUNCTION("""COMPUTED_VALUE"""),"石") -> 石 | AE53: =SUM(AB53:AB62) -> 3.7 | AF53: =IFERROR(__xludf.DUMMYFUNCTION("IFERROR(LET( day, TEXT(AF$1, ""ddd""), hour, LOOKUP(2, 1/($A53<>""""), $A53), type_A, $A$1, list_data, IFERROR(FILTER({'リスト'!$E$4:$F142, 'リスト'!$O$4:$P142}, ('リスト'!$A$4:$A142=day)*('リスト'!$B$4:$B142=hour)*(('リスト'!$G$4:$G142=""毎週配信"")+('リスト'!$G$4:$G1"&"42=type_A))), {"""","""","""",""""}), new_data, IFERROR(FILTER({'新規'!$E$2:$F142, '新規'!$O$2:$P142}, ('新規'!$A$2:$A142=AF$1)*('新規'!$B$2:$B142=hour)), {"""","""","""",""""}), special_data, IFERROR(FILTER({'特殊配信マスタ'!$E$2:$F142, '特殊配信マスタ'!$O$2:$P142}, ('特殊配"&"信マスタ'!$A$2:$A142=day)*('特殊配信マスタ'!$B$2:$B142=hour)*('特殊配信マスタ'!$R$2:$R142='特殊配信マスタ'!$S$2:$S142)), {"""","""","""",""""}), combined, VSTACK(list_data, new_data, special_data), FILTER(combined, INDEX(combined, , 1)<>"""", INDEX(combined, , 1)<>0) ), """")"),"リモートワーク B") -> リモートワーク B | AG53: =IFERROR(__xludf.DUMMYFUNCTION("""COMPUTED_VALUE"""),2.4) -> 2.4 | AH53: =IFERROR(__xludf.DUMMYFUNCTION("""COMPUTED_VALUE"""),"R") -> R | AJ53: =SUM(AG53:AG62) -> 2.7
G54: =IFERROR(__xludf.DUMMYFUNCTION("""COMPUTED_VALUE"""),"◇掲載終了前+UP_35歳以上 A") -> ◇掲載終了前+UP_35歳以上 A | H54: =IFERROR(__xludf.DUMMYFUNCTION("""COMPUTED_VALUE"""),1.0) -> 1 | I54: =IFERROR(__xludf.DUMMYFUNCTION("""COMPUTED_VALUE"""),"平") -> 平 | J54: =IFERROR(__xludf.DUMMYFUNCTION("""COMPUTED_VALUE"""),"内") -> 内 | V54: =IFERROR(__xludf.DUMMYFUNCTION("""COMPUTED_VALUE"""),"ランキング_事務（総務・人事）_希望") -> ランキング_事務（総務・人事）_希望 | W54: =IFERROR(__xludf.DUMMYFUNCTION("""COMPUTED_VALUE"""),0.9) -> 0.9 | X54: =IFERROR(__xludf.DUMMYFUNCTION("""COMPUTED_VALUE"""),"R") -> R | AA54: =IFERROR(__xludf.DUMMYFUNCTION("""COMPUTED_VALUE"""),"フルリモート_35歳以上") -> フルリモート_35歳以上 | AB54: =IFERROR(__xludf.DUMMYFUNCTION("""COMPUTED_VALUE"""),2.1) -> 2.1 | AC54: =IFERROR(__xludf.DUMMYFUNCTION("""COMPUTED_VALUE"""),"R") -> R | AF54: =IFERROR(__xludf.DUMMYFUNCTION("""COMPUTED_VALUE"""),"美容業界×事務_希望") -> 美容業界×事務_希望 | AG54: =IFERROR(__xludf.DUMMYFUNCTION("""COMPUTED_VALUE"""),0.3) -> 0.3 | AH54: =IFERROR(__xludf.DUMMYFUNCTION("""COMPUTED_VALUE"""),"R") -> R
G55: =IFERROR(__xludf.DUMMYFUNCTION("""COMPUTED_VALUE"""),"◇掲載終了前+UP_関西 A") -> ◇掲載終了前+UP_関西 A | H55: =IFERROR(__xludf.DUMMYFUNCTION("""COMPUTED_VALUE"""),1.0) -> 1 | I55: =IFERROR(__xludf.DUMMYFUNCTION("""COMPUTED_VALUE"""),"平") -> 平 | J55: =IFERROR(__xludf.DUMMYFUNCTION("""COMPUTED_VALUE"""),"内") -> 内
G56: =IFERROR(__xludf.DUMMYFUNCTION("""COMPUTED_VALUE"""),"関西単独求人メルマガ_A") -> 関西単独求人メルマガ_A | H56: =IFERROR(__xludf.DUMMYFUNCTION("""COMPUTED_VALUE"""),0.4) -> 0.4 | I56: =IFERROR(__xludf.DUMMYFUNCTION("""COMPUTED_VALUE"""),"武") -> 武 | J56: =IFERROR(__xludf.DUMMYFUNCTION("""COMPUTED_VALUE"""),"部") -> 部
A63: =A53+1 -> 14 | B63: =IFERROR(__xludf.DUMMYFUNCTION("IFERROR(LET( day, TEXT(B$1, ""ddd""), hour, LOOKUP(2, 1/($A63<>""""), $A63), type_A, $A$1, list_data, IFERROR(FILTER({'リスト'!$E$4:$F142, 'リスト'!$O$4:$P142}, ('リスト'!$A$4:$A142=day)*('リスト'!$B$4:$B142=hour)*(('リスト'!$G$4:$G142=""毎週配信"")+('リスト'!$G$4:$G14"&"2=type_A))), {"""","""","""",""""}), new_data, IFERROR(FILTER({'新規'!$E$2:$F142, '新規'!$O$2:$P142}, ('新規'!$A$2:$A142=B$1)*('新規'!$B$2:$B142=hour)), {"""","""","""",""""}), special_data, IFERROR(FILTER({'特殊配信マスタ'!$E$2:$F142, '特殊配信マスタ'!$O$2:$P142}, ('特殊配信マ"&"スタ'!$A$2:$A142=day)*('特殊配信マスタ'!$B$2:$B142=hour)*('特殊配信マスタ'!$R$2:$R142='特殊配信マスタ'!$S$2:$S142)), {"""","""","""",""""}), combined, VSTACK(list_data, new_data, special_data), FILTER(combined, INDEX(combined, , 1)<>"""", INDEX(combined, , 1)<>0) ), """")"),"福祉事務") -> 福祉事務 | C63: =IFERROR(__xludf.DUMMYFUNCTION("""COMPUTED_VALUE"""),1.2) -> 1.2 | D63: =IFERROR(__xludf.DUMMYFUNCTION("""COMPUTED_VALUE"""),"R") -> R | F63: =SUM(C63:C72) -> 4.2 | G63: =IFERROR(__xludf.DUMMYFUNCTION("IFERROR(LET( day, TEXT(G$1, ""ddd""), hour, LOOKUP(2, 1/($A63<>""""), $A63), type_A, $A$1, list_data, IFERROR(FILTER({'リスト'!$E$4:$F142, 'リスト'!$O$4:$P142}, ('リスト'!$A$4:$A142=day)*('リスト'!$B$4:$B142=hour)*(('リスト'!$G$4:$G142=""毎週配信"")+('リスト'!$G$4:$G14"&"2=type_A))), {"""","""","""",""""}), new_data, IFERROR(FILTER({'新規'!$E$2:$F142, '新規'!$O$2:$P142}, ('新規'!$A$2:$A142=G$1)*('新規'!$B$2:$B142=hour)), {"""","""","""",""""}), special_data, IFERROR(FILTER({'特殊配信マスタ'!$E$2:$F142, '特殊配信マスタ'!$O$2:$P142}, ('特殊配信マ"&"スタ'!$A$2:$A142=day)*('特殊配信マスタ'!$B$2:$B142=hour)*('特殊配信マスタ'!$R$2:$R142='特殊配信マスタ'!$S$2:$S142)), {"""","""","""",""""}), combined, VSTACK(list_data, new_data, special_data), FILTER(combined, INDEX(combined, , 1)<>"""", INDEX(combined, , 1)<>0) ), """")"),"") | K63: =SUM(H63:H72) -> 0 | L63: =IFERROR(__xludf.DUMMYFUNCTION("IFERROR(LET( day, TEXT(L$1, ""ddd""), hour, LOOKUP(2, 1/($A63<>""""), $A63), type_A, $A$1, list_data, IFERROR(FILTER({'リスト'!$E$4:$F142, 'リスト'!$O$4:$P142}, ('リスト'!$A$4:$A142=day)*('リスト'!$B$4:$B142=hour)*(('リスト'!$G$4:$G142=""毎週配信"")+('リスト'!$G$4:$G14"&"2=type_A))), {"""","""","""",""""}), new_data, IFERROR(FILTER({'新規'!$E$2:$F142, '新規'!$O$2:$P142}, ('新規'!$A$2:$A142=L$1)*('新規'!$B$2:$B142=hour)), {"""","""","""",""""}), special_data, IFERROR(FILTER({'特殊配信マスタ'!$E$2:$F142, '特殊配信マスタ'!$O$2:$P142}, ('特殊配信マ"&"スタ'!$A$2:$A142=day)*('特殊配信マスタ'!$B$2:$B142=hour)*('特殊配信マスタ'!$R$2:$R142='特殊配信マスタ'!$S$2:$S142)), {"""","""","""",""""}), combined, VSTACK(list_data, new_data, special_data), FILTER(combined, INDEX(combined, , 1)<>"""", INDEX(combined, , 1)<>0) ), """")"),"リモートワーク A_35歳以上") -> リモートワーク A_35歳以上 | M63: =IFERROR(__xludf.DUMMYFUNCTION("""COMPUTED_VALUE"""),1.1) -> 1.1 | N63: =IFERROR(__xludf.DUMMYFUNCTION("""COMPUTED_VALUE"""),"R") -> R | P63: =SUM(M63:M72) -> 2.3 | Q63: =IFERROR(__xludf.DUMMYFUNCTION("IFERROR(LET( day, TEXT(Q$1, ""ddd""), hour, LOOKUP(2, 1/($A63<>""""), $A63), type_A, $A$1, list_data, IFERROR(FILTER({'リスト'!$E$4:$F142, 'リスト'!$O$4:$P142}, ('リスト'!$A$4:$A142=day)*('リスト'!$B$4:$B142=hour)*(('リスト'!$G$4:$G142=""毎週配信"")+('リスト'!$G$4:$G14"&"2=type_A))), {"""","""","""",""""}), new_data, IFERROR(FILTER({'新規'!$E$2:$F142, '新規'!$O$2:$P142}, ('新規'!$A$2:$A142=Q$1)*('新規'!$B$2:$B142=hour)), {"""","""","""",""""}), special_data, IFERROR(FILTER({'特殊配信マスタ'!$E$2:$F142, '特殊配信マスタ'!$O$2:$P142}, ('特殊配信マ"&"スタ'!$A$2:$A142=day)*('特殊配信マスタ'!$B$2:$B142=hour)*('特殊配信マスタ'!$R$2:$R142='特殊配信マスタ'!$S$2:$S142)), {"""","""","""",""""}), combined, VSTACK(list_data, new_data, special_data), FILTER(combined, INDEX(combined, , 1)<>"""", INDEX(combined, , 1)<>0) ), """")"),"フルリモート_全国") -> フルリモート_全国 | R63: =IFERROR(__xludf.DUMMYFUNCTION("""COMPUTED_VALUE"""),3.7) -> 3.7 | S63: =IFERROR(__xludf.DUMMYFUNCTION("""COMPUTED_VALUE"""),"R") -> R | U63: =SUM(R63:R72) -> 3.7 | V63: =IFERROR(__xludf.DUMMYFUNCTION("IFERROR(LET( day, TEXT(V$1, ""ddd""), hour, LOOKUP(2, 1/($A63<>""""), $A63), type_A, $A$1, list_data, IFERROR(FILTER({'リスト'!$E$4:$F142, 'リスト'!$O$4:$P142}, ('リスト'!$A$4:$A142=day)*('リスト'!$B$4:$B142=hour)*(('リスト'!$G$4:$G142=""毎週配信"")+('リスト'!$G$4:$G14"&"2=type_A))), {"""","""","""",""""}), new_data, IFERROR(FILTER({'新規'!$E$2:$F142, '新規'!$O$2:$P142}, ('新規'!$A$2:$A142=V$1)*('新規'!$B$2:$B142=hour)), {"""","""","""",""""}), special_data, IFERROR(FILTER({'特殊配信マスタ'!$E$2:$F142, '特殊配信マスタ'!$O$2:$P142}, ('特殊配信マ"&"スタ'!$A$2:$A142=day)*('特殊配信マスタ'!$B$2:$B142=hour)*('特殊配信マスタ'!$R$2:$R142='特殊配信マスタ'!$S$2:$S142)), {"""","""","""",""""}), combined, VSTACK(list_data, new_data, special_data), FILTER(combined, INDEX(combined, , 1)<>"""", INDEX(combined, , 1)<>0) ), """")"),"☆横浜") -> ☆横浜 | W63: =IFERROR(__xludf.DUMMYFUNCTION("""COMPUTED_VALUE"""),4.0) -> 4 | X63: =IFERROR(__xludf.DUMMYFUNCTION("""COMPUTED_VALUE"""),"平") -> 平 | Y63: =IFERROR(__xludf.DUMMYFUNCTION("""COMPUTED_VALUE"""),"荒") -> 荒 | Z63: =SUM(W63:W72) -> 4 | AA63: =IFERROR(__xludf.DUMMYFUNCTION("IFERROR(LET( day, TEXT(AA$1, ""ddd""), hour, LOOKUP(2, 1/($A63<>""""), $A63), type_A, $A$1, list_data, IFERROR(FILTER({'リスト'!$E$4:$F142, 'リスト'!$O$4:$P142}, ('リスト'!$A$4:$A142=day)*('リスト'!$B$4:$B142=hour)*(('リスト'!$G$4:$G142=""毎週配信"")+('リスト'!$G$4:$G1"&"42=type_A))), {"""","""","""",""""}), new_data, IFERROR(FILTER({'新規'!$E$2:$F142, '新規'!$O$2:$P142}, ('新規'!$A$2:$A142=AA$1)*('新規'!$B$2:$B142=hour)), {"""","""","""",""""}), special_data, IFERROR(FILTER({'特殊配信マスタ'!$E$2:$F142, '特殊配信マスタ'!$O$2:$P142}, ('特殊配"&"信マスタ'!$A$2:$A142=day)*('特殊配信マスタ'!$B$2:$B142=hour)*('特殊配信マスタ'!$R$2:$R142='特殊配信マスタ'!$S$2:$S142)), {"""","""","""",""""}), combined, VSTACK(list_data, new_data, special_data), FILTER(combined, INDEX(combined, , 1)<>"""", INDEX(combined, , 1)<>0) ), """")"),"") | AE63: =SUM(AB63:AB72) -> 0 | AF63: =IFERROR(__xludf.DUMMYFUNCTION("IFERROR(LET( day, TEXT(AF$1, ""ddd""), hour, LOOKUP(2, 1/($A63<>""""), $A63), type_A, $A$1, list_data, IFERROR(FILTER({'リスト'!$E$4:$F142, 'リスト'!$O$4:$P142}, ('リスト'!$A$4:$A142=day)*('リスト'!$B$4:$B142=hour)*(('リスト'!$G$4:$G142=""毎週配信"")+('リスト'!$G$4:$G1"&"42=type_A))), {"""","""","""",""""}), new_data, IFERROR(FILTER({'新規'!$E$2:$F142, '新規'!$O$2:$P142}, ('新規'!$A$2:$A142=AF$1)*('新規'!$B$2:$B142=hour)), {"""","""","""",""""}), special_data, IFERROR(FILTER({'特殊配信マスタ'!$E$2:$F142, '特殊配信マスタ'!$O$2:$P142}, ('特殊配"&"信マスタ'!$A$2:$A142=day)*('特殊配信マスタ'!$B$2:$B142=hour)*('特殊配信マスタ'!$R$2:$R142='特殊配信マスタ'!$S$2:$S142)), {"""","""","""",""""}), combined, VSTACK(list_data, new_data, special_data), FILTER(combined, INDEX(combined, , 1)<>"""", INDEX(combined, , 1)<>0) ), """")"),"☆関西") -> ☆関西 | AG63: =IFERROR(__xludf.DUMMYFUNCTION("""COMPUTED_VALUE"""),1.4) -> 1.4 | AH63: =IFERROR(__xludf.DUMMYFUNCTION("""COMPUTED_VALUE"""),"平") -> 平 | AI63: =IFERROR(__xludf.DUMMYFUNCTION("""COMPUTED_VALUE"""),"荒") -> 荒 | AJ63: =SUM(AG63:AG72) -> 6.2
B64: =IFERROR(__xludf.DUMMYFUNCTION("""COMPUTED_VALUE"""),"福祉事務_35歳以上") -> 福祉事務_35歳以上 | C64: =IFERROR(__xludf.DUMMYFUNCTION("""COMPUTED_VALUE"""),1.0) -> 1 | D64: =IFERROR(__xludf.DUMMYFUNCTION("""COMPUTED_VALUE"""),"R") -> R | L64: =IFERROR(__xludf.DUMMYFUNCTION("""COMPUTED_VALUE"""),"関西‗リモート×フレックス") -> 関西‗リモート×フレックス | M64: =IFERROR(__xludf.DUMMYFUNCTION("""COMPUTED_VALUE"""),1.2) -> 1.2 | N64: =IFERROR(__xludf.DUMMYFUNCTION("""COMPUTED_VALUE"""),"部") -> 部 | O64: =IFERROR(__xludf.DUMMYFUNCTION("""COMPUTED_VALUE"""),"武") -> 武 | AF64: =IFERROR(__xludf.DUMMYFUNCTION("""COMPUTED_VALUE"""),"☆東海") -> ☆東海 | AG64: =IFERROR(__xludf.DUMMYFUNCTION("""COMPUTED_VALUE"""),0.5) -> 0.5 | AH64: =IFERROR(__xludf.DUMMYFUNCTION("""COMPUTED_VALUE"""),"平") -> 平 | AI64: =IFERROR(__xludf.DUMMYFUNCTION("""COMPUTED_VALUE"""),"荒") -> 荒
B65: =IFERROR(__xludf.DUMMYFUNCTION("""COMPUTED_VALUE"""),"未経験向け急募求人_クリエイティブ") -> 未経験向け急募求人_クリエイティブ | C65: =IFERROR(__xludf.DUMMYFUNCTION("""COMPUTED_VALUE"""),0.5) -> 0.5 | D65: =IFERROR(__xludf.DUMMYFUNCTION("""COMPUTED_VALUE"""),"R") -> R | AF65: =IFERROR(__xludf.DUMMYFUNCTION("""COMPUTED_VALUE"""),"希望勤務地_埼玉") -> 希望勤務地_埼玉 | AG65: =IFERROR(__xludf.DUMMYFUNCTION("""COMPUTED_VALUE"""),0.7) -> 0.7 | AH65: =IFERROR(__xludf.DUMMYFUNCTION("""COMPUTED_VALUE"""),"R") -> R
B66: =IFERROR(__xludf.DUMMYFUNCTION("""COMPUTED_VALUE"""),"未経験向け急募求人_営業") -> 未経験向け急募求人_営業 | C66: =IFERROR(__xludf.DUMMYFUNCTION("""COMPUTED_VALUE"""),0.5) -> 0.5 | D66: =IFERROR(__xludf.DUMMYFUNCTION("""COMPUTED_VALUE"""),"R") -> R | AF66: =IFERROR(__xludf.DUMMYFUNCTION("""COMPUTED_VALUE"""),"希望勤務地_千葉") -> 希望勤務地_千葉 | AG66: =IFERROR(__xludf.DUMMYFUNCTION("""COMPUTED_VALUE"""),0.7) -> 0.7 | AH66: =IFERROR(__xludf.DUMMYFUNCTION("""COMPUTED_VALUE"""),"R") -> R
B67: =IFERROR(__xludf.DUMMYFUNCTION("""COMPUTED_VALUE"""),"未経験向け急募求人_事務") -> 未経験向け急募求人_事務 | C67: =IFERROR(__xludf.DUMMYFUNCTION("""COMPUTED_VALUE"""),1.0) -> 1 | D67: =IFERROR(__xludf.DUMMYFUNCTION("""COMPUTED_VALUE"""),"R") -> R | AF67: =IFERROR(__xludf.DUMMYFUNCTION("""COMPUTED_VALUE"""),"希望勤務地_東京") -> 希望勤務地_東京 | AG67: =IFERROR(__xludf.DUMMYFUNCTION("""COMPUTED_VALUE"""),1.9) -> 1.9 | AH67: =IFERROR(__xludf.DUMMYFUNCTION("""COMPUTED_VALUE"""),"R") -> R
AF68: =IFERROR(__xludf.DUMMYFUNCTION("""COMPUTED_VALUE"""),"大手・上場企業×事務") -> 大手・上場企業×事務 | AG68: =IFERROR(__xludf.DUMMYFUNCTION("""COMPUTED_VALUE"""),1.0) -> 1 | AH68: =IFERROR(__xludf.DUMMYFUNCTION("""COMPUTED_VALUE"""),"R") -> R
A73: =A63+1 -> 15 | B73: =IFERROR(__xludf.DUMMYFUNCTION("IFERROR(LET( day, TEXT(B$1, ""ddd""), hour, LOOKUP(2, 1/($A73<>""""), $A73), type_A, $A$1, list_data, IFERROR(FILTER({'リスト'!$E$4:$F142, 'リスト'!$O$4:$P142}, ('リスト'!$A$4:$A142=day)*('リスト'!$B$4:$B142=hour)*(('リスト'!$G$4:$G142=""毎週配信"")+('リスト'!$G$4:$G14"&"2=type_A))), {"""","""","""",""""}), new_data, IFERROR(FILTER({'新規'!$E$2:$F142, '新規'!$O$2:$P142}, ('新規'!$A$2:$A142=B$1)*('新規'!$B$2:$B142=hour)), {"""","""","""",""""}), special_data, IFERROR(FILTER({'特殊配信マスタ'!$E$2:$F142, '特殊配信マスタ'!$O$2:$P142}, ('特殊配信マ"&"スタ'!$A$2:$A142=day)*('特殊配信マスタ'!$B$2:$B142=hour)*('特殊配信マスタ'!$R$2:$R142='特殊配信マスタ'!$S$2:$S142)), {"""","""","""",""""}), combined, VSTACK(list_data, new_data, special_data), FILTER(combined, INDEX(combined, , 1)<>"""", INDEX(combined, , 1)<>0) ), """")"),"ECサイト運用_未経験") -> ECサイト運用_未経験 | C73: =IFERROR(__xludf.DUMMYFUNCTION("""COMPUTED_VALUE"""),0.7) -> 0.7 | D73: =IFERROR(__xludf.DUMMYFUNCTION("""COMPUTED_VALUE"""),"福") -> 福 | E73: =IFERROR(__xludf.DUMMYFUNCTION("""COMPUTED_VALUE"""),"部") -> 部 | F73: =SUM(C73:C82) -> 2.3 | G73: =IFERROR(__xludf.DUMMYFUNCTION("IFERROR(LET( day, TEXT(G$1, ""ddd""), hour, LOOKUP(2, 1/($A73<>""""), $A73), type_A, $A$1, list_data, IFERROR(FILTER({'リスト'!$E$4:$F142, 'リスト'!$O$4:$P142}, ('リスト'!$A$4:$A142=day)*('リスト'!$B$4:$B142=hour)*(('リスト'!$G$4:$G142=""毎週配信"")+('リスト'!$G$4:$G14"&"2=type_A))), {"""","""","""",""""}), new_data, IFERROR(FILTER({'新規'!$E$2:$F142, '新規'!$O$2:$P142}, ('新規'!$A$2:$A142=G$1)*('新規'!$B$2:$B142=hour)), {"""","""","""",""""}), special_data, IFERROR(FILTER({'特殊配信マスタ'!$E$2:$F142, '特殊配信マスタ'!$O$2:$P142}, ('特殊配信マ"&"スタ'!$A$2:$A142=day)*('特殊配信マスタ'!$B$2:$B142=hour)*('特殊配信マスタ'!$R$2:$R142='特殊配信マスタ'!$S$2:$S142)), {"""","""","""",""""}), combined, VSTACK(list_data, new_data, special_data), FILTER(combined, INDEX(combined, , 1)<>"""", INDEX(combined, , 1)<>0) ), """")"),"営業（コールセンター）_希望") -> 営業（コールセンター）_希望 | H73: =IFERROR(__xludf.DUMMYFUNCTION("""COMPUTED_VALUE"""),0.2) -> 0.2 | I73: =IFERROR(__xludf.DUMMYFUNCTION("""COMPUTED_VALUE"""),"R") -> R | K73: =SUM(H73:H82) -> 2.3 | L73: =IFERROR(__xludf.DUMMYFUNCTION("IFERROR(LET( day, TEXT(L$1, ""ddd""), hour, LOOKUP(2, 1/($A73<>""""), $A73), type_A, $A$1, list_data, IFERROR(FILTER({'リスト'!$E$4:$F142, 'リスト'!$O$4:$P142}, ('リスト'!$A$4:$A142=day)*('リスト'!$B$4:$B142=hour)*(('リスト'!$G$4:$G142=""毎週配信"")+('リスト'!$G$4:$G14"&"2=type_A))), {"""","""","""",""""}), new_data, IFERROR(FILTER({'新規'!$E$2:$F142, '新規'!$O$2:$P142}, ('新規'!$A$2:$A142=L$1)*('新規'!$B$2:$B142=hour)), {"""","""","""",""""}), special_data, IFERROR(FILTER({'特殊配信マスタ'!$E$2:$F142, '特殊配信マスタ'!$O$2:$P142}, ('特殊配信マ"&"スタ'!$A$2:$A142=day)*('特殊配信マスタ'!$B$2:$B142=hour)*('特殊配信マスタ'!$R$2:$R142='特殊配信マスタ'!$S$2:$S142)), {"""","""","""",""""}), combined, VSTACK(list_data, new_data, special_data), FILTER(combined, INDEX(combined, , 1)<>"""", INDEX(combined, , 1)<>0) ), """")"),"営業（マーケ）_希望") -> 営業（マーケ）_希望 | M73: =IFERROR(__xludf.DUMMYFUNCTION("""COMPUTED_VALUE"""),0.4) -> 0.4 | N73: =IFERROR(__xludf.DUMMYFUNCTION("""COMPUTED_VALUE"""),"R") -> R | P73: =SUM(M73:M82) -> 0.8 | Q73: =IFERROR(__xludf.DUMMYFUNCTION("IFERROR(LET( day, TEXT(Q$1, ""ddd""), hour, LOOKUP(2, 1/($A73<>""""), $A73), type_A, $A$1, list_data, IFERROR(FILTER({'リスト'!$E$4:$F142, 'リスト'!$O$4:$P142}, ('リスト'!$A$4:$A142=day)*('リスト'!$B$4:$B142=hour)*(('リスト'!$G$4:$G142=""毎週配信"")+('リスト'!$G$4:$G14"&"2=type_A))), {"""","""","""",""""}), new_data, IFERROR(FILTER({'新規'!$E$2:$F142, '新規'!$O$2:$P142}, ('新規'!$A$2:$A142=Q$1)*('新規'!$B$2:$B142=hour)), {"""","""","""",""""}), special_data, IFERROR(FILTER({'特殊配信マスタ'!$E$2:$F142, '特殊配信マスタ'!$O$2:$P142}, ('特殊配信マ"&"スタ'!$A$2:$A142=day)*('特殊配信マスタ'!$B$2:$B142=hour)*('特殊配信マスタ'!$R$2:$R142='特殊配信マスタ'!$S$2:$S142)), {"""","""","""",""""}), combined, VSTACK(list_data, new_data, special_data), FILTER(combined, INDEX(combined, , 1)<>"""", INDEX(combined, , 1)<>0) ), """")"),"リモート手当あり") -> リモート手当あり | R73: =IFERROR(__xludf.DUMMYFUNCTION("""COMPUTED_VALUE"""),4.7) -> 4.7 | S73: =IFERROR(__xludf.DUMMYFUNCTION("""COMPUTED_VALUE"""),"R") -> R | U73: =SUM(R73:R82) -> 5.5 | V73: =IFERROR(__xludf.DUMMYFUNCTION("IFERROR(LET( day, TEXT(V$1, ""ddd""), hour, LOOKUP(2, 1/($A73<>""""), $A73), type_A, $A$1, list_data, IFERROR(FILTER({'リスト'!$E$4:$F142, 'リスト'!$O$4:$P142}, ('リスト'!$A$4:$A142=day)*('リスト'!$B$4:$B142=hour)*(('リスト'!$G$4:$G142=""毎週配信"")+('リスト'!$G$4:$G14"&"2=type_A))), {"""","""","""",""""}), new_data, IFERROR(FILTER({'新規'!$E$2:$F142, '新規'!$O$2:$P142}, ('新規'!$A$2:$A142=V$1)*('新規'!$B$2:$B142=hour)), {"""","""","""",""""}), special_data, IFERROR(FILTER({'特殊配信マスタ'!$E$2:$F142, '特殊配信マスタ'!$O$2:$P142}, ('特殊配信マ"&"スタ'!$A$2:$A142=day)*('特殊配信マスタ'!$B$2:$B142=hour)*('特殊配信マスタ'!$R$2:$R142='特殊配信マスタ'!$S$2:$S142)), {"""","""","""",""""}), combined, VSTACK(list_data, new_data, special_data), FILTER(combined, INDEX(combined, , 1)<>"""", INDEX(combined, , 1)<>0) ), """")"),"事務（貿易事務）_希望") -> 事務（貿易事務）_希望 | W73: =IFERROR(__xludf.DUMMYFUNCTION("""COMPUTED_VALUE"""),0.4) -> 0.4 | X73: =IFERROR(__xludf.DUMMYFUNCTION("""COMPUTED_VALUE"""),"R") -> R | Z73: =SUM(W73:W82) -> 0.7 | AA73: =IFERROR(__xludf.DUMMYFUNCTION("IFERROR(LET( day, TEXT(AA$1, ""ddd""), hour, LOOKUP(2, 1/($A73<>""""), $A73), type_A, $A$1, list_data, IFERROR(FILTER({'リスト'!$E$4:$F142, 'リスト'!$O$4:$P142}, ('リスト'!$A$4:$A142=day)*('リスト'!$B$4:$B142=hour)*(('リスト'!$G$4:$G142=""毎週配信"")+('リスト'!$G$4:$G1"&"42=type_A))), {"""","""","""",""""}), new_data, IFERROR(FILTER({'新規'!$E$2:$F142, '新規'!$O$2:$P142}, ('新規'!$A$2:$A142=AA$1)*('新規'!$B$2:$B142=hour)), {"""","""","""",""""}), special_data, IFERROR(FILTER({'特殊配信マスタ'!$E$2:$F142, '特殊配信マスタ'!$O$2:$P142}, ('特殊配"&"信マスタ'!$A$2:$A142=day)*('特殊配信マスタ'!$B$2:$B142=hour)*('特殊配信マスタ'!$R$2:$R142='特殊配信マスタ'!$S$2:$S142)), {"""","""","""",""""}), combined, VSTACK(list_data, new_data, special_data), FILTER(combined, INDEX(combined, , 1)<>"""", INDEX(combined, , 1)<>0) ), """")"),"") | AE73: =SUM(AB73:AB82) -> 0 | AF73: =IFERROR(__xludf.DUMMYFUNCTION("IFERROR(LET( day, TEXT(AF$1, ""ddd""), hour, LOOKUP(2, 1/($A73<>""""), $A73), type_A, $A$1, list_data, IFERROR(FILTER({'リスト'!$E$4:$F142, 'リスト'!$O$4:$P142}, ('リスト'!$A$4:$A142=day)*('リスト'!$B$4:$B142=hour)*(('リスト'!$G$4:$G142=""毎週配信"")+('リスト'!$G$4:$G1"&"42=type_A))), {"""","""","""",""""}), new_data, IFERROR(FILTER({'新規'!$E$2:$F142, '新規'!$O$2:$P142}, ('新規'!$A$2:$A142=AF$1)*('新規'!$B$2:$B142=hour)), {"""","""","""",""""}), special_data, IFERROR(FILTER({'特殊配信マスタ'!$E$2:$F142, '特殊配信マスタ'!$O$2:$P142}, ('特殊配"&"信マスタ'!$A$2:$A142=day)*('特殊配信マスタ'!$B$2:$B142=hour)*('特殊配信マスタ'!$R$2:$R142='特殊配信マスタ'!$S$2:$S142)), {"""","""","""",""""}), combined, VSTACK(list_data, new_data, special_data), FILTER(combined, INDEX(combined, , 1)<>"""", INDEX(combined, , 1)<>0) ), """")"),"ランキング_事務（医療事務）_希望") -> ランキング_事務（医療事務）_希望 | AG73: =IFERROR(__xludf.DUMMYFUNCTION("""COMPUTED_VALUE"""),0.2) -> 0.2 | AH73: =IFERROR(__xludf.DUMMYFUNCTION("""COMPUTED_VALUE"""),"R") -> R | AJ73: =SUM(AG73:AG82) -> 0.4
B74: =IFERROR(__xludf.DUMMYFUNCTION("""COMPUTED_VALUE"""),"好条件×業務委託") -> 好条件×業務委託 | C74: =IFERROR(__xludf.DUMMYFUNCTION("""COMPUTED_VALUE"""),0.4) -> 0.4 | D74: =IFERROR(__xludf.DUMMYFUNCTION("""COMPUTED_VALUE"""),"部") -> 部 | E74: =IFERROR(__xludf.DUMMYFUNCTION("""COMPUTED_VALUE"""),"武") -> 武 | G74: =IFERROR(__xludf.DUMMYFUNCTION("""COMPUTED_VALUE"""),"事務（金融関連）_希望") -> 事務（金融関連）_希望 | H74: =IFERROR(__xludf.DUMMYFUNCTION("""COMPUTED_VALUE"""),0.3) -> 0.3 | I74: =IFERROR(__xludf.DUMMYFUNCTION("""COMPUTED_VALUE"""),"R") -> R | L74: =IFERROR(__xludf.DUMMYFUNCTION("""COMPUTED_VALUE"""),"事務（その他）_希望") -> 事務（その他）_希望 | M74: =IFERROR(__xludf.DUMMYFUNCTION("""COMPUTED_VALUE"""),0.4) -> 0.4 | N74: =IFERROR(__xludf.DUMMYFUNCTION("""COMPUTED_VALUE"""),"R") -> R | Q74: =IFERROR(__xludf.DUMMYFUNCTION("""COMPUTED_VALUE"""),"営業（その他）_希望") -> 営業（その他）_希望 | R74: =IFERROR(__xludf.DUMMYFUNCTION("""COMPUTED_VALUE"""),0.3) -> 0.3 | S74: =IFERROR(__xludf.DUMMYFUNCTION("""COMPUTED_VALUE"""),"R") -> R | V74: =IFERROR(__xludf.DUMMYFUNCTION("""COMPUTED_VALUE"""),"販サ（フロント）_希望") -> 販サ（フロント）_希望 | W74: =IFERROR(__xludf.DUMMYFUNCTION("""COMPUTED_VALUE"""),0.3) -> 0.3 | X74: =IFERROR(__xludf.DUMMYFUNCTION("""COMPUTED_VALUE"""),"R") -> R | AF74: =IFERROR(__xludf.DUMMYFUNCTION("""COMPUTED_VALUE"""),"営業（キャリアカウンセラー）_希望") -> 営業（キャリアカウンセラー）_希望 | AG74: =IFERROR(__xludf.DUMMYFUNCTION("""COMPUTED_VALUE"""),0.2) -> 0.2 | AH74: =IFERROR(__xludf.DUMMYFUNCTION("""COMPUTED_VALUE"""),"R") -> R
B75: =IFERROR(__xludf.DUMMYFUNCTION("""COMPUTED_VALUE"""),"好条件×契約社員") -> 好条件×契約社員 | C75: =IFERROR(__xludf.DUMMYFUNCTION("""COMPUTED_VALUE"""),1.2) -> 1.2 | D75: =IFERROR(__xludf.DUMMYFUNCTION("""COMPUTED_VALUE"""),"R") -> R | G75: =IFERROR(__xludf.DUMMYFUNCTION("""COMPUTED_VALUE"""),"転職回数不問") -> 転職回数不問 | H75: =IFERROR(__xludf.DUMMYFUNCTION("""COMPUTED_VALUE"""),1.8) -> 1.8 | I75: =IFERROR(__xludf.DUMMYFUNCTION("""COMPUTED_VALUE"""),"R") -> R | Q75: =IFERROR(__xludf.DUMMYFUNCTION("""COMPUTED_VALUE"""),"事務（医療事務）_希望") -> 事務（医療事務）_希望 | R75: =IFERROR(__xludf.DUMMYFUNCTION("""COMPUTED_VALUE"""),0.5) -> 0.5 | S75: =IFERROR(__xludf.DUMMYFUNCTION("""COMPUTED_VALUE"""),"R") -> R
A83: =A73+1 -> 16 | B83: =IFERROR(__xludf.DUMMYFUNCTION("IFERROR(LET( day, TEXT(B$1, ""ddd""), hour, LOOKUP(2, 1/($A83<>""""), $A83), type_A, $A$1, list_data, IFERROR(FILTER({'リスト'!$E$4:$F142, 'リスト'!$O$4:$P142}, ('リスト'!$A$4:$A142=day)*('リスト'!$B$4:$B142=hour)*(('リスト'!$G$4:$G142=""毎週配信"")+('リスト'!$G$4:$G14"&"2=type_A))), {"""","""","""",""""}), new_data, IFERROR(FILTER({'新規'!$E$2:$F142, '新規'!$O$2:$P142}, ('新規'!$A$2:$A142=B$1)*('新規'!$B$2:$B142=hour)), {"""","""","""",""""}), special_data, IFERROR(FILTER({'特殊配信マスタ'!$E$2:$F142, '特殊配信マスタ'!$O$2:$P142}, ('特殊配信マ"&"スタ'!$A$2:$A142=day)*('特殊配信マスタ'!$B$2:$B142=hour)*('特殊配信マスタ'!$R$2:$R142='特殊配信マスタ'!$S$2:$S142)), {"""","""","""",""""}), combined, VSTACK(list_data, new_data, special_data), FILTER(combined, INDEX(combined, , 1)<>"""", INDEX(combined, , 1)<>0) ), """")"),"35歳以上向け A") -> 35歳以上向け A | C83: =IFERROR(__xludf.DUMMYFUNCTION("""COMPUTED_VALUE"""),1.0) -> 1 | D83: =IFERROR(__xludf.DUMMYFUNCTION("""COMPUTED_VALUE"""),"R") -> R | F83: =SUM(C83:C92) -> 1.6 | G83: =IFERROR(__xludf.DUMMYFUNCTION("IFERROR(LET( day, TEXT(G$1, ""ddd""), hour, LOOKUP(2, 1/($A83<>""""), $A83), type_A, $A$1, list_data, IFERROR(FILTER({'リスト'!$E$4:$F142, 'リスト'!$O$4:$P142}, ('リスト'!$A$4:$A142=day)*('リスト'!$B$4:$B142=hour)*(('リスト'!$G$4:$G142=""毎週配信"")+('リスト'!$G$4:$G14"&"2=type_A))), {"""","""","""",""""}), new_data, IFERROR(FILTER({'新規'!$E$2:$F142, '新規'!$O$2:$P142}, ('新規'!$A$2:$A142=G$1)*('新規'!$B$2:$B142=hour)), {"""","""","""",""""}), special_data, IFERROR(FILTER({'特殊配信マスタ'!$E$2:$F142, '特殊配信マスタ'!$O$2:$P142}, ('特殊配信マ"&"スタ'!$A$2:$A142=day)*('特殊配信マスタ'!$B$2:$B142=hour)*('特殊配信マスタ'!$R$2:$R142='特殊配信マスタ'!$S$2:$S142)), {"""","""","""",""""}), combined, VSTACK(list_data, new_data, special_data), FILTER(combined, INDEX(combined, , 1)<>"""", INDEX(combined, , 1)<>0) ), """")"),"年収UP_関西") -> 年収UP_関西 | H83: =IFERROR(__xludf.DUMMYFUNCTION("""COMPUTED_VALUE"""),1.0) -> 1 | I83: =IFERROR(__xludf.DUMMYFUNCTION("""COMPUTED_VALUE"""),"R") -> R | K83: =SUM(H83:H92) -> 3.8 | L83: =IFERROR(__xludf.DUMMYFUNCTION("IFERROR(LET( day, TEXT(L$1, ""ddd""), hour, LOOKUP(2, 1/($A83<>""""), $A83), type_A, $A$1, list_data, IFERROR(FILTER({'リスト'!$E$4:$F142, 'リスト'!$O$4:$P142}, ('リスト'!$A$4:$A142=day)*('リスト'!$B$4:$B142=hour)*(('リスト'!$G$4:$G142=""毎週配信"")+('リスト'!$G$4:$G14"&"2=type_A))), {"""","""","""",""""}), new_data, IFERROR(FILTER({'新規'!$E$2:$F142, '新規'!$O$2:$P142}, ('新規'!$A$2:$A142=L$1)*('新規'!$B$2:$B142=hour)), {"""","""","""",""""}), special_data, IFERROR(FILTER({'特殊配信マスタ'!$E$2:$F142, '特殊配信マスタ'!$O$2:$P142}, ('特殊配信マ"&"スタ'!$A$2:$A142=day)*('特殊配信マスタ'!$B$2:$B142=hour)*('特殊配信マスタ'!$R$2:$R142='特殊配信マスタ'!$S$2:$S142)), {"""","""","""",""""}), combined, VSTACK(list_data, new_data, special_data), FILTER(combined, INDEX(combined, , 1)<>"""", INDEX(combined, , 1)<>0) ), """")"),"エンジニア限定_単独求人メルマガ") -> エンジニア限定_単独求人メルマガ | M83: =IFERROR(__xludf.DUMMYFUNCTION("""COMPUTED_VALUE"""),0.5) -> 0.5 | N83: =IFERROR(__xludf.DUMMYFUNCTION("""COMPUTED_VALUE"""),"武") -> 武 | O83: =IFERROR(__xludf.DUMMYFUNCTION("""COMPUTED_VALUE"""),"部") -> 部 | P83: =SUM(M83:M92) -> 2.6 | Q83: =IFERROR(__xludf.DUMMYFUNCTION("IFERROR(LET( day, TEXT(Q$1, ""ddd""), hour, LOOKUP(2, 1/($A83<>""""), $A83), type_A, $A$1, list_data, IFERROR(FILTER({'リスト'!$E$4:$F142, 'リスト'!$O$4:$P142}, ('リスト'!$A$4:$A142=day)*('リスト'!$B$4:$B142=hour)*(('リスト'!$G$4:$G142=""毎週配信"")+('リスト'!$G$4:$G14"&"2=type_A))), {"""","""","""",""""}), new_data, IFERROR(FILTER({'新規'!$E$2:$F142, '新規'!$O$2:$P142}, ('新規'!$A$2:$A142=Q$1)*('新規'!$B$2:$B142=hour)), {"""","""","""",""""}), special_data, IFERROR(FILTER({'特殊配信マスタ'!$E$2:$F142, '特殊配信マスタ'!$O$2:$P142}, ('特殊配信マ"&"スタ'!$A$2:$A142=day)*('特殊配信マスタ'!$B$2:$B142=hour)*('特殊配信マスタ'!$R$2:$R142='特殊配信マスタ'!$S$2:$S142)), {"""","""","""",""""}), combined, VSTACK(list_data, new_data, special_data), FILTER(combined, INDEX(combined, , 1)<>"""", INDEX(combined, , 1)<>0) ), """")"),"◇ポジションマッチ B1") -> ◇ポジションマッチ B1 | R83: =IFERROR(__xludf.DUMMYFUNCTION("""COMPUTED_VALUE"""),2.5) -> 2.5 | S83: =IFERROR(__xludf.DUMMYFUNCTION("""COMPUTED_VALUE"""),"荒") -> 荒 | T83: =IFERROR(__xludf.DUMMYFUNCTION("""COMPUTED_VALUE"""),"平") -> 平 | U83: =SUM(R83:R92) -> 5 | V83: =IFERROR(__xludf.DUMMYFUNCTION("IFERROR(LET( day, TEXT(V$1, ""ddd""), hour, LOOKUP(2, 1/($A83<>""""), $A83), type_A, $A$1, list_data, IFERROR(FILTER({'リスト'!$E$4:$F142, 'リスト'!$O$4:$P142}, ('リスト'!$A$4:$A142=day)*('リスト'!$B$4:$B142=hour)*(('リスト'!$G$4:$G142=""毎週配信"")+('リスト'!$G$4:$G14"&"2=type_A))), {"""","""","""",""""}), new_data, IFERROR(FILTER({'新規'!$E$2:$F142, '新規'!$O$2:$P142}, ('新規'!$A$2:$A142=V$1)*('新規'!$B$2:$B142=hour)), {"""","""","""",""""}), special_data, IFERROR(FILTER({'特殊配信マスタ'!$E$2:$F142, '特殊配信マスタ'!$O$2:$P142}, ('特殊配信マ"&"スタ'!$A$2:$A142=day)*('特殊配信マスタ'!$B$2:$B142=hour)*('特殊配信マスタ'!$R$2:$R142='特殊配信マスタ'!$S$2:$S142)), {"""","""","""",""""}), combined, VSTACK(list_data, new_data, special_data), FILTER(combined, INDEX(combined, , 1)<>"""", INDEX(combined, , 1)<>0) ), """")"),"☆救済メルマガ(UP10)") -> ☆救済メルマガ(UP10) | W83: =IFERROR(__xludf.DUMMYFUNCTION("""COMPUTED_VALUE"""),4.0) -> 4 | X83: =IFERROR(__xludf.DUMMYFUNCTION("""COMPUTED_VALUE"""),"平") -> 平 | Y83: =IFERROR(__xludf.DUMMYFUNCTION("""COMPUTED_VALUE"""),"荒") -> 荒 | Z83: =SUM(W83:W92) -> 4 | AA83: =IFERROR(__xludf.DUMMYFUNCTION("IFERROR(LET( day, TEXT(AA$1, ""ddd""), hour, LOOKUP(2, 1/($A83<>""""), $A83), type_A, $A$1, list_data, IFERROR(FILTER({'リスト'!$E$4:$F142, 'リスト'!$O$4:$P142}, ('リスト'!$A$4:$A142=day)*('リスト'!$B$4:$B142=hour)*(('リスト'!$G$4:$G142=""毎週配信"")+('リスト'!$G$4:$G1"&"42=type_A))), {"""","""","""",""""}), new_data, IFERROR(FILTER({'新規'!$E$2:$F142, '新規'!$O$2:$P142}, ('新規'!$A$2:$A142=AA$1)*('新規'!$B$2:$B142=hour)), {"""","""","""",""""}), special_data, IFERROR(FILTER({'特殊配信マスタ'!$E$2:$F142, '特殊配信マスタ'!$O$2:$P142}, ('特殊配"&"信マスタ'!$A$2:$A142=day)*('特殊配信マスタ'!$B$2:$B142=hour)*('特殊配信マスタ'!$R$2:$R142='特殊配信マスタ'!$S$2:$S142)), {"""","""","""",""""}), combined, VSTACK(list_data, new_data, special_data), FILTER(combined, INDEX(combined, , 1)<>"""", INDEX(combined, , 1)<>0) ), """")"),"") | AE83: =SUM(AB83:AB92) -> 0 | AF83: =IFERROR(__xludf.DUMMYFUNCTION("IFERROR(LET( day, TEXT(AF$1, ""ddd""), hour, LOOKUP(2, 1/($A83<>""""), $A83), type_A, $A$1, list_data, IFERROR(FILTER({'リスト'!$E$4:$F142, 'リスト'!$O$4:$P142}, ('リスト'!$A$4:$A142=day)*('リスト'!$B$4:$B142=hour)*(('リスト'!$G$4:$G142=""毎週配信"")+('リスト'!$G$4:$G1"&"42=type_A))), {"""","""","""",""""}), new_data, IFERROR(FILTER({'新規'!$E$2:$F142, '新規'!$O$2:$P142}, ('新規'!$A$2:$A142=AF$1)*('新規'!$B$2:$B142=hour)), {"""","""","""",""""}), special_data, IFERROR(FILTER({'特殊配信マスタ'!$E$2:$F142, '特殊配信マスタ'!$O$2:$P142}, ('特殊配"&"信マスタ'!$A$2:$A142=day)*('特殊配信マスタ'!$B$2:$B142=hour)*('特殊配信マスタ'!$R$2:$R142='特殊配信マスタ'!$S$2:$S142)), {"""","""","""",""""}), combined, VSTACK(list_data, new_data, special_data), FILTER(combined, INDEX(combined, , 1)<>"""", INDEX(combined, , 1)<>0) ), """")"),"事務職 B") -> 事務職 B | AG83: =IFERROR(__xludf.DUMMYFUNCTION("""COMPUTED_VALUE"""),1.7) -> 1.7 | AH83: =IFERROR(__xludf.DUMMYFUNCTION("""COMPUTED_VALUE"""),"R") -> R | AJ83: =SUM(AG83:AG92) -> 5.7
B84: =IFERROR(__xludf.DUMMYFUNCTION("""COMPUTED_VALUE"""),"育児両立_フレックス") -> 育児両立_フレックス | C84: =IFERROR(__xludf.DUMMYFUNCTION("""COMPUTED_VALUE"""),0.6) -> 0.6 | D84: =IFERROR(__xludf.DUMMYFUNCTION("""COMPUTED_VALUE"""),"R") -> R | G84: =IFERROR(__xludf.DUMMYFUNCTION("""COMPUTED_VALUE"""),"副業OK×リモート_ランキング") -> 副業OK×リモート_ランキング | H84: =IFERROR(__xludf.DUMMYFUNCTION("""COMPUTED_VALUE"""),2.8) -> 2.8 | I84: =IFERROR(__xludf.DUMMYFUNCTION("""COMPUTED_VALUE"""),"R") -> R | L84: =IFERROR(__xludf.DUMMYFUNCTION("""COMPUTED_VALUE"""),"年休130日以上_残業10時間以下") -> 年休130日以上_残業10時間以下 | M84: =IFERROR(__xludf.DUMMYFUNCTION("""COMPUTED_VALUE"""),2.1) -> 2.1 | N84: =IFERROR(__xludf.DUMMYFUNCTION("""COMPUTED_VALUE"""),"R") -> R | Q84: =IFERROR(__xludf.DUMMYFUNCTION("""COMPUTED_VALUE"""),"◇ポジションマッチ_36歳以上 B1") -> ◇ポジションマッチ_36歳以上 B1 | R84: =IFERROR(__xludf.DUMMYFUNCTION("""COMPUTED_VALUE"""),2.5) -> 2.5 | S84: =IFERROR(__xludf.DUMMYFUNCTION("""COMPUTED_VALUE"""),"荒") -> 荒 | T84: =IFERROR(__xludf.DUMMYFUNCTION("""COMPUTED_VALUE"""),"平") -> 平 | AF84: =IFERROR(__xludf.DUMMYFUNCTION("""COMPUTED_VALUE"""),"事務職_35歳以上 B") -> 事務職_35歳以上 B | AG84: =IFERROR(__xludf.DUMMYFUNCTION("""COMPUTED_VALUE"""),3.0) -> 3 | AH84: =IFERROR(__xludf.DUMMYFUNCTION("""COMPUTED_VALUE"""),"R") -> R
AF85: =IFERROR(__xludf.DUMMYFUNCTION("""COMPUTED_VALUE"""),"事務職_関西 B") -> 事務職_関西 B | AG85: =IFERROR(__xludf.DUMMYFUNCTION("""COMPUTED_VALUE"""),1.0) -> 1 | AH85: =IFERROR(__xludf.DUMMYFUNCTION("""COMPUTED_VALUE"""),"R") -> R
A93: =A83+1 -> 17 | B93: =IFERROR(__xludf.DUMMYFUNCTION("IFERROR(LET( day, TEXT(B$1, ""ddd""), hour, LOOKUP(2, 1/($A93<>""""), $A93), type_A, $A$1, list_data, IFERROR(FILTER({'リスト'!$E$4:$F142, 'リスト'!$O$4:$P142}, ('リスト'!$A$4:$A142=day)*('リスト'!$B$4:$B142=hour)*(('リスト'!$G$4:$G142=""毎週配信"")+('リスト'!$G$4:$G14"&"2=type_A))), {"""","""","""",""""}), new_data, IFERROR(FILTER({'新規'!$E$2:$F142, '新規'!$O$2:$P142}, ('新規'!$A$2:$A142=B$1)*('新規'!$B$2:$B142=hour)), {"""","""","""",""""}), special_data, IFERROR(FILTER({'特殊配信マスタ'!$E$2:$F142, '特殊配信マスタ'!$O$2:$P142}, ('特殊配信マ"&"スタ'!$A$2:$A142=day)*('特殊配信マスタ'!$B$2:$B142=hour)*('特殊配信マスタ'!$R$2:$R142='特殊配信マスタ'!$S$2:$S142)), {"""","""","""",""""}), combined, VSTACK(list_data, new_data, special_data), FILTER(combined, INDEX(combined, , 1)<>"""", INDEX(combined, , 1)<>0) ), """")"),"引っ越し特典") -> 引っ越し特典 | C93: =IFERROR(__xludf.DUMMYFUNCTION("""COMPUTED_VALUE"""),2.3) -> 2.3 | D93: =IFERROR(__xludf.DUMMYFUNCTION("""COMPUTED_VALUE"""),"部") -> 部 | E93: =IFERROR(__xludf.DUMMYFUNCTION("""COMPUTED_VALUE"""),"石") -> 石 | F93: =SUM(C93:C102) -> 7.2 | G93: =IFERROR(__xludf.DUMMYFUNCTION("IFERROR(LET( day, TEXT(G$1, ""ddd""), hour, LOOKUP(2, 1/($A93<>""""), $A93), type_A, $A$1, list_data, IFERROR(FILTER({'リスト'!$E$4:$F142, 'リスト'!$O$4:$P142}, ('リスト'!$A$4:$A142=day)*('リスト'!$B$4:$B142=hour)*(('リスト'!$G$4:$G142=""毎週配信"")+('リスト'!$G$4:$G14"&"2=type_A))), {"""","""","""",""""}), new_data, IFERROR(FILTER({'新規'!$E$2:$F142, '新規'!$O$2:$P142}, ('新規'!$A$2:$A142=G$1)*('新規'!$B$2:$B142=hour)), {"""","""","""",""""}), special_data, IFERROR(FILTER({'特殊配信マスタ'!$E$2:$F142, '特殊配信マスタ'!$O$2:$P142}, ('特殊配信マ"&"スタ'!$A$2:$A142=day)*('特殊配信マスタ'!$B$2:$B142=hour)*('特殊配信マスタ'!$R$2:$R142='特殊配信マスタ'!$S$2:$S142)), {"""","""","""",""""}), combined, VSTACK(list_data, new_data, special_data), FILTER(combined, INDEX(combined, , 1)<>"""", INDEX(combined, , 1)<>0) ), """")"),"☆推進課") -> ☆推進課 | H93: =IFERROR(__xludf.DUMMYFUNCTION("""COMPUTED_VALUE"""),3.0) -> 3 | I93: =IFERROR(__xludf.DUMMYFUNCTION("""COMPUTED_VALUE"""),"荒") -> 荒 | J93: =IFERROR(__xludf.DUMMYFUNCTION("""COMPUTED_VALUE"""),"平") -> 平 | K93: =SUM(H93:H102) -> 8.1 | L93: =IFERROR(__xludf.DUMMYFUNCTION("IFERROR(LET( day, TEXT(L$1, ""ddd""), hour, LOOKUP(2, 1/($A93<>""""), $A93), type_A, $A$1, list_data, IFERROR(FILTER({'リスト'!$E$4:$F142, 'リスト'!$O$4:$P142}, ('リスト'!$A$4:$A142=day)*('リスト'!$B$4:$B142=hour)*(('リスト'!$G$4:$G142=""毎週配信"")+('リスト'!$G$4:$G14"&"2=type_A))), {"""","""","""",""""}), new_data, IFERROR(FILTER({'新規'!$E$2:$F142, '新規'!$O$2:$P142}, ('新規'!$A$2:$A142=L$1)*('新規'!$B$2:$B142=hour)), {"""","""","""",""""}), special_data, IFERROR(FILTER({'特殊配信マスタ'!$E$2:$F142, '特殊配信マスタ'!$O$2:$P142}, ('特殊配信マ"&"スタ'!$A$2:$A142=day)*('特殊配信マスタ'!$B$2:$B142=hour)*('特殊配信マスタ'!$R$2:$R142='特殊配信マスタ'!$S$2:$S142)), {"""","""","""",""""}), combined, VSTACK(list_data, new_data, special_data), FILTER(combined, INDEX(combined, , 1)<>"""", INDEX(combined, , 1)<>0) ), """")"),"単独求人訴求メルマガ_C") -> 単独求人訴求メルマガ_C | M93: =IFERROR(__xludf.DUMMYFUNCTION("""COMPUTED_VALUE"""),2.3) -> 2.3 | N93: =IFERROR(__xludf.DUMMYFUNCTION("""COMPUTED_VALUE"""),"石") -> 石 | O93: =IFERROR(__xludf.DUMMYFUNCTION("""COMPUTED_VALUE"""),"武") -> 武 | P93: =SUM(M93:M102) -> 2.9 | Q93: =IFERROR(__xludf.DUMMYFUNCTION("IFERROR(LET( day, TEXT(Q$1, ""ddd""), hour, LOOKUP(2, 1/($A93<>""""), $A93), type_A, $A$1, list_data, IFERROR(FILTER({'リスト'!$E$4:$F142, 'リスト'!$O$4:$P142}, ('リスト'!$A$4:$A142=day)*('リスト'!$B$4:$B142=hour)*(('リスト'!$G$4:$G142=""毎週配信"")+('リスト'!$G$4:$G14"&"2=type_A))), {"""","""","""",""""}), new_data, IFERROR(FILTER({'新規'!$E$2:$F142, '新規'!$O$2:$P142}, ('新規'!$A$2:$A142=Q$1)*('新規'!$B$2:$B142=hour)), {"""","""","""",""""}), special_data, IFERROR(FILTER({'特殊配信マスタ'!$E$2:$F142, '特殊配信マスタ'!$O$2:$P142}, ('特殊配信マ"&"スタ'!$A$2:$A142=day)*('特殊配信マスタ'!$B$2:$B142=hour)*('特殊配信マスタ'!$R$2:$R142='特殊配信マスタ'!$S$2:$S142)), {"""","""","""",""""}), combined, VSTACK(list_data, new_data, special_data), FILTER(combined, INDEX(combined, , 1)<>"""", INDEX(combined, , 1)<>0) ), """")"),"☆Womantype[全]") -> ☆Womantype[全] | R93: =IFERROR(__xludf.DUMMYFUNCTION("""COMPUTED_VALUE"""),5.0) -> 5 | S93: =IFERROR(__xludf.DUMMYFUNCTION("""COMPUTED_VALUE"""),"内") -> 内 | T93: =IFERROR(__xludf.DUMMYFUNCTION("""COMPUTED_VALUE"""),"平") -> 平 | U93: =SUM(R93:R102) -> 5 | V93: =IFERROR(__xludf.DUMMYFUNCTION("IFERROR(LET( day, TEXT(V$1, ""ddd""), hour, LOOKUP(2, 1/($A93<>""""), $A93), type_A, $A$1, list_data, IFERROR(FILTER({'リスト'!$E$4:$F142, 'リスト'!$O$4:$P142}, ('リスト'!$A$4:$A142=day)*('リスト'!$B$4:$B142=hour)*(('リスト'!$G$4:$G142=""毎週配信"")+('リスト'!$G$4:$G14"&"2=type_A))), {"""","""","""",""""}), new_data, IFERROR(FILTER({'新規'!$E$2:$F142, '新規'!$O$2:$P142}, ('新規'!$A$2:$A142=V$1)*('新規'!$B$2:$B142=hour)), {"""","""","""",""""}), special_data, IFERROR(FILTER({'特殊配信マスタ'!$E$2:$F142, '特殊配信マスタ'!$O$2:$P142}, ('特殊配信マ"&"スタ'!$A$2:$A142=day)*('特殊配信マスタ'!$B$2:$B142=hour)*('特殊配信マスタ'!$R$2:$R142='特殊配信マスタ'!$S$2:$S142)), {"""","""","""",""""}), combined, VSTACK(list_data, new_data, special_data), FILTER(combined, INDEX(combined, , 1)<>"""", INDEX(combined, , 1)<>0) ), """")"),"京都市で働く") -> 京都市で働く | W93: =IFERROR(__xludf.DUMMYFUNCTION("""COMPUTED_VALUE"""),0.2) -> 0.2 | X93: =IFERROR(__xludf.DUMMYFUNCTION("""COMPUTED_VALUE"""),"部") -> 部 | Y93: =IFERROR(__xludf.DUMMYFUNCTION("""COMPUTED_VALUE"""),"武") -> 武 | Z93: =SUM(W93:W102) -> 4.1 | AA93: =IFERROR(__xludf.DUMMYFUNCTION("IFERROR(LET( day, TEXT(AA$1, ""ddd""), hour, LOOKUP(2, 1/($A93<>""""), $A93), type_A, $A$1, list_data, IFERROR(FILTER({'リスト'!$E$4:$F142, 'リスト'!$O$4:$P142}, ('リスト'!$A$4:$A142=day)*('リスト'!$B$4:$B142=hour)*(('リスト'!$G$4:$G142=""毎週配信"")+('リスト'!$G$4:$G1"&"42=type_A))), {"""","""","""",""""}), new_data, IFERROR(FILTER({'新規'!$E$2:$F142, '新規'!$O$2:$P142}, ('新規'!$A$2:$A142=AA$1)*('新規'!$B$2:$B142=hour)), {"""","""","""",""""}), special_data, IFERROR(FILTER({'特殊配信マスタ'!$E$2:$F142, '特殊配信マスタ'!$O$2:$P142}, ('特殊配"&"信マスタ'!$A$2:$A142=day)*('特殊配信マスタ'!$B$2:$B142=hour)*('特殊配信マスタ'!$R$2:$R142='特殊配信マスタ'!$S$2:$S142)), {"""","""","""",""""}), combined, VSTACK(list_data, new_data, special_data), FILTER(combined, INDEX(combined, , 1)<>"""", INDEX(combined, , 1)<>0) ), """")"),"☆IT派遣［全］") -> ☆IT派遣［全］ | AB93: =IFERROR(__xludf.DUMMYFUNCTION("""COMPUTED_VALUE"""),2.6) -> 2.6 | AC93: =IFERROR(__xludf.DUMMYFUNCTION("""COMPUTED_VALUE"""),"内") -> 内 | AD93: =IFERROR(__xludf.DUMMYFUNCTION("""COMPUTED_VALUE"""),"平") -> 平 | AE93: =SUM(AB93:AB102) -> 3.3 | AF93: =IFERROR(__xludf.DUMMYFUNCTION("IFERROR(LET( day, TEXT(AF$1, ""ddd""), hour, LOOKUP(2, 1/($A93<>""""), $A93), type_A, $A$1, list_data, IFERROR(FILTER({'リスト'!$E$4:$F142, 'リスト'!$O$4:$P142}, ('リスト'!$A$4:$A142=day)*('リスト'!$B$4:$B142=hour)*(('リスト'!$G$4:$G142=""毎週配信"")+('リスト'!$G$4:$G1"&"42=type_A))), {"""","""","""",""""}), new_data, IFERROR(FILTER({'新規'!$E$2:$F142, '新規'!$O$2:$P142}, ('新規'!$A$2:$A142=AF$1)*('新規'!$B$2:$B142=hour)), {"""","""","""",""""}), special_data, IFERROR(FILTER({'特殊配信マスタ'!$E$2:$F142, '特殊配信マスタ'!$O$2:$P142}, ('特殊配"&"信マスタ'!$A$2:$A142=day)*('特殊配信マスタ'!$B$2:$B142=hour)*('特殊配信マスタ'!$R$2:$R142='特殊配信マスタ'!$S$2:$S142)), {"""","""","""",""""}), combined, VSTACK(list_data, new_data, special_data), FILTER(combined, INDEX(combined, , 1)<>"""", INDEX(combined, , 1)<>0) ), """")"),"単独求人訴求メルマガ_C") -> 単独求人訴求メルマガ_C | AG93: =IFERROR(__xludf.DUMMYFUNCTION("""COMPUTED_VALUE"""),3.0) -> 3 | AH93: =IFERROR(__xludf.DUMMYFUNCTION("""COMPUTED_VALUE"""),"石") -> 石 | AI93: =IFERROR(__xludf.DUMMYFUNCTION("""COMPUTED_VALUE"""),"武") -> 武 | AJ93: =SUM(AG93:AG102) -> 3
B94: =IFERROR(__xludf.DUMMYFUNCTION("""COMPUTED_VALUE"""),"◇応募ランキング A") -> ◇応募ランキング A | C94: =IFERROR(__xludf.DUMMYFUNCTION("""COMPUTED_VALUE"""),0.7) -> 0.7 | D94: =IFERROR(__xludf.DUMMYFUNCTION("""COMPUTED_VALUE"""),"荒") -> 荒 | E94: =IFERROR(__xludf.DUMMYFUNCTION("""COMPUTED_VALUE"""),"平") -> 平 | G94: =IFERROR(__xludf.DUMMYFUNCTION("""COMPUTED_VALUE"""),"☆推進課_35歳以上") -> ☆推進課_35歳以上 | H94: =IFERROR(__xludf.DUMMYFUNCTION("""COMPUTED_VALUE"""),1.0) -> 1 | I94: =IFERROR(__xludf.DUMMYFUNCTION("""COMPUTED_VALUE"""),"荒") -> 荒 | J94: =IFERROR(__xludf.DUMMYFUNCTION("""COMPUTED_VALUE"""),"平") -> 平 | L94: =IFERROR(__xludf.DUMMYFUNCTION("""COMPUTED_VALUE"""),"東海_リモート") -> 東海_リモート | M94: =IFERROR(__xludf.DUMMYFUNCTION("""COMPUTED_VALUE"""),0.6) -> 0.6 | N94: =IFERROR(__xludf.DUMMYFUNCTION("""COMPUTED_VALUE"""),"R") -> R | V94: =IFERROR(__xludf.DUMMYFUNCTION("""COMPUTED_VALUE"""),"熊本市で働く") -> 熊本市で働く | W94: =IFERROR(__xludf.DUMMYFUNCTION("""COMPUTED_VALUE"""),0.1) -> 0.1 | X94: =IFERROR(__xludf.DUMMYFUNCTION("""COMPUTED_VALUE"""),"部") -> 部 | Y94: =IFERROR(__xludf.DUMMYFUNCTION("""COMPUTED_VALUE"""),"武") -> 武 | AA94: =IFERROR(__xludf.DUMMYFUNCTION("""COMPUTED_VALUE"""),"事務・営業職経験者向け") -> 事務・営業職経験者向け | AB94: =IFERROR(__xludf.DUMMYFUNCTION("""COMPUTED_VALUE"""),0.7) -> 0.7 | AC94: =IFERROR(__xludf.DUMMYFUNCTION("""COMPUTED_VALUE"""),"R") -> R
B95: =IFERROR(__xludf.DUMMYFUNCTION("""COMPUTED_VALUE"""),"仙台_リモートOK_未経験") -> 仙台_リモートOK_未経験 | C95: =IFERROR(__xludf.DUMMYFUNCTION("""COMPUTED_VALUE"""),0.2) -> 0.2 | D95: =IFERROR(__xludf.DUMMYFUNCTION("""COMPUTED_VALUE"""),"R") -> R | G95: =IFERROR(__xludf.DUMMYFUNCTION("""COMPUTED_VALUE"""),"☆推進課_関西") -> ☆推進課_関西 | H95: =IFERROR(__xludf.DUMMYFUNCTION("""COMPUTED_VALUE"""),1.0) -> 1 | I95: =IFERROR(__xludf.DUMMYFUNCTION("""COMPUTED_VALUE"""),"荒") -> 荒 | J95: =IFERROR(__xludf.DUMMYFUNCTION("""COMPUTED_VALUE"""),"平") -> 平 | V95: =IFERROR(__xludf.DUMMYFUNCTION("""COMPUTED_VALUE"""),"広島市で働く") -> 広島市で働く | W95: =IFERROR(__xludf.DUMMYFUNCTION("""COMPUTED_VALUE"""),0.1) -> 0.1 | X95: =IFERROR(__xludf.DUMMYFUNCTION("""COMPUTED_VALUE"""),"部") -> 部 | Y95: =IFERROR(__xludf.DUMMYFUNCTION("""COMPUTED_VALUE"""),"武") -> 武
B96: =IFERROR(__xludf.DUMMYFUNCTION("""COMPUTED_VALUE"""),"大阪_リモートOK_未経験") -> 大阪_リモートOK_未経験 | C96: =IFERROR(__xludf.DUMMYFUNCTION("""COMPUTED_VALUE"""),0.7) -> 0.7 | D96: =IFERROR(__xludf.DUMMYFUNCTION("""COMPUTED_VALUE"""),"R") -> R | G96: =IFERROR(__xludf.DUMMYFUNCTION("""COMPUTED_VALUE"""),"掲載終了間近_人気求人ランキング") -> 掲載終了間近_人気求人ランキング | H96: =IFERROR(__xludf.DUMMYFUNCTION("""COMPUTED_VALUE"""),3.1) -> 3.1 | I96: =IFERROR(__xludf.DUMMYFUNCTION("""COMPUTED_VALUE"""),"武") -> 武 | J96: =IFERROR(__xludf.DUMMYFUNCTION("""COMPUTED_VALUE"""),"部") -> 部 | V96: =IFERROR(__xludf.DUMMYFUNCTION("""COMPUTED_VALUE"""),"横浜駅で働く") -> 横浜駅で働く | W96: =IFERROR(__xludf.DUMMYFUNCTION("""COMPUTED_VALUE"""),1.2) -> 1.2 | X96: =IFERROR(__xludf.DUMMYFUNCTION("""COMPUTED_VALUE"""),"R") -> R
B97: =IFERROR(__xludf.DUMMYFUNCTION("""COMPUTED_VALUE"""),"単独求人訴求メルマガ_B") -> 単独求人訴求メルマガ_B | C97: =IFERROR(__xludf.DUMMYFUNCTION("""COMPUTED_VALUE"""),2.9) -> 2.9 | D97: =IFERROR(__xludf.DUMMYFUNCTION("""COMPUTED_VALUE"""),"武") -> 武 | E97: =IFERROR(__xludf.DUMMYFUNCTION("""COMPUTED_VALUE"""),"部") -> 部 | V97: =IFERROR(__xludf.DUMMYFUNCTION("""COMPUTED_VALUE"""),"札幌駅で働く") -> 札幌駅で働く | W97: =IFERROR(__xludf.DUMMYFUNCTION("""COMPUTED_VALUE"""),0.2) -> 0.2 | X97: =IFERROR(__xludf.DUMMYFUNCTION("""COMPUTED_VALUE"""),"R") -> R
B98: =IFERROR(__xludf.DUMMYFUNCTION("""COMPUTED_VALUE"""),"福岡_リモートOK_未経験") -> 福岡_リモートOK_未経験 | C98: =IFERROR(__xludf.DUMMYFUNCTION("""COMPUTED_VALUE"""),0.4) -> 0.4 | D98: =IFERROR(__xludf.DUMMYFUNCTION("""COMPUTED_VALUE"""),"R") -> R | V98: =IFERROR(__xludf.DUMMYFUNCTION("""COMPUTED_VALUE"""),"新大阪駅・本町駅で働く") -> 新大阪駅・本町駅で働く | W98: =IFERROR(__xludf.DUMMYFUNCTION("""COMPUTED_VALUE"""),0.9) -> 0.9 | X98: =IFERROR(__xludf.DUMMYFUNCTION("""COMPUTED_VALUE"""),"R") -> R
V99: =IFERROR(__xludf.DUMMYFUNCTION("""COMPUTED_VALUE"""),"仙台駅で働く") -> 仙台駅で働く | W99: =IFERROR(__xludf.DUMMYFUNCTION("""COMPUTED_VALUE"""),0.2) -> 0.2 | X99: =IFERROR(__xludf.DUMMYFUNCTION("""COMPUTED_VALUE"""),"R") -> R
V100: =IFERROR(__xludf.DUMMYFUNCTION("""COMPUTED_VALUE"""),"大宮浦和で働く") -> 大宮浦和で働く | W100: =IFERROR(__xludf.DUMMYFUNCTION("""COMPUTED_VALUE"""),0.8) -> 0.8 | X100: =IFERROR(__xludf.DUMMYFUNCTION("""COMPUTED_VALUE"""),"R") -> R
V101: =IFERROR(__xludf.DUMMYFUNCTION("""COMPUTED_VALUE"""),"博多区で働く") -> 博多区で働く | W101: =IFERROR(__xludf.DUMMYFUNCTION("""COMPUTED_VALUE"""),0.4) -> 0.4 | X101: =IFERROR(__xludf.DUMMYFUNCTION("""COMPUTED_VALUE"""),"R") -> R
A103: =A93+1 -> 18 | B103: =IFERROR(__xludf.DUMMYFUNCTION("IFERROR(LET( day, TEXT(B$1, ""ddd""), hour, LOOKUP(2, 1/($A103<>""""), $A103), type_A, $A$1, list_data, IFERROR(FILTER({'リスト'!$E$4:$F142, 'リスト'!$O$4:$P142}, ('リスト'!$A$4:$A142=day)*('リスト'!$B$4:$B142=hour)*(('リスト'!$G$4:$G142=""毎週配信"")+('リスト'!$G$4:$G"&"142=type_A))), {"""","""","""",""""}), new_data, IFERROR(FILTER({'新規'!$E$2:$F142, '新規'!$O$2:$P142}, ('新規'!$A$2:$A142=B$1)*('新規'!$B$2:$B142=hour)), {"""","""","""",""""}), special_data, IFERROR(FILTER({'特殊配信マスタ'!$E$2:$F142, '特殊配信マスタ'!$O$2:$P142}, ('特殊配"&"信マスタ'!$A$2:$A142=day)*('特殊配信マスタ'!$B$2:$B142=hour)*('特殊配信マスタ'!$R$2:$R142='特殊配信マスタ'!$S$2:$S142)), {"""","""","""",""""}), combined, VSTACK(list_data, new_data, special_data), FILTER(combined, INDEX(combined, , 1)<>"""", INDEX(combined, , 1)<>0) ), """")"),"☆エンジニア_経験_首都圏版") -> ☆エンジニア_経験_首都圏版 | C103: =IFERROR(__xludf.DUMMYFUNCTION("""COMPUTED_VALUE"""),0.1) -> 0.1 | D103: =IFERROR(__xludf.DUMMYFUNCTION("""COMPUTED_VALUE"""),"部") -> 部 | E103: =IFERROR(__xludf.DUMMYFUNCTION("""COMPUTED_VALUE"""),"内") -> 内 | F103: =SUM(C103:C112) -> 0.5 | G103: =IFERROR(__xludf.DUMMYFUNCTION("IFERROR(LET( day, TEXT(G$1, ""ddd""), hour, LOOKUP(2, 1/($A103<>""""), $A103), type_A, $A$1, list_data, IFERROR(FILTER({'リスト'!$E$4:$F142, 'リスト'!$O$4:$P142}, ('リスト'!$A$4:$A142=day)*('リスト'!$B$4:$B142=hour)*(('リスト'!$G$4:$G142=""毎週配信"")+('リスト'!$G$4:$G"&"142=type_A))), {"""","""","""",""""}), new_data, IFERROR(FILTER({'新規'!$E$2:$F142, '新規'!$O$2:$P142}, ('新規'!$A$2:$A142=G$1)*('新規'!$B$2:$B142=hour)), {"""","""","""",""""}), special_data, IFERROR(FILTER({'特殊配信マスタ'!$E$2:$F142, '特殊配信マスタ'!$O$2:$P142}, ('特殊配"&"信マスタ'!$A$2:$A142=day)*('特殊配信マスタ'!$B$2:$B142=hour)*('特殊配信マスタ'!$R$2:$R142='特殊配信マスタ'!$S$2:$S142)), {"""","""","""",""""}), combined, VSTACK(list_data, new_data, special_data), FILTER(combined, INDEX(combined, , 1)<>"""", INDEX(combined, , 1)<>0) ), """")"),"過去会員×フルリモート×未経験歓迎") -> 過去会員×フルリモート×未経験歓迎 | H103: =IFERROR(__xludf.DUMMYFUNCTION("""COMPUTED_VALUE"""),8.5) -> 8.5 | I103: =IFERROR(__xludf.DUMMYFUNCTION("""COMPUTED_VALUE"""),"部") -> 部 | J103: =IFERROR(__xludf.DUMMYFUNCTION("""COMPUTED_VALUE"""),"石") -> 石 | K103: =SUM(H103:H112) -> 10.6 | L103: =IFERROR(__xludf.DUMMYFUNCTION("IFERROR(LET( day, TEXT(L$1, ""ddd""), hour, LOOKUP(2, 1/($A103<>""""), $A103), type_A, $A$1, list_data, IFERROR(FILTER({'リスト'!$E$4:$F142, 'リスト'!$O$4:$P142}, ('リスト'!$A$4:$A142=day)*('リスト'!$B$4:$B142=hour)*(('リスト'!$G$4:$G142=""毎週配信"")+('リスト'!$G$4:$G"&"142=type_A))), {"""","""","""",""""}), new_data, IFERROR(FILTER({'新規'!$E$2:$F142, '新規'!$O$2:$P142}, ('新規'!$A$2:$A142=L$1)*('新規'!$B$2:$B142=hour)), {"""","""","""",""""}), special_data, IFERROR(FILTER({'特殊配信マスタ'!$E$2:$F142, '特殊配信マスタ'!$O$2:$P142}, ('特殊配"&"信マスタ'!$A$2:$A142=day)*('特殊配信マスタ'!$B$2:$B142=hour)*('特殊配信マスタ'!$R$2:$R142='特殊配信マスタ'!$S$2:$S142)), {"""","""","""",""""}), combined, VSTACK(list_data, new_data, special_data), FILTER(combined, INDEX(combined, , 1)<>"""", INDEX(combined, , 1)<>0) ), """")"),"TP部_働きやすい企業特集") -> TP部_働きやすい企業特集 | M103: =IFERROR(__xludf.DUMMYFUNCTION("""COMPUTED_VALUE"""),1.6) -> 1.6 | N103: =IFERROR(__xludf.DUMMYFUNCTION("""COMPUTED_VALUE"""),"武") -> 武 | O103: =IFERROR(__xludf.DUMMYFUNCTION("""COMPUTED_VALUE"""),"部") -> 部 | P103: =SUM(M103:M112) -> 3.3 | Q103: =IFERROR(__xludf.DUMMYFUNCTION("IFERROR(LET( day, TEXT(Q$1, ""ddd""), hour, LOOKUP(2, 1/($A103<>""""), $A103), type_A, $A$1, list_data, IFERROR(FILTER({'リスト'!$E$4:$F142, 'リスト'!$O$4:$P142}, ('リスト'!$A$4:$A142=day)*('リスト'!$B$4:$B142=hour)*(('リスト'!$G$4:$G142=""毎週配信"")+('リスト'!$G$4:$G"&"142=type_A))), {"""","""","""",""""}), new_data, IFERROR(FILTER({'新規'!$E$2:$F142, '新規'!$O$2:$P142}, ('新規'!$A$2:$A142=Q$1)*('新規'!$B$2:$B142=hour)), {"""","""","""",""""}), special_data, IFERROR(FILTER({'特殊配信マスタ'!$E$2:$F142, '特殊配信マスタ'!$O$2:$P142}, ('特殊配"&"信マスタ'!$A$2:$A142=day)*('特殊配信マスタ'!$B$2:$B142=hour)*('特殊配信マスタ'!$R$2:$R142='特殊配信マスタ'!$S$2:$S142)), {"""","""","""",""""}), combined, VSTACK(list_data, new_data, special_data), FILTER(combined, INDEX(combined, , 1)<>"""", INDEX(combined, , 1)<>0) ), """")"),"") | U103: =SUM(R103:R112) -> 0 | V103: =IFERROR(__xludf.DUMMYFUNCTION("IFERROR(LET( day, TEXT(V$1, ""ddd""), hour, LOOKUP(2, 1/($A103<>""""), $A103), type_A, $A$1, list_data, IFERROR(FILTER({'リスト'!$E$4:$F142, 'リスト'!$O$4:$P142}, ('リスト'!$A$4:$A142=day)*('リスト'!$B$4:$B142=hour)*(('リスト'!$G$4:$G142=""毎週配信"")+('リスト'!$G$4:$G"&"142=type_A))), {"""","""","""",""""}), new_data, IFERROR(FILTER({'新規'!$E$2:$F142, '新規'!$O$2:$P142}, ('新規'!$A$2:$A142=V$1)*('新規'!$B$2:$B142=hour)), {"""","""","""",""""}), special_data, IFERROR(FILTER({'特殊配信マスタ'!$E$2:$F142, '特殊配信マスタ'!$O$2:$P142}, ('特殊配"&"信マスタ'!$A$2:$A142=day)*('特殊配信マスタ'!$B$2:$B142=hour)*('特殊配信マスタ'!$R$2:$R142='特殊配信マスタ'!$S$2:$S142)), {"""","""","""",""""}), combined, VSTACK(list_data, new_data, special_data), FILTER(combined, INDEX(combined, , 1)<>"""", INDEX(combined, , 1)<>0) ), """")"),"関西限定事務求人特集") -> 関西限定事務求人特集 | W103: =IFERROR(__xludf.DUMMYFUNCTION("""COMPUTED_VALUE"""),0.6) -> 0.6 | X103: =IFERROR(__xludf.DUMMYFUNCTION("""COMPUTED_VALUE"""),"R") -> R | Z103: =SUM(W103:W112) -> 3.1 | AA103: =IFERROR(__xludf.DUMMYFUNCTION("IFERROR(LET( day, TEXT(AA$1, ""ddd""), hour, LOOKUP(2, 1/($A103<>""""), $A103), type_A, $A$1, list_data, IFERROR(FILTER({'リスト'!$E$4:$F142, 'リスト'!$O$4:$P142}, ('リスト'!$A$4:$A142=day)*('リスト'!$B$4:$B142=hour)*(('リスト'!$G$4:$G142=""毎週配信"")+('リスト'!$G$4:$"&"G142=type_A))), {"""","""","""",""""}), new_data, IFERROR(FILTER({'新規'!$E$2:$F142, '新規'!$O$2:$P142}, ('新規'!$A$2:$A142=AA$1)*('新規'!$B$2:$B142=hour)), {"""","""","""",""""}), special_data, IFERROR(FILTER({'特殊配信マスタ'!$E$2:$F142, '特殊配信マスタ'!$O$2:$P142}, ('特"&"殊配信マスタ'!$A$2:$A142=day)*('特殊配信マスタ'!$B$2:$B142=hour)*('特殊配信マスタ'!$R$2:$R142='特殊配信マスタ'!$S$2:$S142)), {"""","""","""",""""}), combined, VSTACK(list_data, new_data, special_data), FILTER(combined, INDEX(combined, , 1)<>"""", INDEX(combined, , 1)<>0) ), """&""")"),"コスメ業界_希望") -> コスメ業界_希望 | AB103: =IFERROR(__xludf.DUMMYFUNCTION("""COMPUTED_VALUE"""),0.3) -> 0.3 | AC103: =IFERROR(__xludf.DUMMYFUNCTION("""COMPUTED_VALUE"""),"部") -> 部 | AD103: =IFERROR(__xludf.DUMMYFUNCTION("""COMPUTED_VALUE"""),"石") -> 石 | AE103: =SUM(AB103:AB112) -> 3.5 | AF103: =IFERROR(__xludf.DUMMYFUNCTION("IFERROR(LET( day, TEXT(AF$1, ""ddd""), hour, LOOKUP(2, 1/($A103<>""""), $A103), type_A, $A$1, list_data, IFERROR(FILTER({'リスト'!$E$4:$F142, 'リスト'!$O$4:$P142}, ('リスト'!$A$4:$A142=day)*('リスト'!$B$4:$B142=hour)*(('リスト'!$G$4:$G142=""毎週配信"")+('リスト'!$G$4:$"&"G142=type_A))), {"""","""","""",""""}), new_data, IFERROR(FILTER({'新規'!$E$2:$F142, '新規'!$O$2:$P142}, ('新規'!$A$2:$A142=AF$1)*('新規'!$B$2:$B142=hour)), {"""","""","""",""""}), special_data, IFERROR(FILTER({'特殊配信マスタ'!$E$2:$F142, '特殊配信マスタ'!$O$2:$P142}, ('特"&"殊配信マスタ'!$A$2:$A142=day)*('特殊配信マスタ'!$B$2:$B142=hour)*('特殊配信マスタ'!$R$2:$R142='特殊配信マスタ'!$S$2:$S142)), {"""","""","""",""""}), combined, VSTACK(list_data, new_data, special_data), FILTER(combined, INDEX(combined, , 1)<>"""", INDEX(combined, , 1)<>0) ), """&""")"),"自己PR不要_フルリモート") -> 自己PR不要_フルリモート | AG103: =IFERROR(__xludf.DUMMYFUNCTION("""COMPUTED_VALUE"""),2.2) -> 2.2 | AH103: =IFERROR(__xludf.DUMMYFUNCTION("""COMPUTED_VALUE"""),"R") -> R | AJ103: =SUM(AG103:AG112) -> 3.6
B104: =IFERROR(__xludf.DUMMYFUNCTION("""COMPUTED_VALUE"""),"☆エンジニア_未経験_首都圏版") -> ☆エンジニア_未経験_首都圏版 | C104: =IFERROR(__xludf.DUMMYFUNCTION("""COMPUTED_VALUE"""),0.4) -> 0.4 | D104: =IFERROR(__xludf.DUMMYFUNCTION("""COMPUTED_VALUE"""),"部") -> 部 | E104: =IFERROR(__xludf.DUMMYFUNCTION("""COMPUTED_VALUE"""),"内") -> 内 | G104: =IFERROR(__xludf.DUMMYFUNCTION("""COMPUTED_VALUE"""),"☆営業_経験_首都圏版") -> ☆営業_経験_首都圏版 | H104: =IFERROR(__xludf.DUMMYFUNCTION("""COMPUTED_VALUE"""),0.1) -> 0.1 | I104: =IFERROR(__xludf.DUMMYFUNCTION("""COMPUTED_VALUE"""),"部") -> 部 | J104: =IFERROR(__xludf.DUMMYFUNCTION("""COMPUTED_VALUE"""),"荒") -> 荒 | L104: =IFERROR(__xludf.DUMMYFUNCTION("""COMPUTED_VALUE"""),"☆販サ_経験_35歳以上_首都圏版") -> ☆販サ_経験_35歳以上_首都圏版 | M104: =IFERROR(__xludf.DUMMYFUNCTION("""COMPUTED_VALUE"""),0.1) -> 0.1 | N104: =IFERROR(__xludf.DUMMYFUNCTION("""COMPUTED_VALUE"""),"部") -> 部 | O104: =IFERROR(__xludf.DUMMYFUNCTION("""COMPUTED_VALUE"""),"平") -> 平 | V104: =IFERROR(__xludf.DUMMYFUNCTION("""COMPUTED_VALUE"""),"賞与3ヶ月以上×リモート_ランキング") -> 賞与3ヶ月以上×リモート_ランキング | W104: =IFERROR(__xludf.DUMMYFUNCTION("""COMPUTED_VALUE"""),2.5) -> 2.5 | X104: =IFERROR(__xludf.DUMMYFUNCTION("""COMPUTED_VALUE"""),"R") -> R | AA104: =IFERROR(__xludf.DUMMYFUNCTION("""COMPUTED_VALUE"""),"プライベート重視_35歳以上") -> プライベート重視_35歳以上 | AB104: =IFERROR(__xludf.DUMMYFUNCTION("""COMPUTED_VALUE"""),0.9) -> 0.9 | AC104: =IFERROR(__xludf.DUMMYFUNCTION("""COMPUTED_VALUE"""),"R") -> R | AF104: =IFERROR(__xludf.DUMMYFUNCTION("""COMPUTED_VALUE"""),"事務_経験_35歳以上_首都圏版") -> 事務_経験_35歳以上_首都圏版 | AG104: =IFERROR(__xludf.DUMMYFUNCTION("""COMPUTED_VALUE"""),0.1) -> 0.1 | AH104: =IFERROR(__xludf.DUMMYFUNCTION("""COMPUTED_VALUE"""),"R") -> R
G105: =IFERROR(__xludf.DUMMYFUNCTION("""COMPUTED_VALUE"""),"☆営業_未経験_首都圏版") -> ☆営業_未経験_首都圏版 | H105: =IFERROR(__xludf.DUMMYFUNCTION("""COMPUTED_VALUE"""),0.3) -> 0.3 | I105: =IFERROR(__xludf.DUMMYFUNCTION("""COMPUTED_VALUE"""),"部") -> 部 | J105: =IFERROR(__xludf.DUMMYFUNCTION("""COMPUTED_VALUE"""),"荒") -> 荒 | L105: =IFERROR(__xludf.DUMMYFUNCTION("""COMPUTED_VALUE"""),"☆販サ_経験_35歳以上_全国版") -> ☆販サ_経験_35歳以上_全国版 | M105: =IFERROR(__xludf.DUMMYFUNCTION("""COMPUTED_VALUE"""),0.2) -> 0.2 | N105: =IFERROR(__xludf.DUMMYFUNCTION("""COMPUTED_VALUE"""),"部") -> 部 | O105: =IFERROR(__xludf.DUMMYFUNCTION("""COMPUTED_VALUE"""),"平") -> 平 | AA105: =IFERROR(__xludf.DUMMYFUNCTION("""COMPUTED_VALUE"""),"月曜日はリモート×フレックスで働く") -> 月曜日はリモート×フレックスで働く | AB105: =IFERROR(__xludf.DUMMYFUNCTION("""COMPUTED_VALUE"""),2.3) -> 2.3 | AC105: =IFERROR(__xludf.DUMMYFUNCTION("""COMPUTED_VALUE"""),"R") -> R | AF105: =IFERROR(__xludf.DUMMYFUNCTION("""COMPUTED_VALUE"""),"事務_未経験_35歳以上_首都圏版") -> 事務_未経験_35歳以上_首都圏版 | AG105: =IFERROR(__xludf.DUMMYFUNCTION("""COMPUTED_VALUE"""),0.1) -> 0.1 | AH105: =IFERROR(__xludf.DUMMYFUNCTION("""COMPUTED_VALUE"""),"R") -> R
G106: =IFERROR(__xludf.DUMMYFUNCTION("""COMPUTED_VALUE"""),"駅直結_事務") -> 駅直結_事務 | H106: =IFERROR(__xludf.DUMMYFUNCTION("""COMPUTED_VALUE"""),1.7) -> 1.7 | I106: =IFERROR(__xludf.DUMMYFUNCTION("""COMPUTED_VALUE"""),"R") -> R | L106: =IFERROR(__xludf.DUMMYFUNCTION("""COMPUTED_VALUE"""),"☆販サ_経験_首都圏版") -> ☆販サ_経験_首都圏版 | M106: =IFERROR(__xludf.DUMMYFUNCTION("""COMPUTED_VALUE"""),0.2) -> 0.2 | N106: =IFERROR(__xludf.DUMMYFUNCTION("""COMPUTED_VALUE"""),"部") -> 部 | O106: =IFERROR(__xludf.DUMMYFUNCTION("""COMPUTED_VALUE"""),"平") -> 平 | AF106: =IFERROR(__xludf.DUMMYFUNCTION("""COMPUTED_VALUE"""),"事務_未経験_休眠会員_首都圏版") -> 事務_未経験_休眠会員_首都圏版 | AG106: =IFERROR(__xludf.DUMMYFUNCTION("""COMPUTED_VALUE"""),1.0) -> 1 | AH106: =IFERROR(__xludf.DUMMYFUNCTION("""COMPUTED_VALUE"""),"R") -> R
L107: =IFERROR(__xludf.DUMMYFUNCTION("""COMPUTED_VALUE"""),"☆販サ_経験_全国版") -> ☆販サ_経験_全国版 | M107: =IFERROR(__xludf.DUMMYFUNCTION("""COMPUTED_VALUE"""),0.3) -> 0.3 | N107: =IFERROR(__xludf.DUMMYFUNCTION("""COMPUTED_VALUE"""),"部") -> 部 | O107: =IFERROR(__xludf.DUMMYFUNCTION("""COMPUTED_VALUE"""),"平") -> 平 | AF107: =IFERROR(__xludf.DUMMYFUNCTION("""COMPUTED_VALUE"""),"中国地方で働く") -> 中国地方で働く | AG107: =IFERROR(__xludf.DUMMYFUNCTION("""COMPUTED_VALUE"""),0.2) -> 0.2 | AH107: =IFERROR(__xludf.DUMMYFUNCTION("""COMPUTED_VALUE"""),"R") -> R
L108: =IFERROR(__xludf.DUMMYFUNCTION("""COMPUTED_VALUE"""),"☆販サ_未経験_35歳以上_首都圏版") -> ☆販サ_未経験_35歳以上_首都圏版 | M108: =IFERROR(__xludf.DUMMYFUNCTION("""COMPUTED_VALUE"""),0.2) -> 0.2 | N108: =IFERROR(__xludf.DUMMYFUNCTION("""COMPUTED_VALUE"""),"部") -> 部 | O108: =IFERROR(__xludf.DUMMYFUNCTION("""COMPUTED_VALUE"""),"平") -> 平
L109: =IFERROR(__xludf.DUMMYFUNCTION("""COMPUTED_VALUE"""),"☆販サ_未経験_首都圏版") -> ☆販サ_未経験_首都圏版 | M109: =IFERROR(__xludf.DUMMYFUNCTION("""COMPUTED_VALUE"""),0.3) -> 0.3 | N109: =IFERROR(__xludf.DUMMYFUNCTION("""COMPUTED_VALUE"""),"部") -> 部 | O109: =IFERROR(__xludf.DUMMYFUNCTION("""COMPUTED_VALUE"""),"平") -> 平
L110: =IFERROR(__xludf.DUMMYFUNCTION("""COMPUTED_VALUE"""),"40代事務ランキング") -> 40代事務ランキング | M110: =IFERROR(__xludf.DUMMYFUNCTION("""COMPUTED_VALUE"""),0.4) -> 0.4 | N110: =IFERROR(__xludf.DUMMYFUNCTION("""COMPUTED_VALUE"""),"石") -> 石 | O110: =IFERROR(__xludf.DUMMYFUNCTION("""COMPUTED_VALUE"""),"部") -> 部
A113: =A103+1 -> 19 | B113: =IFERROR(__xludf.DUMMYFUNCTION("IFERROR(LET( day, TEXT(B$1, ""ddd""), hour, LOOKUP(2, 1/($A113<>""""), $A113), type_A, $A$1, list_data, IFERROR(FILTER({'リスト'!$E$4:$F142, 'リスト'!$O$4:$P142}, ('リスト'!$A$4:$A142=day)*('リスト'!$B$4:$B142=hour)*(('リスト'!$G$4:$G142=""毎週配信"")+('リスト'!$G$4:$G"&"142=type_A))), {"""","""","""",""""}), new_data, IFERROR(FILTER({'新規'!$E$2:$F142, '新規'!$O$2:$P142}, ('新規'!$A$2:$A142=B$1)*('新規'!$B$2:$B142=hour)), {"""","""","""",""""}), special_data, IFERROR(FILTER({'特殊配信マスタ'!$E$2:$F142, '特殊配信マスタ'!$O$2:$P142}, ('特殊配"&"信マスタ'!$A$2:$A142=day)*('特殊配信マスタ'!$B$2:$B142=hour)*('特殊配信マスタ'!$R$2:$R142='特殊配信マスタ'!$S$2:$S142)), {"""","""","""",""""}), combined, VSTACK(list_data, new_data, special_data), FILTER(combined, INDEX(combined, , 1)<>"""", INDEX(combined, , 1)<>0) ), """")"),"35歳以上向け_関西 A") -> 35歳以上向け_関西 A | C113: =IFERROR(__xludf.DUMMYFUNCTION("""COMPUTED_VALUE"""),0.3) -> 0.3 | D113: =IFERROR(__xludf.DUMMYFUNCTION("""COMPUTED_VALUE"""),"R") -> R | F113: =SUM(C113:C122) -> 13.4 | G113: =IFERROR(__xludf.DUMMYFUNCTION("IFERROR(LET( day, TEXT(G$1, ""ddd""), hour, LOOKUP(2, 1/($A113<>""""), $A113), type_A, $A$1, list_data, IFERROR(FILTER({'リスト'!$E$4:$F142, 'リスト'!$O$4:$P142}, ('リスト'!$A$4:$A142=day)*('リスト'!$B$4:$B142=hour)*(('リスト'!$G$4:$G142=""毎週配信"")+('リスト'!$G$4:$G"&"142=type_A))), {"""","""","""",""""}), new_data, IFERROR(FILTER({'新規'!$E$2:$F142, '新規'!$O$2:$P142}, ('新規'!$A$2:$A142=G$1)*('新規'!$B$2:$B142=hour)), {"""","""","""",""""}), special_data, IFERROR(FILTER({'特殊配信マスタ'!$E$2:$F142, '特殊配信マスタ'!$O$2:$P142}, ('特殊配"&"信マスタ'!$A$2:$A142=day)*('特殊配信マスタ'!$B$2:$B142=hour)*('特殊配信マスタ'!$R$2:$R142='特殊配信マスタ'!$S$2:$S142)), {"""","""","""",""""}), combined, VSTACK(list_data, new_data, special_data), FILTER(combined, INDEX(combined, , 1)<>"""", INDEX(combined, , 1)<>0) ), """")"),"フルリモート×正社員") -> フルリモート×正社員 | H113: =IFERROR(__xludf.DUMMYFUNCTION("""COMPUTED_VALUE"""),3.0) -> 3 | I113: =IFERROR(__xludf.DUMMYFUNCTION("""COMPUTED_VALUE"""),"R") -> R | K113: =SUM(H113:H122) -> 6.5 | L113: =IFERROR(__xludf.DUMMYFUNCTION("IFERROR(LET( day, TEXT(L$1, ""ddd""), hour, LOOKUP(2, 1/($A113<>""""), $A113), type_A, $A$1, list_data, IFERROR(FILTER({'リスト'!$E$4:$F142, 'リスト'!$O$4:$P142}, ('リスト'!$A$4:$A142=day)*('リスト'!$B$4:$B142=hour)*(('リスト'!$G$4:$G142=""毎週配信"")+('リスト'!$G$4:$G"&"142=type_A))), {"""","""","""",""""}), new_data, IFERROR(FILTER({'新規'!$E$2:$F142, '新規'!$O$2:$P142}, ('新規'!$A$2:$A142=L$1)*('新規'!$B$2:$B142=hour)), {"""","""","""",""""}), special_data, IFERROR(FILTER({'特殊配信マスタ'!$E$2:$F142, '特殊配信マスタ'!$O$2:$P142}, ('特殊配"&"信マスタ'!$A$2:$A142=day)*('特殊配信マスタ'!$B$2:$B142=hour)*('特殊配信マスタ'!$R$2:$R142='特殊配信マスタ'!$S$2:$S142)), {"""","""","""",""""}), combined, VSTACK(list_data, new_data, special_data), FILTER(combined, INDEX(combined, , 1)<>"""", INDEX(combined, , 1)<>0) ), """")"),"埼玉_路線") -> 埼玉_路線 | M113: =IFERROR(__xludf.DUMMYFUNCTION("""COMPUTED_VALUE"""),0.7) -> 0.7 | N113: =IFERROR(__xludf.DUMMYFUNCTION("""COMPUTED_VALUE"""),"部") -> 部 | O113: =IFERROR(__xludf.DUMMYFUNCTION("""COMPUTED_VALUE"""),"内") -> 内 | P113: =SUM(M113:M122) -> 4.3 | Q113: =IFERROR(__xludf.DUMMYFUNCTION("IFERROR(LET( day, TEXT(Q$1, ""ddd""), hour, LOOKUP(2, 1/($A113<>""""), $A113), type_A, $A$1, list_data, IFERROR(FILTER({'リスト'!$E$4:$F142, 'リスト'!$O$4:$P142}, ('リスト'!$A$4:$A142=day)*('リスト'!$B$4:$B142=hour)*(('リスト'!$G$4:$G142=""毎週配信"")+('リスト'!$G$4:$G"&"142=type_A))), {"""","""","""",""""}), new_data, IFERROR(FILTER({'新規'!$E$2:$F142, '新規'!$O$2:$P142}, ('新規'!$A$2:$A142=Q$1)*('新規'!$B$2:$B142=hour)), {"""","""","""",""""}), special_data, IFERROR(FILTER({'特殊配信マスタ'!$E$2:$F142, '特殊配信マスタ'!$O$2:$P142}, ('特殊配"&"信マスタ'!$A$2:$A142=day)*('特殊配信マスタ'!$B$2:$B142=hour)*('特殊配信マスタ'!$R$2:$R142='特殊配信マスタ'!$S$2:$S142)), {"""","""","""",""""}), combined, VSTACK(list_data, new_data, special_data), FILTER(combined, INDEX(combined, , 1)<>"""", INDEX(combined, , 1)<>0) ), """")"),"TP部_リモート×未経験OKの求人特集") -> TP部_リモート×未経験OKの求人特集 | R113: =IFERROR(__xludf.DUMMYFUNCTION("""COMPUTED_VALUE"""),1.9) -> 1.9 | S113: =IFERROR(__xludf.DUMMYFUNCTION("""COMPUTED_VALUE"""),"部") -> 部 | T113: =IFERROR(__xludf.DUMMYFUNCTION("""COMPUTED_VALUE"""),"石") -> 石 | U113: =SUM(R113:R122) -> 3.4 | V113: =IFERROR(__xludf.DUMMYFUNCTION("IFERROR(LET( day, TEXT(V$1, ""ddd""), hour, LOOKUP(2, 1/($A113<>""""), $A113), type_A, $A$1, list_data, IFERROR(FILTER({'リスト'!$E$4:$F142, 'リスト'!$O$4:$P142}, ('リスト'!$A$4:$A142=day)*('リスト'!$B$4:$B142=hour)*(('リスト'!$G$4:$G142=""毎週配信"")+('リスト'!$G$4:$G"&"142=type_A))), {"""","""","""",""""}), new_data, IFERROR(FILTER({'新規'!$E$2:$F142, '新規'!$O$2:$P142}, ('新規'!$A$2:$A142=V$1)*('新規'!$B$2:$B142=hour)), {"""","""","""",""""}), special_data, IFERROR(FILTER({'特殊配信マスタ'!$E$2:$F142, '特殊配信マスタ'!$O$2:$P142}, ('特殊配"&"信マスタ'!$A$2:$A142=day)*('特殊配信マスタ'!$B$2:$B142=hour)*('特殊配信マスタ'!$R$2:$R142='特殊配信マスタ'!$S$2:$S142)), {"""","""","""",""""}), combined, VSTACK(list_data, new_data, special_data), FILTER(combined, INDEX(combined, , 1)<>"""", INDEX(combined, , 1)<>0) ), """")"),"美容業界×未経験歓迎") -> 美容業界×未経験歓迎 | W113: =IFERROR(__xludf.DUMMYFUNCTION("""COMPUTED_VALUE"""),0.3) -> 0.3 | X113: =IFERROR(__xludf.DUMMYFUNCTION("""COMPUTED_VALUE"""),"部") -> 部 | Y113: =IFERROR(__xludf.DUMMYFUNCTION("""COMPUTED_VALUE"""),"石") -> 石 | Z113: =SUM(W113:W122) -> 7 | AA113: =IFERROR(__xludf.DUMMYFUNCTION("IFERROR(LET( day, TEXT(AA$1, ""ddd""), hour, LOOKUP(2, 1/($A113<>""""), $A113), type_A, $A$1, list_data, IFERROR(FILTER({'リスト'!$E$4:$F142, 'リスト'!$O$4:$P142}, ('リスト'!$A$4:$A142=day)*('リスト'!$B$4:$B142=hour)*(('リスト'!$G$4:$G142=""毎週配信"")+('リスト'!$G$4:$"&"G142=type_A))), {"""","""","""",""""}), new_data, IFERROR(FILTER({'新規'!$E$2:$F142, '新規'!$O$2:$P142}, ('新規'!$A$2:$A142=AA$1)*('新規'!$B$2:$B142=hour)), {"""","""","""",""""}), special_data, IFERROR(FILTER({'特殊配信マスタ'!$E$2:$F142, '特殊配信マスタ'!$O$2:$P142}, ('特"&"殊配信マスタ'!$A$2:$A142=day)*('特殊配信マスタ'!$B$2:$B142=hour)*('特殊配信マスタ'!$R$2:$R142='特殊配信マスタ'!$S$2:$S142)), {"""","""","""",""""}), combined, VSTACK(list_data, new_data, special_data), FILTER(combined, INDEX(combined, , 1)<>"""", INDEX(combined, , 1)<>0) ), """&""")"),"☆TP部メルマガ") -> ☆TP部メルマガ | AB113: =IFERROR(__xludf.DUMMYFUNCTION("""COMPUTED_VALUE"""),1.3) -> 1.3 | AC113: =IFERROR(__xludf.DUMMYFUNCTION("""COMPUTED_VALUE"""),"荒") -> 荒 | AD113: =IFERROR(__xludf.DUMMYFUNCTION("""COMPUTED_VALUE"""),"平") -> 平 | AE113: =SUM(AB113:AB122) -> 6.1 | AF113: =IFERROR(__xludf.DUMMYFUNCTION("IFERROR(LET( day, TEXT(AF$1, ""ddd""), hour, LOOKUP(2, 1/($A113<>""""), $A113), type_A, $A$1, list_data, IFERROR(FILTER({'リスト'!$E$4:$F142, 'リスト'!$O$4:$P142}, ('リスト'!$A$4:$A142=day)*('リスト'!$B$4:$B142=hour)*(('リスト'!$G$4:$G142=""毎週配信"")+('リスト'!$G$4:$"&"G142=type_A))), {"""","""","""",""""}), new_data, IFERROR(FILTER({'新規'!$E$2:$F142, '新規'!$O$2:$P142}, ('新規'!$A$2:$A142=AF$1)*('新規'!$B$2:$B142=hour)), {"""","""","""",""""}), special_data, IFERROR(FILTER({'特殊配信マスタ'!$E$2:$F142, '特殊配信マスタ'!$O$2:$P142}, ('特"&"殊配信マスタ'!$A$2:$A142=day)*('特殊配信マスタ'!$B$2:$B142=hour)*('特殊配信マスタ'!$R$2:$R142='特殊配信マスタ'!$S$2:$S142)), {"""","""","""",""""}), combined, VSTACK(list_data, new_data, special_data), FILTER(combined, INDEX(combined, , 1)<>"""", INDEX(combined, , 1)<>0) ), """&""")"),"超好条件_営業") -> 超好条件_営業 | AG113: =IFERROR(__xludf.DUMMYFUNCTION("""COMPUTED_VALUE"""),0.9) -> 0.9 | AH113: =IFERROR(__xludf.DUMMYFUNCTION("""COMPUTED_VALUE"""),"部") -> 部 | AI113: =IFERROR(__xludf.DUMMYFUNCTION("""COMPUTED_VALUE"""),"石") -> 石 | AJ113: =SUM(AG113:AG122) -> 3.4
B114: =IFERROR(__xludf.DUMMYFUNCTION("""COMPUTED_VALUE"""),"40代ラスト転職") -> 40代ラスト転職 | C114: =IFERROR(__xludf.DUMMYFUNCTION("""COMPUTED_VALUE"""),0.9) -> 0.9 | D114: =IFERROR(__xludf.DUMMYFUNCTION("""COMPUTED_VALUE"""),"R") -> R | G114: =IFERROR(__xludf.DUMMYFUNCTION("""COMPUTED_VALUE"""),"渋谷・恵比寿勤務_事務") -> 渋谷・恵比寿勤務_事務 | H114: =IFERROR(__xludf.DUMMYFUNCTION("""COMPUTED_VALUE"""),1.2) -> 1.2 | I114: =IFERROR(__xludf.DUMMYFUNCTION("""COMPUTED_VALUE"""),"R") -> R | L114: =IFERROR(__xludf.DUMMYFUNCTION("""COMPUTED_VALUE"""),"神奈川_路線") -> 神奈川_路線 | M114: =IFERROR(__xludf.DUMMYFUNCTION("""COMPUTED_VALUE"""),0.9) -> 0.9 | N114: =IFERROR(__xludf.DUMMYFUNCTION("""COMPUTED_VALUE"""),"部") -> 部 | O114: =IFERROR(__xludf.DUMMYFUNCTION("""COMPUTED_VALUE"""),"内") -> 内 | Q114: =IFERROR(__xludf.DUMMYFUNCTION("""COMPUTED_VALUE"""),"経験_アパレル・コスメ") -> 経験_アパレル・コスメ | R114: =IFERROR(__xludf.DUMMYFUNCTION("""COMPUTED_VALUE"""),0.2) -> 0.2 | S114: =IFERROR(__xludf.DUMMYFUNCTION("""COMPUTED_VALUE"""),"R") -> R | V114: =IFERROR(__xludf.DUMMYFUNCTION("""COMPUTED_VALUE"""),"フルリモート×未経験歓迎") -> フルリモート×未経験歓迎 | W114: =IFERROR(__xludf.DUMMYFUNCTION("""COMPUTED_VALUE"""),6.7) -> 6.7 | X114: =IFERROR(__xludf.DUMMYFUNCTION("""COMPUTED_VALUE"""),"R") -> R | AA114: =IFERROR(__xludf.DUMMYFUNCTION("""COMPUTED_VALUE"""),"☆TP部メルマガ_未就業") -> ☆TP部メルマガ_未就業 | AB114: =IFERROR(__xludf.DUMMYFUNCTION("""COMPUTED_VALUE"""),0.5) -> 0.5 | AC114: =IFERROR(__xludf.DUMMYFUNCTION("""COMPUTED_VALUE"""),"荒") -> 荒 | AD114: =IFERROR(__xludf.DUMMYFUNCTION("""COMPUTED_VALUE"""),"平") -> 平 | AF114: =IFERROR(__xludf.DUMMYFUNCTION("""COMPUTED_VALUE"""),"自己PR不要_35歳以上") -> 自己PR不要_35歳以上 | AG114: =IFERROR(__xludf.DUMMYFUNCTION("""COMPUTED_VALUE"""),0.4) -> 0.4 | AH114: =IFERROR(__xludf.DUMMYFUNCTION("""COMPUTED_VALUE"""),"R") -> R
B115: =IFERROR(__xludf.DUMMYFUNCTION("""COMPUTED_VALUE"""),"TP部_営業_現住所") -> TP部_営業_現住所 | C115: =IFERROR(__xludf.DUMMYFUNCTION("""COMPUTED_VALUE"""),2.0) -> 2 | D115: =IFERROR(__xludf.DUMMYFUNCTION("""COMPUTED_VALUE"""),"R") -> R | G115: =IFERROR(__xludf.DUMMYFUNCTION("""COMPUTED_VALUE"""),"未経験_研修・資格_エンジニア系_首都圏") -> 未経験_研修・資格_エンジニア系_首都圏 | H115: =IFERROR(__xludf.DUMMYFUNCTION("""COMPUTED_VALUE"""),0.3) -> 0.3 | I115: =IFERROR(__xludf.DUMMYFUNCTION("""COMPUTED_VALUE"""),"R") -> R | L115: =IFERROR(__xludf.DUMMYFUNCTION("""COMPUTED_VALUE"""),"千葉_路線") -> 千葉_路線 | M115: =IFERROR(__xludf.DUMMYFUNCTION("""COMPUTED_VALUE"""),0.6) -> 0.6 | N115: =IFERROR(__xludf.DUMMYFUNCTION("""COMPUTED_VALUE"""),"部") -> 部 | O115: =IFERROR(__xludf.DUMMYFUNCTION("""COMPUTED_VALUE"""),"内") -> 内 | Q115: =IFERROR(__xludf.DUMMYFUNCTION("""COMPUTED_VALUE"""),"経験_一般事務") -> 経験_一般事務 | R115: =IFERROR(__xludf.DUMMYFUNCTION("""COMPUTED_VALUE"""),0.7) -> 0.7 | S115: =IFERROR(__xludf.DUMMYFUNCTION("""COMPUTED_VALUE"""),"R") -> R | AA115: =IFERROR(__xludf.DUMMYFUNCTION("""COMPUTED_VALUE"""),"ランキング_販サ（フロント）_希望") -> ランキング_販サ（フロント）_希望 | AB115: =IFERROR(__xludf.DUMMYFUNCTION("""COMPUTED_VALUE"""),0.3) -> 0.3 | AC115: =IFERROR(__xludf.DUMMYFUNCTION("""COMPUTED_VALUE"""),"R") -> R | AF115: =IFERROR(__xludf.DUMMYFUNCTION("""COMPUTED_VALUE"""),"関西‗超好条件_事務") -> 関西‗超好条件_事務 | AG115: =IFERROR(__xludf.DUMMYFUNCTION("""COMPUTED_VALUE"""),0.7) -> 0.7 | AH115: =IFERROR(__xludf.DUMMYFUNCTION("""COMPUTED_VALUE"""),"部") -> 部 | AI115: =IFERROR(__xludf.DUMMYFUNCTION("""COMPUTED_VALUE"""),"武") -> 武
B116: =IFERROR(__xludf.DUMMYFUNCTION("""COMPUTED_VALUE"""),"フルリモート_全国_エンジニア") -> フルリモート_全国_エンジニア | C116: =IFERROR(__xludf.DUMMYFUNCTION("""COMPUTED_VALUE"""),1.3) -> 1.3 | D116: =IFERROR(__xludf.DUMMYFUNCTION("""COMPUTED_VALUE"""),"R") -> R | G116: =IFERROR(__xludf.DUMMYFUNCTION("""COMPUTED_VALUE"""),"六本木勤務") -> 六本木勤務 | H116: =IFERROR(__xludf.DUMMYFUNCTION("""COMPUTED_VALUE"""),2.0) -> 2 | I116: =IFERROR(__xludf.DUMMYFUNCTION("""COMPUTED_VALUE"""),"R") -> R | L116: =IFERROR(__xludf.DUMMYFUNCTION("""COMPUTED_VALUE"""),"大阪_路線") -> 大阪_路線 | M116: =IFERROR(__xludf.DUMMYFUNCTION("""COMPUTED_VALUE"""),0.7) -> 0.7 | N116: =IFERROR(__xludf.DUMMYFUNCTION("""COMPUTED_VALUE"""),"部") -> 部 | O116: =IFERROR(__xludf.DUMMYFUNCTION("""COMPUTED_VALUE"""),"内") -> 内 | Q116: =IFERROR(__xludf.DUMMYFUNCTION("""COMPUTED_VALUE"""),"経験_営業") -> 経験_営業 | R116: =IFERROR(__xludf.DUMMYFUNCTION("""COMPUTED_VALUE"""),0.6) -> 0.6 | S116: =IFERROR(__xludf.DUMMYFUNCTION("""COMPUTED_VALUE"""),"R") -> R | AA116: =IFERROR(__xludf.DUMMYFUNCTION("""COMPUTED_VALUE"""),"上場_営業経験") -> 上場_営業経験 | AB116: =IFERROR(__xludf.DUMMYFUNCTION("""COMPUTED_VALUE"""),0.7) -> 0.7 | AC116: =IFERROR(__xludf.DUMMYFUNCTION("""COMPUTED_VALUE"""),"R") -> R | AF116: =IFERROR(__xludf.DUMMYFUNCTION("""COMPUTED_VALUE"""),"全国_超好条件_事務") -> 全国_超好条件_事務 | AG116: =IFERROR(__xludf.DUMMYFUNCTION("""COMPUTED_VALUE"""),1.0) -> 1 | AH116: =IFERROR(__xludf.DUMMYFUNCTION("""COMPUTED_VALUE"""),"R") -> R
B117: =IFERROR(__xludf.DUMMYFUNCTION("""COMPUTED_VALUE"""),"フルリモート_全国_営業") -> フルリモート_全国_営業 | C117: =IFERROR(__xludf.DUMMYFUNCTION("""COMPUTED_VALUE"""),1.8) -> 1.8 | D117: =IFERROR(__xludf.DUMMYFUNCTION("""COMPUTED_VALUE"""),"R") -> R | L117: =IFERROR(__xludf.DUMMYFUNCTION("""COMPUTED_VALUE"""),"東京_路線_事務") -> 東京_路線_事務 | M117: =IFERROR(__xludf.DUMMYFUNCTION("""COMPUTED_VALUE"""),1.0) -> 1 | N117: =IFERROR(__xludf.DUMMYFUNCTION("""COMPUTED_VALUE"""),"部") -> 部 | O117: =IFERROR(__xludf.DUMMYFUNCTION("""COMPUTED_VALUE"""),"内") -> 内 | AA117: =IFERROR(__xludf.DUMMYFUNCTION("""COMPUTED_VALUE"""),"上場_事務経験") -> 上場_事務経験 | AB117: =IFERROR(__xludf.DUMMYFUNCTION("""COMPUTED_VALUE"""),1.9) -> 1.9 | AC117: =IFERROR(__xludf.DUMMYFUNCTION("""COMPUTED_VALUE"""),"R") -> R | AF117: =IFERROR(__xludf.DUMMYFUNCTION("""COMPUTED_VALUE"""),"超好条件_エンジニア") -> 超好条件_エンジニア | AG117: =IFERROR(__xludf.DUMMYFUNCTION("""COMPUTED_VALUE"""),0.4) -> 0.4 | AH117: =IFERROR(__xludf.DUMMYFUNCTION("""COMPUTED_VALUE"""),"部") -> 部 | AI117: =IFERROR(__xludf.DUMMYFUNCTION("""COMPUTED_VALUE"""),"石") -> 石
B118: =IFERROR(__xludf.DUMMYFUNCTION("""COMPUTED_VALUE"""),"フルリモート_全国_事務") -> フルリモート_全国_事務 | C118: =IFERROR(__xludf.DUMMYFUNCTION("""COMPUTED_VALUE"""),5.5) -> 5.5 | D118: =IFERROR(__xludf.DUMMYFUNCTION("""COMPUTED_VALUE"""),"R") -> R | L118: =IFERROR(__xludf.DUMMYFUNCTION("""COMPUTED_VALUE"""),"未経験エンジニア希望向け_首都圏") -> 未経験エンジニア希望向け_首都圏 | M118: =IFERROR(__xludf.DUMMYFUNCTION("""COMPUTED_VALUE"""),0.4) -> 0.4 | N118: =IFERROR(__xludf.DUMMYFUNCTION("""COMPUTED_VALUE"""),"R") -> R | AA118: =IFERROR(__xludf.DUMMYFUNCTION("""COMPUTED_VALUE"""),"上場_販サ経験") -> 上場_販サ経験 | AB118: =IFERROR(__xludf.DUMMYFUNCTION("""COMPUTED_VALUE"""),1.4) -> 1.4 | AC118: =IFERROR(__xludf.DUMMYFUNCTION("""COMPUTED_VALUE"""),"R") -> R
B119: =IFERROR(__xludf.DUMMYFUNCTION("""COMPUTED_VALUE"""),"未経験_研修・資格_事務系_関西") -> 未経験_研修・資格_事務系_関西 | C119: =IFERROR(__xludf.DUMMYFUNCTION("""COMPUTED_VALUE"""),0.3) -> 0.3 | D119: =IFERROR(__xludf.DUMMYFUNCTION("""COMPUTED_VALUE"""),"R") -> R
B120: =IFERROR(__xludf.DUMMYFUNCTION("""COMPUTED_VALUE"""),"未経験_研修・資格_事務系_首都圏") -> 未経験_研修・資格_事務系_首都圏 | C120: =IFERROR(__xludf.DUMMYFUNCTION("""COMPUTED_VALUE"""),1.3) -> 1.3 | D120: =IFERROR(__xludf.DUMMYFUNCTION("""COMPUTED_VALUE"""),"R") -> R
A123: =A113+1 -> 20 | B123: =IFERROR(__xludf.DUMMYFUNCTION("IFERROR(LET( day, TEXT(B$1, ""ddd""), hour, LOOKUP(2, 1/($A123<>""""), $A123), type_A, $A$1, list_data, IFERROR(FILTER({'リスト'!$E$4:$F142, 'リスト'!$O$4:$P142}, ('リスト'!$A$4:$A142=day)*('リスト'!$B$4:$B142=hour)*(('リスト'!$G$4:$G142=""毎週配信"")+('リスト'!$G$4:$G"&"142=type_A))), {"""","""","""",""""}), new_data, IFERROR(FILTER({'新規'!$E$2:$F142, '新規'!$O$2:$P142}, ('新規'!$A$2:$A142=B$1)*('新規'!$B$2:$B142=hour)), {"""","""","""",""""}), special_data, IFERROR(FILTER({'特殊配信マスタ'!$E$2:$F142, '特殊配信マスタ'!$O$2:$P142}, ('特殊配"&"信マスタ'!$A$2:$A142=day)*('特殊配信マスタ'!$B$2:$B142=hour)*('特殊配信マスタ'!$R$2:$R142='特殊配信マスタ'!$S$2:$S142)), {"""","""","""",""""}), combined, VSTACK(list_data, new_data, special_data), FILTER(combined, INDEX(combined, , 1)<>"""", INDEX(combined, , 1)<>0) ), """")"),"当日新規会員") -> 当日新規会員 | C123: =IFERROR(__xludf.DUMMYFUNCTION("""COMPUTED_VALUE"""),0.1) -> 0.1 | D123: =IFERROR(__xludf.DUMMYFUNCTION("""COMPUTED_VALUE"""),"荒") -> 荒 | E123: =IFERROR(__xludf.DUMMYFUNCTION("""COMPUTED_VALUE"""),"内") -> 内 | F123: =SUM(C123:C132) -> 0.1 | G123: =IFERROR(__xludf.DUMMYFUNCTION("IFERROR(LET( day, TEXT(G$1, ""ddd""), hour, LOOKUP(2, 1/($A123<>""""), $A123), type_A, $A$1, list_data, IFERROR(FILTER({'リスト'!$E$4:$F142, 'リスト'!$O$4:$P142}, ('リスト'!$A$4:$A142=day)*('リスト'!$B$4:$B142=hour)*(('リスト'!$G$4:$G142=""毎週配信"")+('リスト'!$G$4:$G"&"142=type_A))), {"""","""","""",""""}), new_data, IFERROR(FILTER({'新規'!$E$2:$F142, '新規'!$O$2:$P142}, ('新規'!$A$2:$A142=G$1)*('新規'!$B$2:$B142=hour)), {"""","""","""",""""}), special_data, IFERROR(FILTER({'特殊配信マスタ'!$E$2:$F142, '特殊配信マスタ'!$O$2:$P142}, ('特殊配"&"信マスタ'!$A$2:$A142=day)*('特殊配信マスタ'!$B$2:$B142=hour)*('特殊配信マスタ'!$R$2:$R142='特殊配信マスタ'!$S$2:$S142)), {"""","""","""",""""}), combined, VSTACK(list_data, new_data, special_data), FILTER(combined, INDEX(combined, , 1)<>"""", INDEX(combined, , 1)<>0) ), """")"),"これから人気") -> これから人気 | H123: =IFERROR(__xludf.DUMMYFUNCTION("""COMPUTED_VALUE"""),1.0) -> 1 | I123: =IFERROR(__xludf.DUMMYFUNCTION("""COMPUTED_VALUE"""),"R") -> R | K123: =SUM(H123:H132) -> 5 | L123: =IFERROR(__xludf.DUMMYFUNCTION("IFERROR(LET( day, TEXT(L$1, ""ddd""), hour, LOOKUP(2, 1/($A123<>""""), $A123), type_A, $A$1, list_data, IFERROR(FILTER({'リスト'!$E$4:$F142, 'リスト'!$O$4:$P142}, ('リスト'!$A$4:$A142=day)*('リスト'!$B$4:$B142=hour)*(('リスト'!$G$4:$G142=""毎週配信"")+('リスト'!$G$4:$G"&"142=type_A))), {"""","""","""",""""}), new_data, IFERROR(FILTER({'新規'!$E$2:$F142, '新規'!$O$2:$P142}, ('新規'!$A$2:$A142=L$1)*('新規'!$B$2:$B142=hour)), {"""","""","""",""""}), special_data, IFERROR(FILTER({'特殊配信マスタ'!$E$2:$F142, '特殊配信マスタ'!$O$2:$P142}, ('特殊配"&"信マスタ'!$A$2:$A142=day)*('特殊配信マスタ'!$B$2:$B142=hour)*('特殊配信マスタ'!$R$2:$R142='特殊配信マスタ'!$S$2:$S142)), {"""","""","""",""""}), combined, VSTACK(list_data, new_data, special_data), FILTER(combined, INDEX(combined, , 1)<>"""", INDEX(combined, , 1)<>0) ), """")"),"事務職 A") -> 事務職 A | M123: =IFERROR(__xludf.DUMMYFUNCTION("""COMPUTED_VALUE"""),1.3) -> 1.3 | N123: =IFERROR(__xludf.DUMMYFUNCTION("""COMPUTED_VALUE"""),"R") -> R | P123: =SUM(M123:M132) -> 7.9 | Q123: =IFERROR(__xludf.DUMMYFUNCTION("IFERROR(LET( day, TEXT(Q$1, ""ddd""), hour, LOOKUP(2, 1/($A123<>""""), $A123), type_A, $A$1, list_data, IFERROR(FILTER({'リスト'!$E$4:$F142, 'リスト'!$O$4:$P142}, ('リスト'!$A$4:$A142=day)*('リスト'!$B$4:$B142=hour)*(('リスト'!$G$4:$G142=""毎週配信"")+('リスト'!$G$4:$G"&"142=type_A))), {"""","""","""",""""}), new_data, IFERROR(FILTER({'新規'!$E$2:$F142, '新規'!$O$2:$P142}, ('新規'!$A$2:$A142=Q$1)*('新規'!$B$2:$B142=hour)), {"""","""","""",""""}), special_data, IFERROR(FILTER({'特殊配信マスタ'!$E$2:$F142, '特殊配信マスタ'!$O$2:$P142}, ('特殊配"&"信マスタ'!$A$2:$A142=day)*('特殊配信マスタ'!$B$2:$B142=hour)*('特殊配信マスタ'!$R$2:$R142='特殊配信マスタ'!$S$2:$S142)), {"""","""","""",""""}), combined, VSTACK(list_data, new_data, special_data), FILTER(combined, INDEX(combined, , 1)<>"""", INDEX(combined, , 1)<>0) ), """")"),"２回目転職×称号") -> ２回目転職×称号 | R123: =IFERROR(__xludf.DUMMYFUNCTION("""COMPUTED_VALUE"""),0.9) -> 0.9 | S123: =IFERROR(__xludf.DUMMYFUNCTION("""COMPUTED_VALUE"""),"部") -> 部 | T123: =IFERROR(__xludf.DUMMYFUNCTION("""COMPUTED_VALUE"""),"石") -> 石 | U123: =SUM(R123:R132) -> 9.2 | V123: =IFERROR(__xludf.DUMMYFUNCTION("IFERROR(LET( day, TEXT(V$1, ""ddd""), hour, LOOKUP(2, 1/($A123<>""""), $A123), type_A, $A$1, list_data, IFERROR(FILTER({'リスト'!$E$4:$F142, 'リスト'!$O$4:$P142}, ('リスト'!$A$4:$A142=day)*('リスト'!$B$4:$B142=hour)*(('リスト'!$G$4:$G142=""毎週配信"")+('リスト'!$G$4:$G"&"142=type_A))), {"""","""","""",""""}), new_data, IFERROR(FILTER({'新規'!$E$2:$F142, '新規'!$O$2:$P142}, ('新規'!$A$2:$A142=V$1)*('新規'!$B$2:$B142=hour)), {"""","""","""",""""}), special_data, IFERROR(FILTER({'特殊配信マスタ'!$E$2:$F142, '特殊配信マスタ'!$O$2:$P142}, ('特殊配"&"信マスタ'!$A$2:$A142=day)*('特殊配信マスタ'!$B$2:$B142=hour)*('特殊配信マスタ'!$R$2:$R142='特殊配信マスタ'!$S$2:$S142)), {"""","""","""",""""}), combined, VSTACK(list_data, new_data, special_data), FILTER(combined, INDEX(combined, , 1)<>"""", INDEX(combined, , 1)<>0) ), """")"),"35歳以上向け B") -> 35歳以上向け B | W123: =IFERROR(__xludf.DUMMYFUNCTION("""COMPUTED_VALUE"""),1.1) -> 1.1 | X123: =IFERROR(__xludf.DUMMYFUNCTION("""COMPUTED_VALUE"""),"R") -> R | Z123: =SUM(W123:W132) -> 2.5 | AA123: =IFERROR(__xludf.DUMMYFUNCTION("IFERROR(LET( day, TEXT(AA$1, ""ddd""), hour, LOOKUP(2, 1/($A123<>""""), $A123), type_A, $A$1, list_data, IFERROR(FILTER({'リスト'!$E$4:$F142, 'リスト'!$O$4:$P142}, ('リスト'!$A$4:$A142=day)*('リスト'!$B$4:$B142=hour)*(('リスト'!$G$4:$G142=""毎週配信"")+('リスト'!$G$4:$"&"G142=type_A))), {"""","""","""",""""}), new_data, IFERROR(FILTER({'新規'!$E$2:$F142, '新規'!$O$2:$P142}, ('新規'!$A$2:$A142=AA$1)*('新規'!$B$2:$B142=hour)), {"""","""","""",""""}), special_data, IFERROR(FILTER({'特殊配信マスタ'!$E$2:$F142, '特殊配信マスタ'!$O$2:$P142}, ('特"&"殊配信マスタ'!$A$2:$A142=day)*('特殊配信マスタ'!$B$2:$B142=hour)*('特殊配信マスタ'!$R$2:$R142='特殊配信マスタ'!$S$2:$S142)), {"""","""","""",""""}), combined, VSTACK(list_data, new_data, special_data), FILTER(combined, INDEX(combined, , 1)<>"""", INDEX(combined, , 1)<>0) ), """&""")"),"異業種提案_事務") -> 異業種提案_事務 | AB123: =IFERROR(__xludf.DUMMYFUNCTION("""COMPUTED_VALUE"""),2.1) -> 2.1 | AC123: =IFERROR(__xludf.DUMMYFUNCTION("""COMPUTED_VALUE"""),"R") -> R | AE123: =SUM(AB123:AB132) -> 3.8 | AF123: =IFERROR(__xludf.DUMMYFUNCTION("IFERROR(LET( day, TEXT(AF$1, ""ddd""), hour, LOOKUP(2, 1/($A123<>""""), $A123), type_A, $A$1, list_data, IFERROR(FILTER({'リスト'!$E$4:$F142, 'リスト'!$O$4:$P142}, ('リスト'!$A$4:$A142=day)*('リスト'!$B$4:$B142=hour)*(('リスト'!$G$4:$G142=""毎週配信"")+('リスト'!$G$4:$"&"G142=type_A))), {"""","""","""",""""}), new_data, IFERROR(FILTER({'新規'!$E$2:$F142, '新規'!$O$2:$P142}, ('新規'!$A$2:$A142=AF$1)*('新規'!$B$2:$B142=hour)), {"""","""","""",""""}), special_data, IFERROR(FILTER({'特殊配信マスタ'!$E$2:$F142, '特殊配信マスタ'!$O$2:$P142}, ('特"&"殊配信マスタ'!$A$2:$A142=day)*('特殊配信マスタ'!$B$2:$B142=hour)*('特殊配信マスタ'!$R$2:$R142='特殊配信マスタ'!$S$2:$S142)), {"""","""","""",""""}), combined, VSTACK(list_data, new_data, special_data), FILTER(combined, INDEX(combined, , 1)<>"""", INDEX(combined, , 1)<>0) ), """&""")"),"36歳以上正社員求人") -> 36歳以上正社員求人 | AG123: =IFERROR(__xludf.DUMMYFUNCTION("""COMPUTED_VALUE"""),2.0) -> 2 | AH123: =IFERROR(__xludf.DUMMYFUNCTION("""COMPUTED_VALUE"""),"R") -> R | AJ123: =SUM(AG123:AG132) -> 5.4
G124: =IFERROR(__xludf.DUMMYFUNCTION("""COMPUTED_VALUE"""),"ユニークな福利厚生制度_B") -> ユニークな福利厚生制度_B | H124: =IFERROR(__xludf.DUMMYFUNCTION("""COMPUTED_VALUE"""),1.2) -> 1.2 | I124: =IFERROR(__xludf.DUMMYFUNCTION("""COMPUTED_VALUE"""),"R") -> R | L124: =IFERROR(__xludf.DUMMYFUNCTION("""COMPUTED_VALUE"""),"事務職_35歳以上 A_ランキング") -> 事務職_35歳以上 A_ランキング | M124: =IFERROR(__xludf.DUMMYFUNCTION("""COMPUTED_VALUE"""),1.0) -> 1 | N124: =IFERROR(__xludf.DUMMYFUNCTION("""COMPUTED_VALUE"""),"R") -> R | Q124: =IFERROR(__xludf.DUMMYFUNCTION("""COMPUTED_VALUE"""),"残業したくない") -> 残業したくない | R124: =IFERROR(__xludf.DUMMYFUNCTION("""COMPUTED_VALUE"""),2.1) -> 2.1 | S124: =IFERROR(__xludf.DUMMYFUNCTION("""COMPUTED_VALUE"""),"R") -> R | V124: =IFERROR(__xludf.DUMMYFUNCTION("""COMPUTED_VALUE"""),"35歳以上向け_関西 B") -> 35歳以上向け_関西 B | W124: =IFERROR(__xludf.DUMMYFUNCTION("""COMPUTED_VALUE"""),0.3) -> 0.3 | X124: =IFERROR(__xludf.DUMMYFUNCTION("""COMPUTED_VALUE"""),"R") -> R | AA124: =IFERROR(__xludf.DUMMYFUNCTION("""COMPUTED_VALUE"""),"正社員_関西") -> 正社員_関西 | AB124: =IFERROR(__xludf.DUMMYFUNCTION("""COMPUTED_VALUE"""),1.6) -> 1.6 | AC124: =IFERROR(__xludf.DUMMYFUNCTION("""COMPUTED_VALUE"""),"R") -> R | AF124: =IFERROR(__xludf.DUMMYFUNCTION("""COMPUTED_VALUE"""),"広報・マーケティング_リモート_未経験") -> 広報・マーケティング_リモート_未経験 | AG124: =IFERROR(__xludf.DUMMYFUNCTION("""COMPUTED_VALUE"""),1.0) -> 1 | AH124: =IFERROR(__xludf.DUMMYFUNCTION("""COMPUTED_VALUE"""),"R") -> R
G125: =IFERROR(__xludf.DUMMYFUNCTION("""COMPUTED_VALUE"""),"大手上場_35歳以上 A") -> 大手上場_35歳以上 A | H125: =IFERROR(__xludf.DUMMYFUNCTION("""COMPUTED_VALUE"""),1.0) -> 1 | I125: =IFERROR(__xludf.DUMMYFUNCTION("""COMPUTED_VALUE"""),"R") -> R | L125: =IFERROR(__xludf.DUMMYFUNCTION("""COMPUTED_VALUE"""),"事務職_関西 A") -> 事務職_関西 A | M125: =IFERROR(__xludf.DUMMYFUNCTION("""COMPUTED_VALUE"""),1.0) -> 1 | N125: =IFERROR(__xludf.DUMMYFUNCTION("""COMPUTED_VALUE"""),"R") -> R | Q125: =IFERROR(__xludf.DUMMYFUNCTION("""COMPUTED_VALUE"""),"残業したくない_関西") -> 残業したくない_関西 | R125: =IFERROR(__xludf.DUMMYFUNCTION("""COMPUTED_VALUE"""),0.7) -> 0.7 | S125: =IFERROR(__xludf.DUMMYFUNCTION("""COMPUTED_VALUE"""),"R") -> R | V125: =IFERROR(__xludf.DUMMYFUNCTION("""COMPUTED_VALUE"""),"35歳未満_PV多い求人") -> 35歳未満_PV多い求人 | W125: =IFERROR(__xludf.DUMMYFUNCTION("""COMPUTED_VALUE"""),1.0) -> 1 | X125: =IFERROR(__xludf.DUMMYFUNCTION("""COMPUTED_VALUE"""),"R") -> R | AA125: =IFERROR(__xludf.DUMMYFUNCTION("""COMPUTED_VALUE"""),"当日新規会員") -> 当日新規会員 | AB125: =IFERROR(__xludf.DUMMYFUNCTION("""COMPUTED_VALUE"""),0.1) -> 0.1 | AC125: =IFERROR(__xludf.DUMMYFUNCTION("""COMPUTED_VALUE"""),"荒") -> 荒 | AD125: =IFERROR(__xludf.DUMMYFUNCTION("""COMPUTED_VALUE"""),"内") -> 内 | AF125: =IFERROR(__xludf.DUMMYFUNCTION("""COMPUTED_VALUE"""),"国認定企業") -> 国認定企業 | AG125: =IFERROR(__xludf.DUMMYFUNCTION("""COMPUTED_VALUE"""),1.6) -> 1.6 | AH125: =IFERROR(__xludf.DUMMYFUNCTION("""COMPUTED_VALUE"""),"R") -> R
G126: =IFERROR(__xludf.DUMMYFUNCTION("""COMPUTED_VALUE"""),"大手上場_関西 A") -> 大手上場_関西 A | H126: =IFERROR(__xludf.DUMMYFUNCTION("""COMPUTED_VALUE"""),1.0) -> 1 | I126: =IFERROR(__xludf.DUMMYFUNCTION("""COMPUTED_VALUE"""),"R") -> R | L126: =IFERROR(__xludf.DUMMYFUNCTION("""COMPUTED_VALUE"""),"首都圏_フルリモート_求人特集") -> 首都圏_フルリモート_求人特集 | M126: =IFERROR(__xludf.DUMMYFUNCTION("""COMPUTED_VALUE"""),3.9) -> 3.9 | N126: =IFERROR(__xludf.DUMMYFUNCTION("""COMPUTED_VALUE"""),"R") -> R | Q126: =IFERROR(__xludf.DUMMYFUNCTION("""COMPUTED_VALUE"""),"住宅手当あり_首都圏") -> 住宅手当あり_首都圏 | R126: =IFERROR(__xludf.DUMMYFUNCTION("""COMPUTED_VALUE"""),1.8) -> 1.8 | S126: =IFERROR(__xludf.DUMMYFUNCTION("""COMPUTED_VALUE"""),"R") -> R | V126: =IFERROR(__xludf.DUMMYFUNCTION("""COMPUTED_VALUE"""),"当日新規会員") -> 当日新規会員 | W126: =IFERROR(__xludf.DUMMYFUNCTION("""COMPUTED_VALUE"""),0.1) -> 0.1 | X126: =IFERROR(__xludf.DUMMYFUNCTION("""COMPUTED_VALUE"""),"荒") -> 荒 | Y126: =IFERROR(__xludf.DUMMYFUNCTION("""COMPUTED_VALUE"""),"内") -> 内 | AF126: =IFERROR(__xludf.DUMMYFUNCTION("""COMPUTED_VALUE"""),"新規会員向け_フルリモート×未経験歓迎") -> 新規会員向け_フルリモート×未経験歓迎 | AG126: =IFERROR(__xludf.DUMMYFUNCTION("""COMPUTED_VALUE"""),0.4) -> 0.4 | AH126: =IFERROR(__xludf.DUMMYFUNCTION("""COMPUTED_VALUE"""),"R") -> R
G127: =IFERROR(__xludf.DUMMYFUNCTION("""COMPUTED_VALUE"""),"大手上場_第二新卒 A") -> 大手上場_第二新卒 A | H127: =IFERROR(__xludf.DUMMYFUNCTION("""COMPUTED_VALUE"""),0.7) -> 0.7 | I127: =IFERROR(__xludf.DUMMYFUNCTION("""COMPUTED_VALUE"""),"R") -> R | L127: =IFERROR(__xludf.DUMMYFUNCTION("""COMPUTED_VALUE"""),"当日新規会員") -> 当日新規会員 | M127: =IFERROR(__xludf.DUMMYFUNCTION("""COMPUTED_VALUE"""),0.1) -> 0.1 | N127: =IFERROR(__xludf.DUMMYFUNCTION("""COMPUTED_VALUE"""),"荒") -> 荒 | O127: =IFERROR(__xludf.DUMMYFUNCTION("""COMPUTED_VALUE"""),"内") -> 内 | Q127: =IFERROR(__xludf.DUMMYFUNCTION("""COMPUTED_VALUE"""),"住宅手当あり_首都圏_35歳以上") -> 住宅手当あり_首都圏_35歳以上 | R127: =IFERROR(__xludf.DUMMYFUNCTION("""COMPUTED_VALUE"""),1.4) -> 1.4 | S127: =IFERROR(__xludf.DUMMYFUNCTION("""COMPUTED_VALUE"""),"R") -> R | AF127: =IFERROR(__xludf.DUMMYFUNCTION("""COMPUTED_VALUE"""),"当日新規会員") -> 当日新規会員 | AG127: =IFERROR(__xludf.DUMMYFUNCTION("""COMPUTED_VALUE"""),0.1) -> 0.1 | AH127: =IFERROR(__xludf.DUMMYFUNCTION("""COMPUTED_VALUE"""),"荒") -> 荒 | AI127: =IFERROR(__xludf.DUMMYFUNCTION("""COMPUTED_VALUE"""),"内") -> 内
G128: =IFERROR(__xludf.DUMMYFUNCTION("""COMPUTED_VALUE"""),"当日新規会員") -> 当日新規会員 | H128: =IFERROR(__xludf.DUMMYFUNCTION("""COMPUTED_VALUE"""),0.1) -> 0.1 | I128: =IFERROR(__xludf.DUMMYFUNCTION("""COMPUTED_VALUE"""),"荒") -> 荒 | J128: =IFERROR(__xludf.DUMMYFUNCTION("""COMPUTED_VALUE"""),"内") -> 内 | L128: =IFERROR(__xludf.DUMMYFUNCTION("""COMPUTED_VALUE"""),"未経験_研修・資格_クリエイティブ系_埼玉神奈川千葉") -> 未経験_研修・資格_クリエイティブ系_埼玉神奈川千葉 | M128: =IFERROR(__xludf.DUMMYFUNCTION("""COMPUTED_VALUE"""),0.3) -> 0.3 | N128: =IFERROR(__xludf.DUMMYFUNCTION("""COMPUTED_VALUE"""),"R") -> R | Q128: =IFERROR(__xludf.DUMMYFUNCTION("""COMPUTED_VALUE"""),"当日新規会員") -> 当日新規会員 | R128: =IFERROR(__xludf.DUMMYFUNCTION("""COMPUTED_VALUE"""),0.1) -> 0.1 | S128: =IFERROR(__xludf.DUMMYFUNCTION("""COMPUTED_VALUE"""),"荒") -> 荒 | T128: =IFERROR(__xludf.DUMMYFUNCTION("""COMPUTED_VALUE"""),"内") -> 内 | AF128: =IFERROR(__xludf.DUMMYFUNCTION("""COMPUTED_VALUE"""),"不動産×事務") -> 不動産×事務 | AG128: =IFERROR(__xludf.DUMMYFUNCTION("""COMPUTED_VALUE"""),0.2) -> 0.2 | AH128: =IFERROR(__xludf.DUMMYFUNCTION("""COMPUTED_VALUE"""),"R") -> R
L129: =IFERROR(__xludf.DUMMYFUNCTION("""COMPUTED_VALUE"""),"未経験_研修・資格_クリエイティブ系_東京") -> 未経験_研修・資格_クリエイティブ系_東京 | M129: =IFERROR(__xludf.DUMMYFUNCTION("""COMPUTED_VALUE"""),0.3) -> 0.3 | N129: =IFERROR(__xludf.DUMMYFUNCTION("""COMPUTED_VALUE"""),"R") -> R | Q129: =IFERROR(__xludf.DUMMYFUNCTION("""COMPUTED_VALUE"""),"有給取得率") -> 有給取得率 | R129: =IFERROR(__xludf.DUMMYFUNCTION("""COMPUTED_VALUE"""),2.2) -> 2.2 | S129: =IFERROR(__xludf.DUMMYFUNCTION("""COMPUTED_VALUE"""),"石") -> 石 | T129: =IFERROR(__xludf.DUMMYFUNCTION("""COMPUTED_VALUE"""),"武") -> 武 | AF129: =IFERROR(__xludf.DUMMYFUNCTION("""COMPUTED_VALUE"""),"保育士_幼稚園教諭") -> 保育士_幼稚園教諭 | AG129: =IFERROR(__xludf.DUMMYFUNCTION("""COMPUTED_VALUE"""),0.1) -> 0.1 | AH129: =IFERROR(__xludf.DUMMYFUNCTION("""COMPUTED_VALUE"""),"石") -> 石 | AI129: =IFERROR(__xludf.DUMMYFUNCTION("""COMPUTED_VALUE"""),"部") -> 部
Q130: =IFERROR(__xludf.DUMMYFUNCTION("""COMPUTED_VALUE"""),"有給取得率①") -> 有給取得率① | AF130: =IFERROR(__xludf.DUMMYFUNCTION("""COMPUTED_VALUE"""),"保育士_幼稚園教諭") -> 保育士_幼稚園教諭
A133: =A123+1 -> 21 | B133: =IFERROR(__xludf.DUMMYFUNCTION("IFERROR(LET( day, TEXT(B$1, ""ddd""), hour, LOOKUP(2, 1/($A133<>""""), $A133), type_A, $A$1, list_data, IFERROR(FILTER({'リスト'!$E$4:$F142, 'リスト'!$O$4:$P142}, ('リスト'!$A$4:$A142=day)*('リスト'!$B$4:$B142=hour)*(('リスト'!$G$4:$G142=""毎週配信"")+('リスト'!$G$4:$G"&"142=type_A))), {"""","""","""",""""}), new_data, IFERROR(FILTER({'新規'!$E$2:$F142, '新規'!$O$2:$P142}, ('新規'!$A$2:$A142=B$1)*('新規'!$B$2:$B142=hour)), {"""","""","""",""""}), special_data, IFERROR(FILTER({'特殊配信マスタ'!$E$2:$F142, '特殊配信マスタ'!$O$2:$P142}, ('特殊配"&"信マスタ'!$A$2:$A142=day)*('特殊配信マスタ'!$B$2:$B142=hour)*('特殊配信マスタ'!$R$2:$R142='特殊配信マスタ'!$S$2:$S142)), {"""","""","""",""""}), combined, VSTACK(list_data, new_data, special_data), FILTER(combined, INDEX(combined, , 1)<>"""", INDEX(combined, , 1)<>0) ), """")"),"WEB面接・コロナ対策") -> WEB面接・コロナ対策 | C133: =IFERROR(__xludf.DUMMYFUNCTION("""COMPUTED_VALUE"""),9.3) -> 9.3 | D133: =IFERROR(__xludf.DUMMYFUNCTION("""COMPUTED_VALUE"""),"R") -> R | F133: =SUM(C133:C142) -> 10.6 | G133: =IFERROR(__xludf.DUMMYFUNCTION("IFERROR(LET( day, TEXT(G$1, ""ddd""), hour, LOOKUP(2, 1/($A133<>""""), $A133), type_A, $A$1, list_data, IFERROR(FILTER({'リスト'!$E$4:$F142, 'リスト'!$O$4:$P142}, ('リスト'!$A$4:$A142=day)*('リスト'!$B$4:$B142=hour)*(('リスト'!$G$4:$G142=""毎週配信"")+('リスト'!$G$4:$G"&"142=type_A))), {"""","""","""",""""}), new_data, IFERROR(FILTER({'新規'!$E$2:$F142, '新規'!$O$2:$P142}, ('新規'!$A$2:$A142=G$1)*('新規'!$B$2:$B142=hour)), {"""","""","""",""""}), special_data, IFERROR(FILTER({'特殊配信マスタ'!$E$2:$F142, '特殊配信マスタ'!$O$2:$P142}, ('特殊配"&"信マスタ'!$A$2:$A142=day)*('特殊配信マスタ'!$B$2:$B142=hour)*('特殊配信マスタ'!$R$2:$R142='特殊配信マスタ'!$S$2:$S142)), {"""","""","""",""""}), combined, VSTACK(list_data, new_data, special_data), FILTER(combined, INDEX(combined, , 1)<>"""", INDEX(combined, , 1)<>0) ), """")"),"◇ウキにしか掲載していない求人") -> ◇ウキにしか掲載していない求人 | H133: =IFERROR(__xludf.DUMMYFUNCTION("""COMPUTED_VALUE"""),6.9) -> 6.9 | I133: =IFERROR(__xludf.DUMMYFUNCTION("""COMPUTED_VALUE"""),"部") -> 部 | J133: =IFERROR(__xludf.DUMMYFUNCTION("""COMPUTED_VALUE"""),"武") -> 武 | K133: =SUM(H133:H142) -> 9.8 | L133: =IFERROR(__xludf.DUMMYFUNCTION("IFERROR(LET( day, TEXT(L$1, ""ddd""), hour, LOOKUP(2, 1/($A133<>""""), $A133), type_A, $A$1, list_data, IFERROR(FILTER({'リスト'!$E$4:$F142, 'リスト'!$O$4:$P142}, ('リスト'!$A$4:$A142=day)*('リスト'!$B$4:$B142=hour)*(('リスト'!$G$4:$G142=""毎週配信"")+('リスト'!$G$4:$G"&"142=type_A))), {"""","""","""",""""}), new_data, IFERROR(FILTER({'新規'!$E$2:$F142, '新規'!$O$2:$P142}, ('新規'!$A$2:$A142=L$1)*('新規'!$B$2:$B142=hour)), {"""","""","""",""""}), special_data, IFERROR(FILTER({'特殊配信マスタ'!$E$2:$F142, '特殊配信マスタ'!$O$2:$P142}, ('特殊配"&"信マスタ'!$A$2:$A142=day)*('特殊配信マスタ'!$B$2:$B142=hour)*('特殊配信マスタ'!$R$2:$R142='特殊配信マスタ'!$S$2:$S142)), {"""","""","""",""""}), combined, VSTACK(list_data, new_data, special_data), FILTER(combined, INDEX(combined, , 1)<>"""", INDEX(combined, , 1)<>0) ), """")"),"応募から1日_好条件事務ランキング") -> 応募から1日_好条件事務ランキング | M133: =IFERROR(__xludf.DUMMYFUNCTION("""COMPUTED_VALUE"""),0.1) -> 0.1 | N133: =IFERROR(__xludf.DUMMYFUNCTION("""COMPUTED_VALUE"""),"R") -> R | P133: =SUM(M133:M142) -> 6.1 | Q133: =IFERROR(__xludf.DUMMYFUNCTION("IFERROR(LET( day, TEXT(Q$1, ""ddd""), hour, LOOKUP(2, 1/($A133<>""""), $A133), type_A, $A$1, list_data, IFERROR(FILTER({'リスト'!$E$4:$F142, 'リスト'!$O$4:$P142}, ('リスト'!$A$4:$A142=day)*('リスト'!$B$4:$B142=hour)*(('リスト'!$G$4:$G142=""毎週配信"")+('リスト'!$G$4:$G"&"142=type_A))), {"""","""","""",""""}), new_data, IFERROR(FILTER({'新規'!$E$2:$F142, '新規'!$O$2:$P142}, ('新規'!$A$2:$A142=Q$1)*('新規'!$B$2:$B142=hour)), {"""","""","""",""""}), special_data, IFERROR(FILTER({'特殊配信マスタ'!$E$2:$F142, '特殊配信マスタ'!$O$2:$P142}, ('特殊配"&"信マスタ'!$A$2:$A142=day)*('特殊配信マスタ'!$B$2:$B142=hour)*('特殊配信マスタ'!$R$2:$R142='特殊配信マスタ'!$S$2:$S142)), {"""","""","""",""""}), combined, VSTACK(list_data, new_data, special_data), FILTER(combined, INDEX(combined, , 1)<>"""", INDEX(combined, , 1)<>0) ), """")"),"ウルトラ好条件") -> ウルトラ好条件 | R133: =IFERROR(__xludf.DUMMYFUNCTION("""COMPUTED_VALUE"""),6.7) -> 6.7 | S133: =IFERROR(__xludf.DUMMYFUNCTION("""COMPUTED_VALUE"""),"R") -> R | U133: =SUM(R133:R142) -> 7.4 | V133: =IFERROR(__xludf.DUMMYFUNCTION("IFERROR(LET( day, TEXT(V$1, ""ddd""), hour, LOOKUP(2, 1/($A133<>""""), $A133), type_A, $A$1, list_data, IFERROR(FILTER({'リスト'!$E$4:$F142, 'リスト'!$O$4:$P142}, ('リスト'!$A$4:$A142=day)*('リスト'!$B$4:$B142=hour)*(('リスト'!$G$4:$G142=""毎週配信"")+('リスト'!$G$4:$G"&"142=type_A))), {"""","""","""",""""}), new_data, IFERROR(FILTER({'新規'!$E$2:$F142, '新規'!$O$2:$P142}, ('新規'!$A$2:$A142=V$1)*('新規'!$B$2:$B142=hour)), {"""","""","""",""""}), special_data, IFERROR(FILTER({'特殊配信マスタ'!$E$2:$F142, '特殊配信マスタ'!$O$2:$P142}, ('特殊配"&"信マスタ'!$A$2:$A142=day)*('特殊配信マスタ'!$B$2:$B142=hour)*('特殊配信マスタ'!$R$2:$R142='特殊配信マスタ'!$S$2:$S142)), {"""","""","""",""""}), combined, VSTACK(list_data, new_data, special_data), FILTER(combined, INDEX(combined, , 1)<>"""", INDEX(combined, , 1)<>0) ), """")"),"応募から1日_好条件事務ランキング") -> 応募から1日_好条件事務ランキング | W133: =IFERROR(__xludf.DUMMYFUNCTION("""COMPUTED_VALUE"""),0.1) -> 0.1 | X133: =IFERROR(__xludf.DUMMYFUNCTION("""COMPUTED_VALUE"""),"R") -> R | Z133: =SUM(W133:W142) -> 3.9 | AA133: =IFERROR(__xludf.DUMMYFUNCTION("IFERROR(LET( day, TEXT(AA$1, ""ddd""), hour, LOOKUP(2, 1/($A133<>""""), $A133), type_A, $A$1, list_data, IFERROR(FILTER({'リスト'!$E$4:$F142, 'リスト'!$O$4:$P142}, ('リスト'!$A$4:$A142=day)*('リスト'!$B$4:$B142=hour)*(('リスト'!$G$4:$G142=""毎週配信"")+('リスト'!$G$4:$"&"G142=type_A))), {"""","""","""",""""}), new_data, IFERROR(FILTER({'新規'!$E$2:$F142, '新規'!$O$2:$P142}, ('新規'!$A$2:$A142=AA$1)*('新規'!$B$2:$B142=hour)), {"""","""","""",""""}), special_data, IFERROR(FILTER({'特殊配信マスタ'!$E$2:$F142, '特殊配信マスタ'!$O$2:$P142}, ('特"&"殊配信マスタ'!$A$2:$A142=day)*('特殊配信マスタ'!$B$2:$B142=hour)*('特殊配信マスタ'!$R$2:$R142='特殊配信マスタ'!$S$2:$S142)), {"""","""","""",""""}), combined, VSTACK(list_data, new_data, special_data), FILTER(combined, INDEX(combined, , 1)<>"""", INDEX(combined, , 1)<>0) ), """&""")"),"リモート_ランキング") -> リモート_ランキング | AB133: =IFERROR(__xludf.DUMMYFUNCTION("""COMPUTED_VALUE"""),2.5) -> 2.5 | AC133: =IFERROR(__xludf.DUMMYFUNCTION("""COMPUTED_VALUE"""),"R") -> R | AE133: =SUM(AB133:AB142) -> 3.3 | AF133: =IFERROR(__xludf.DUMMYFUNCTION("IFERROR(LET( day, TEXT(AF$1, ""ddd""), hour, LOOKUP(2, 1/($A133<>""""), $A133), type_A, $A$1, list_data, IFERROR(FILTER({'リスト'!$E$4:$F142, 'リスト'!$O$4:$P142}, ('リスト'!$A$4:$A142=day)*('リスト'!$B$4:$B142=hour)*(('リスト'!$G$4:$G142=""毎週配信"")+('リスト'!$G$4:$"&"G142=type_A))), {"""","""","""",""""}), new_data, IFERROR(FILTER({'新規'!$E$2:$F142, '新規'!$O$2:$P142}, ('新規'!$A$2:$A142=AF$1)*('新規'!$B$2:$B142=hour)), {"""","""","""",""""}), special_data, IFERROR(FILTER({'特殊配信マスタ'!$E$2:$F142, '特殊配信マスタ'!$O$2:$P142}, ('特"&"殊配信マスタ'!$A$2:$A142=day)*('特殊配信マスタ'!$B$2:$B142=hour)*('特殊配信マスタ'!$R$2:$R142='特殊配信マスタ'!$S$2:$S142)), {"""","""","""",""""}), combined, VSTACK(list_data, new_data, special_data), FILTER(combined, INDEX(combined, , 1)<>"""", INDEX(combined, , 1)<>0) ), """&""")"),"フルフレックス") -> フルフレックス | AG133: =IFERROR(__xludf.DUMMYFUNCTION("""COMPUTED_VALUE"""),3.1) -> 3.1 | AH133: =IFERROR(__xludf.DUMMYFUNCTION("""COMPUTED_VALUE"""),"R") -> R | AJ133: =SUM(AG133:AG142) -> 4.1
B134: =IFERROR(__xludf.DUMMYFUNCTION("""COMPUTED_VALUE"""),"ランキング_事務（貿易事務）_希望") -> ランキング_事務（貿易事務）_希望 | C134: =IFERROR(__xludf.DUMMYFUNCTION("""COMPUTED_VALUE"""),0.4) -> 0.4 | D134: =IFERROR(__xludf.DUMMYFUNCTION("""COMPUTED_VALUE"""),"R") -> R | G134: =IFERROR(__xludf.DUMMYFUNCTION("""COMPUTED_VALUE"""),"応募から1日_好条件事務ランキング") -> 応募から1日_好条件事務ランキング | H134: =IFERROR(__xludf.DUMMYFUNCTION("""COMPUTED_VALUE"""),0.1) -> 0.1 | I134: =IFERROR(__xludf.DUMMYFUNCTION("""COMPUTED_VALUE"""),"R") -> R | L134: =IFERROR(__xludf.DUMMYFUNCTION("""COMPUTED_VALUE"""),"応募から3日会員") -> 応募から3日会員 | M134: =IFERROR(__xludf.DUMMYFUNCTION("""COMPUTED_VALUE"""),0.1) -> 0.1 | N134: =IFERROR(__xludf.DUMMYFUNCTION("""COMPUTED_VALUE"""),"R") -> R | Q134: =IFERROR(__xludf.DUMMYFUNCTION("""COMPUTED_VALUE"""),"応募から1日_好条件事務ランキング") -> 応募から1日_好条件事務ランキング | R134: =IFERROR(__xludf.DUMMYFUNCTION("""COMPUTED_VALUE"""),0.1) -> 0.1 | S134: =IFERROR(__xludf.DUMMYFUNCTION("""COMPUTED_VALUE"""),"R") -> R | V134: =IFERROR(__xludf.DUMMYFUNCTION("""COMPUTED_VALUE"""),"応募から3日会員") -> 応募から3日会員 | W134: =IFERROR(__xludf.DUMMYFUNCTION("""COMPUTED_VALUE"""),0.1) -> 0.1 | X134: =IFERROR(__xludf.DUMMYFUNCTION("""COMPUTED_VALUE"""),"R") -> R | AA134: =IFERROR(__xludf.DUMMYFUNCTION("""COMPUTED_VALUE"""),"応募から1日_好条件事務ランキング") -> 応募から1日_好条件事務ランキング | AB134: =IFERROR(__xludf.DUMMYFUNCTION("""COMPUTED_VALUE"""),0.1) -> 0.1 | AC134: =IFERROR(__xludf.DUMMYFUNCTION("""COMPUTED_VALUE"""),"R") -> R | AF134: =IFERROR(__xludf.DUMMYFUNCTION("""COMPUTED_VALUE"""),"営業_カタカナ職業") -> 営業_カタカナ職業 | AG134: =IFERROR(__xludf.DUMMYFUNCTION("""COMPUTED_VALUE"""),0.8) -> 0.8 | AH134: =IFERROR(__xludf.DUMMYFUNCTION("""COMPUTED_VALUE"""),"R") -> R
B135: =IFERROR(__xludf.DUMMYFUNCTION("""COMPUTED_VALUE"""),"応募から1日_好条件事務ランキング") -> 応募から1日_好条件事務ランキング | C135: =IFERROR(__xludf.DUMMYFUNCTION("""COMPUTED_VALUE"""),0.1) -> 0.1 | D135: =IFERROR(__xludf.DUMMYFUNCTION("""COMPUTED_VALUE"""),"R") -> R | G135: =IFERROR(__xludf.DUMMYFUNCTION("""COMPUTED_VALUE"""),"応募から3日会員") -> 応募から3日会員 | H135: =IFERROR(__xludf.DUMMYFUNCTION("""COMPUTED_VALUE"""),0.1) -> 0.1 | I135: =IFERROR(__xludf.DUMMYFUNCTION("""COMPUTED_VALUE"""),"R") -> R | L135: =IFERROR(__xludf.DUMMYFUNCTION("""COMPUTED_VALUE"""),"学歴不問×大手上場企業") -> 学歴不問×大手上場企業 | M135: =IFERROR(__xludf.DUMMYFUNCTION("""COMPUTED_VALUE"""),1.3) -> 1.3 | N135: =IFERROR(__xludf.DUMMYFUNCTION("""COMPUTED_VALUE"""),"R") -> R | Q135: =IFERROR(__xludf.DUMMYFUNCTION("""COMPUTED_VALUE"""),"応募から3日会員") -> 応募から3日会員 | R135: =IFERROR(__xludf.DUMMYFUNCTION("""COMPUTED_VALUE"""),0.1) -> 0.1 | S135: =IFERROR(__xludf.DUMMYFUNCTION("""COMPUTED_VALUE"""),"R") -> R | V135: =IFERROR(__xludf.DUMMYFUNCTION("""COMPUTED_VALUE"""),"月給30万以上_ランキング") -> 月給30万以上_ランキング | W135: =IFERROR(__xludf.DUMMYFUNCTION("""COMPUTED_VALUE"""),1.7) -> 1.7 | X135: =IFERROR(__xludf.DUMMYFUNCTION("""COMPUTED_VALUE"""),"R") -> R | AA135: =IFERROR(__xludf.DUMMYFUNCTION("""COMPUTED_VALUE"""),"応募から3日会員") -> 応募から3日会員 | AB135: =IFERROR(__xludf.DUMMYFUNCTION("""COMPUTED_VALUE"""),0.1) -> 0.1 | AC135: =IFERROR(__xludf.DUMMYFUNCTION("""COMPUTED_VALUE"""),"R") -> R | AF135: =IFERROR(__xludf.DUMMYFUNCTION("""COMPUTED_VALUE"""),"応募から1日_好条件事務ランキング") -> 応募から1日_好条件事務ランキング | AG135: =IFERROR(__xludf.DUMMYFUNCTION("""COMPUTED_VALUE"""),0.1) -> 0.1 | AH135: =IFERROR(__xludf.DUMMYFUNCTION("""COMPUTED_VALUE"""),"R") -> R
B136: =IFERROR(__xludf.DUMMYFUNCTION("""COMPUTED_VALUE"""),"応募から3日会員") -> 応募から3日会員 | C136: =IFERROR(__xludf.DUMMYFUNCTION("""COMPUTED_VALUE"""),0.1) -> 0.1 | D136: =IFERROR(__xludf.DUMMYFUNCTION("""COMPUTED_VALUE"""),"R") -> R | G136: =IFERROR(__xludf.DUMMYFUNCTION("""COMPUTED_VALUE"""),"年収UP_営業") -> 年収UP_営業 | H136: =IFERROR(__xludf.DUMMYFUNCTION("""COMPUTED_VALUE"""),0.6) -> 0.6 | I136: =IFERROR(__xludf.DUMMYFUNCTION("""COMPUTED_VALUE"""),"R") -> R | L136: =IFERROR(__xludf.DUMMYFUNCTION("""COMPUTED_VALUE"""),"新働きやすさ_A") -> 新働きやすさ_A | M136: =IFERROR(__xludf.DUMMYFUNCTION("""COMPUTED_VALUE"""),2.0) -> 2 | N136: =IFERROR(__xludf.DUMMYFUNCTION("""COMPUTED_VALUE"""),"R") -> R | Q136: =IFERROR(__xludf.DUMMYFUNCTION("""COMPUTED_VALUE"""),"希望業種_人材サービス") -> 希望業種_人材サービス | R136: =IFERROR(__xludf.DUMMYFUNCTION("""COMPUTED_VALUE"""),0.5) -> 0.5 | S136: =IFERROR(__xludf.DUMMYFUNCTION("""COMPUTED_VALUE"""),"R") -> R | V136: =IFERROR(__xludf.DUMMYFUNCTION("""COMPUTED_VALUE"""),"検討中ランキング_クリエイティブ") -> 検討中ランキング_クリエイティブ | W136: =IFERROR(__xludf.DUMMYFUNCTION("""COMPUTED_VALUE"""),0.3) -> 0.3 | X136: =IFERROR(__xludf.DUMMYFUNCTION("""COMPUTED_VALUE"""),"R") -> R | AA136: =IFERROR(__xludf.DUMMYFUNCTION("""COMPUTED_VALUE"""),"名駅・栄駅で働く") -> 名駅・栄駅で働く | AB136: =IFERROR(__xludf.DUMMYFUNCTION("""COMPUTED_VALUE"""),0.6) -> 0.6 | AC136: =IFERROR(__xludf.DUMMYFUNCTION("""COMPUTED_VALUE"""),"R") -> R | AF136: =IFERROR(__xludf.DUMMYFUNCTION("""COMPUTED_VALUE"""),"応募から3日会員") -> 応募から3日会員 | AG136: =IFERROR(__xludf.DUMMYFUNCTION("""COMPUTED_VALUE"""),0.1) -> 0.1 | AH136: =IFERROR(__xludf.DUMMYFUNCTION("""COMPUTED_VALUE"""),"R") -> R
B137: =IFERROR(__xludf.DUMMYFUNCTION("""COMPUTED_VALUE"""),"フルリモート×フレックス_エンジニア") -> フルリモート×フレックス_エンジニア | C137: =IFERROR(__xludf.DUMMYFUNCTION("""COMPUTED_VALUE"""),0.7) -> 0.7 | D137: =IFERROR(__xludf.DUMMYFUNCTION("""COMPUTED_VALUE"""),"石") -> 石 | E137: =IFERROR(__xludf.DUMMYFUNCTION("""COMPUTED_VALUE"""),"部") -> 部 | G137: =IFERROR(__xludf.DUMMYFUNCTION("""COMPUTED_VALUE"""),"年収UP_事務") -> 年収UP_事務 | H137: =IFERROR(__xludf.DUMMYFUNCTION("""COMPUTED_VALUE"""),1.5) -> 1.5 | I137: =IFERROR(__xludf.DUMMYFUNCTION("""COMPUTED_VALUE"""),"R") -> R | L137: =IFERROR(__xludf.DUMMYFUNCTION("""COMPUTED_VALUE"""),"新働きやすさ_A_関西") -> 新働きやすさ_A_関西 | M137: =IFERROR(__xludf.DUMMYFUNCTION("""COMPUTED_VALUE"""),0.8) -> 0.8 | N137: =IFERROR(__xludf.DUMMYFUNCTION("""COMPUTED_VALUE"""),"R") -> R | V137: =IFERROR(__xludf.DUMMYFUNCTION("""COMPUTED_VALUE"""),"検討中ランキング_販サ") -> 検討中ランキング_販サ | W137: =IFERROR(__xludf.DUMMYFUNCTION("""COMPUTED_VALUE"""),0.4) -> 0.4 | X137: =IFERROR(__xludf.DUMMYFUNCTION("""COMPUTED_VALUE"""),"R") -> R
B138: =IFERROR(__xludf.DUMMYFUNCTION("""COMPUTED_VALUE"""),"フルリモート×フレックス_エンジニア＿関西") -> フルリモート×フレックス_エンジニア＿関西 | G138: =IFERROR(__xludf.DUMMYFUNCTION("""COMPUTED_VALUE"""),"年収UP_販サ") -> 年収UP_販サ | H138: =IFERROR(__xludf.DUMMYFUNCTION("""COMPUTED_VALUE"""),0.6) -> 0.6 | I138: =IFERROR(__xludf.DUMMYFUNCTION("""COMPUTED_VALUE"""),"R") -> R | L138: =IFERROR(__xludf.DUMMYFUNCTION("""COMPUTED_VALUE"""),"髪色・服装自由_事務") -> 髪色・服装自由_事務 | M138: =IFERROR(__xludf.DUMMYFUNCTION("""COMPUTED_VALUE"""),1.8) -> 1.8 | N138: =IFERROR(__xludf.DUMMYFUNCTION("""COMPUTED_VALUE"""),"R") -> R | V138: =IFERROR(__xludf.DUMMYFUNCTION("""COMPUTED_VALUE"""),"事務（一般事務）_希望") -> 事務（一般事務）_希望 | W138: =IFERROR(__xludf.DUMMYFUNCTION("""COMPUTED_VALUE"""),1.3) -> 1.3 | X138: =IFERROR(__xludf.DUMMYFUNCTION("""COMPUTED_VALUE"""),"R") -> R

Sheet ルール
A1: 26/4/14_編集版のルール
A2: ルール内容 | B2: 書式（色） | C2: 人間 | D2: Gemini
A3: **設定・確認完了** | B3: 赤 | C3: 確定版の設定・確認ごと手動で各自塗りつぶす
A4: **設定中（未確認）** | B4: なし
A5: **配信停止・未着手** | B5: グレー
A6: 設定者RPAのR | B6: 水色
A7: 確定後 | C7: 26/4/14(日付)_編集版を操作し、確定後は_確定版を新規作成する
A8: 編集版 | C8: リストとかマスタの条件書式を、編集版に相続したい。たとえば、C17が隔週Aなので緑に塗りつぶされてるのでそれを反映。そして配信停止の時はグレーになる
A9: リストシートの種別 | B9: 緑 | C9: ピンクと週替わりに配信
A10: リストシートの種別 | B10: ピンク | C10: 緑と週替わりに配信
A11: 特殊配信マスタのぴじしょん
B13: チェック観点 | Y13: 45420
B14: １ | C14: 日付と色のチェック
C15: 火曜日からスタートしているか
C16: 隔週が緑⇒桃⇒緑⇒と毎週変わっているか
B18: ２ | C18: ポジションマッチ
C19: A3・B3の時「◇ポジションマッチ 関西」がオープンする
C20: A1⇒A2⇒A3→A1→A2・・と毎週回る。Bも同様。どちらも3の時関西も配信する週になる
B22: ３ | C22: ☆IT派遣［全］
C23: └(第2・第4日曜)x月はx日・x日
C24: 月初作成時に記載しておく
B26: ４ | C26: 毎月は配信
C27: 月末1週間前は普段は閉じているグループをオープン
C28: 配信しない曜日はグレーアウトしておく
C29: 月末増発シートと内容があっているか確認
B31: ５ | C31: 検
C32: イレギュラー
C33: 水色に塗る
B35: ６ | C35: PR挿入
C36: └PR128掲載中(5/8迄)
C37: └PR128削除(5/8迄)
C38: └PR128削除(5/8迄)、PR129追加(6/5迄)
C39: 起票・終了したらレ点忘れず
B41: ７ | C41: 月初1日に要対応 20時の「当日新規会員」の荒木さんの名前の部分に以下コメント追加
C42: 「月初のため文面変更をお願い致します！」
C43: →このメルマガは毎月リード文を変更しております。そのため毎月1日に文面変更の依頼を荒木さんにコメントでしております。
C44: 参考：11/30のシートの12/1の該当箇所のコメントをご確認ください。
B46: ８ | C46: 前週のRPA化コメントの確認
B48: ９ | C48: 求人特集（35歳以上）
C49: └求人特集配信日のみオープン
C50: \\cdc-fs00.cdc.local\career\00_全社共有\01_企画課\求人特集一覧
C51: 求人特集の「30代・40代歓迎!ベテラン歓迎の求人特集」がある場合は、掲載される次の日（水か土）に16万通配信
C52: 増枠シート・スプレッドシートに「求人特集（35歳以上）」と記載 ※この特集のみ特別対応
C53: ※参考例：4/19週の4/23(土)18時 求人特集（35歳以上） 16万通
B55: ５． | C55: 長期休暇・・・休暇前後も含め休日の対応をチェック
A57: マスタ
A58: リスト | B58: 毎週固定配信
A59: 特殊配信マスタ | B59: ポジションマッチなどのサイクル配信
A60: 新規 | B60: 検証中やイレギュラー配信
A64: メルマガスケジュール作成メーカー：仕様書 (Rule.md)
A65: 1. 全体コンセプト
A67: スプレッドシート上の「マスタ（リスト・特殊配信）」に基づき、指定された期間（通常1週間：火〜月）の配信スケジュールを自動生成する。
A69: BOSS-Sへの入稿作業および、チーム内での進捗管理（色塗り）を効率化することを目的とする。
A71: 2. スケジュール生成ロジック
A72: 2.1 基本配信（「リスト」シート参照）
A74: 毎週配信: 指定した曜日に該当するものをすべて抽出。
A76: 隔週配信（A/B）: * 実行時に「今週がA週かB週か」を判定（またはユーザーが指定）。
A78: 隔週Aの週は「隔週A」のみ、Bの週は「隔週B」のみを抽出。
A80: セル色：マスタに基づき「緑」または「ピンク」を適用。
A81: 2.2 特殊配信（「特殊配信マスタ」シート参照）
A83: ポジションマッチ (A1〜A3 / B1〜B3):
... A120: 4. GAS実装機能（メソッド定義案）
A121: 関数名 | B121: 役割
A122: onOpen() | B122: スプシ上部に「スケジュール作成メニュー」を表示。
A123: getCurrentCycle() | B123: 前回のシート名から、現在の隔週(A/B)とポジションマッチ(1-3)を特定。
A124: generateSheet() | B124: メインロジック。日付計算、マスタ抽出、セル結合、書式設定を実行。
A125: applyPR() | B125: PR管理シートと照合し、文言やIDを自動挿入。
A126: createFinalVersion() | B126: 編集版から「確定版」を別シートとして書き出し。
A127: 5. 運用フロー（イメージ）
A129: 操作パネル で「次週の開始日（火）」を入力。
A131: 作成ボタン を押すと、GASがマスタを走査。
A133: 自動生成 された新しいシートに、今週必要な枠がすべて並ぶ。
A135: 担当者 が作業完了後、名前を入力 → 自動で赤色に！
A137: 広報 閲覧専用の「カレンダー」シートへ自動同期。
A140: ★自動求人特集メルマガ★
A141: 求人数が700超えてないか、毎週チェックしてから配信設定
A142: Q1回くらいで確認※200件以下を保つこと、危ないものはRPA外す
A143: →本部対応：1000件超えるとアウト。手動はその時点でみているので700件まで大丈夫としている。これはQ1回確認にしたので200件以下をボーダーラインとしている。

Sheet 新規
A1: 曜日 | B1: 時間 | C1: 開始 | D1: 終了 | E1: メルマガ内容 | F1: 通数 | G1: 種別 | H1: PR | I1: 形式 | J1: 対象年齢 | K1: 対象現住所 | L1: 自動求人特集ID | M1: 備考 | N1: 新規 | O1: 設定者 | P1: 確認者 | Q1: 配信停止 | R1: サイクル | S1: 今週サイクル(内部) | T1: 今週非配信(内部)
A2: 46113 | B2: 12 | E2: 5月入社可能 | F2: 2 | G2: 検 | I2: フリー | M2: ＜配信条件＞※2万通 年齢：35歳～60歳以上 最終ログイン日：40 | O2: 石 | P2: 部 | Q2: FALSE | R2: FALSE | S2: FALSE | T2: FALSE
A3: 46126 | B3: 21 | E3: フルリモート×フレックス_エンジニア | F3: 0.7 | G3: 検 | I3: 抽出 | O3: 石 | P3: 部 | Q3: FALSE | R3: FALSE | S3: FALSE | T3: FALSE
A4: 46127 | B4: 12 | E4: 5月入社可能 | F4: 2 | G4: 検 | I4: フリー | M4: ＜配信条件＞※2万通 年齢：35歳～60歳以上 最終ログイン日：40 | O4: 石 | P4: 部 | Q4: FALSE | R4: FALSE | S4: FALSE | T4: FALSE
A5: 46129 | B5: 20 | E5: 有給取得率 | F5: 2.2 | G5: 検 | I5: 抽出 | O5: 石 | P5: 武 | Q5: FALSE | R5: FALSE | S5: FALSE | T5: FALSE
A6: 46132 | B6: 20 | E6: 保育士_幼稚園教諭 | F6: 0.1 | G6: 検 | I6: 抽出 | O6: 石 | P6: 部 | Q6: FALSE | R6: FALSE | S6: FALSE | T6: FALSE
A7: 46132 | B7: 20 | E7: 保育士_幼稚園教諭 | M7: スプシ | N7: 26/04 | Q7: FALSE | R7: FALSE | S7: FALSE | T7: FALSE
A8: 46130 | B8: 10 | E8: JAD特集 | F8: 2 | G8: AP | I8: フリー | J8: 4/18(土) ～4/25(土) 4回 期間：4月18日～4月25日 通数：2万通 配信日： 配信対象：最終ログイン日から7日以内（19517人が該当） 抽出ID：20929 1社あたりの上限職種数：全て 抽出上限社数：150社 | Q8: FALSE | R8: FALSE | S8: FALSE | T8: FALSE
A9: 46137 | B9: 10 | E9: JAD特集 | F9: 2 | G9: AP | I9: フリー | J9: 4/18(土) ～4/25(土) 4回 期間：4月18日～4月25日 通数：2万通 配信日： 配信対象：最終ログイン日から7日以内（19517人が該当） 抽出ID：20929 1社あたりの上限職種数：全て 抽出上限社数：150社 | Q9: FALSE | R9: FALSE | S9: FALSE | T9: FALSE
A10: 46091 | B10: 11 | E10: エンジニアフェア | G10: type課 | I10: フリー | J10: 3/10(火)～4/7(火) 現住所：関東 新規会員の指定：最新レジュメ更新日からの経過日数を指定 経過日数を指定：※上限の8.5万通以下になるよう設定お願いいたします。 ※文面にも記載いたします。 | Q10: FALSE | R10: FALSE | S10: FALSE | T10: FALSE
A11: 46098 | B11: 11 | E11: エンジニアフェア | G11: type課 | I11: フリー | J11: 3/10(火)～4/7(火) 現住所：関東 新規会員の指定：最新レジュメ更新日からの経過日数を指定 経過日数を指定：※上限の8.5万通以下になるよう設定お願いいたします。 ※文面にも記載いたします。 | Q11: FALSE | R11: FALSE | S11: FALSE | T11: FALSE
A12: 46105 | B12: 11 | E12: エンジニアフェア | G12: type課 | I12: フリー | J12: 3/10(火)～4/7(火) 現住所：関東 新規会員の指定：最新レジュメ更新日からの経過日数を指定 経過日数を指定：※上限の8.5万通以下になるよう設定お願いいたします。 ※文面にも記載いたします。 | Q12: FALSE | R12: FALSE | S12: FALSE | T12: FALSE
A13: 46112 | B13: 11 | E13: エンジニアフェア | G13: type課 | I13: フリー | J13: 3/10(火)～4/7(火) 現住所：関東 新規会員の指定：最新レジュメ更新日からの経過日数を指定 経過日数を指定：※上限の8.5万通以下になるよう設定お願いいたします。 ※文面にも記載いたします。 | Q13: FALSE | R13: FALSE | S13: FALSE | T13: FALSE
A14: 46119 | B14: 11 | E14: エンジニアフェア | G14: type課 | I14: フリー | J14: 3/10(火)～4/7(火) 現住所：関東 新規会員の指定：最新レジュメ更新日からの経過日数を指定 経過日数を指定：※上限の8.5万通以下になるよう設定お願いいたします。 ※文面にも記載いたします。 | Q14: FALSE | R14: FALSE | S14: FALSE | T14: FALSE
A15: 46119 | B15: 21 | E15: フルリモート×フレックス_エンジニア | M15: スプシ | Q15: FALSE | R15: FALSE | S15: FALSE | T15: FALSE
A16: 46122 | B16: 20 | E16: 有給取得率② | M16: スプシ | Q16: FALSE | R16: FALSE | S16: FALSE | T16: FALSE
A17: 46126 | B17: 21 | E17: フルリモート×フレックス_エンジニア＿関西 | M17: スプシ | Q17: FALSE | R17: FALSE | S17: FALSE | T17: FALSE
A18: 46129 | B18: 20 | E18: 有給取得率① | M18: スプシ | Q18: FALSE | R18: FALSE | S18: FALSE | T18: FALSE

Sheet リスト
A1: 46126 | B1: ='26414_編集版'!B1 -> 46126
A2: 曜日 | B2: 時間 | C2: 開始 | D2: 終了 | E2: メルマガ内容 | F2: 通数 | G2: 種別 | H2: PR | I2: 形式 | J2: 対象年齢 | K2: 対象現住所 | L2: 自動求人特集ID | M2: 備考 | N2: 新規 | O2: 設定者 | P2: 確認者 | Q2: 配信停止 | R2: サイクル | S2: 今週サイクル(内部) | T2: 今週非配信(内部)
A3: 火 | B3: 9 | E3: ランキング×WEBマーケティング | F3: 0.4 | G3: 隔週A | I3: 抽出 | O3: 部 | P3: 石 | Q3: =IF(G3="隔週A", MOD(INT(('26414_編集版'!$B$1-DATE(2026,4,14))/7), 2)=1, IF(G3="隔週B", MOD(INT(('26414_編集版'!$B$1-DATE(2026,4,14))/7), 2)=0, FALSE)) -> FALSE
A4: 火 | B4: 15 | E4: ECサイト運用_未経験 | F4: 0.7 | G4: 隔週A | I4: 抽出 | O4: 福 | P4: 部 | Q4: =IF(G4="隔週A", MOD(INT(('26414_編集版'!$B$1-DATE(2026,4,14))/7), 2)=1, IF(G4="隔週B", MOD(INT(('26414_編集版'!$B$1-DATE(2026,4,14))/7), 2)=0, FALSE)) -> FALSE
A5: 火 | B5: 17 | E5: 引っ越し特典 | F5: 2.3 | G5: 隔週A | I5: 抽出 | O5: 部 | P5: 石 | Q5: =IF(G5="隔週A", MOD(INT(('26414_編集版'!$B$1-DATE(2026,4,14))/7), 2)=1, IF(G5="隔週B", MOD(INT(('26414_編集版'!$B$1-DATE(2026,4,14))/7), 2)=0, FALSE)) -> FALSE
A6: 金 | B6: 13 | E6: 外部人気求人ランキング | F6: 1.4 | G6: 隔週A | I6: 抽出 | O6: 石 | P6: 部 | Q6: =IF(G6="隔週A", MOD(INT(('26414_編集版'!$B$1-DATE(2026,4,14))/7), 2)=1, IF(G6="隔週B", MOD(INT(('26414_編集版'!$B$1-DATE(2026,4,14))/7), 2)=0, FALSE)) -> FALSE
A7: 金 | B7: 19 | E7: TP部_リモート×未経験OKの求人特集 | F7: 1.9 | G7: 隔週A | I7: 抽出 | O7: 部 | P7: 石 | Q7: =IF(G7="隔週A", MOD(INT(('26414_編集版'!$B$1-DATE(2026,4,14))/7), 2)=1, IF(G7="隔週B", MOD(INT(('26414_編集版'!$B$1-DATE(2026,4,14))/7), 2)=0, FALSE)) -> FALSE
A8: 金 | B8: 20 | E8: ２回目転職×称号 | F8: 0.9 | G8: 隔週A | I8: 抽出 | O8: 部 | P8: 石 | Q8: =IF(G8="隔週A", MOD(INT(('26414_編集版'!$B$1-DATE(2026,4,14))/7), 2)=1, IF(G8="隔週B", MOD(INT(('26414_編集版'!$B$1-DATE(2026,4,14))/7), 2)=0, FALSE)) -> FALSE
A9: 月 | B9: 12 | E9: 未経験OK_専門性の高い事務 | F9: 1.4 | G9: 隔週A | I9: 抽出 | O9: 部 | P9: 石 | Q9: =IF(G9="隔週A", MOD(INT(('26414_編集版'!$B$1-DATE(2026,4,14))/7), 2)=1, IF(G9="隔週B", MOD(INT(('26414_編集版'!$B$1-DATE(2026,4,14))/7), 2)=0, FALSE)) -> FALSE
A10: 月 | B10: 19 | E10: 超好条件_営業 | F10: 0.9 | G10: 隔週A | I10: 抽出 | O10: 部 | P10: 石 | Q10: =IF(G10="隔週A", MOD(INT(('26414_編集版'!$B$1-DATE(2026,4,14))/7), 2)=1, IF(G10="隔週B", MOD(INT(('26414_編集版'!$B$1-DATE(2026,4,14))/7), 2)=0, FALSE)) -> FALSE
A11: 水 | B11: 18 | E11: 過去会員×フルリモート×未経験歓迎 | F11: 8.5 | G11: 隔週A | I11: 抽出 | O11: 部 | P11: 石 | Q11: =IF(G11="隔週A", MOD(INT(('26414_編集版'!$B$1-DATE(2026,4,14))/7), 2)=1, IF(G11="隔週B", MOD(INT(('26414_編集版'!$B$1-DATE(2026,4,14))/7), 2)=0, FALSE)) -> FALSE
A12: 土 | B12: 11 | E12: フレックス_ランキング | F12: 2 | G12: 隔週A | I12: 抽出 | O12: 石 | P12: 福 | Q12: =IF(G12="隔週A", MOD(INT(('26414_編集版'!$B$1-DATE(2026,4,14))/7), 2)=1, IF(G12="隔週B", MOD(INT(('26414_編集版'!$B$1-DATE(2026,4,14))/7), 2)=0, FALSE)) -> FALSE
A13: 土 | B13: 12 | E13: 高層ビルで働く_首都圏 | F13: 1.6 | G13: 隔週A | I13: 抽出 | O13: 部 | P13: 石 | Q13: =IF(G13="隔週A", MOD(INT(('26414_編集版'!$B$1-DATE(2026,4,14))/7), 2)=1, IF(G13="隔週B", MOD(INT(('26414_編集版'!$B$1-DATE(2026,4,14))/7), 2)=0, FALSE)) -> FALSE
A14: 土 | B14: 12 | E14: 高層ビルで働く_大阪 | F14: 0.5 | G14: 隔週A | I14: 抽出 | O14: 部 | P14: 石 | Q14: =IF(G14="隔週A", MOD(INT(('26414_編集版'!$B$1-DATE(2026,4,14))/7), 2)=1, IF(G14="隔週B", MOD(INT(('26414_編集版'!$B$1-DATE(2026,4,14))/7), 2)=0, FALSE)) -> FALSE
... A31: 金 | B31: 18 | E31: 高収入_未経験OK | F31: 3 | G31: 隔週B | I31: 抽出 | O31: 武 | P31: 部 | Q31: =IF(G31="隔週A", MOD(INT(('26414_編集版'!$B$1-DATE(2026,4,14))/7), 2)=1, IF(G31="隔週B", MOD(INT(('26414_編集版'!$B$1-DATE(2026,4,14))/7), 2)=0, FALSE)) -> TRUE
A32: 金 | B32: 19 | E32: TP部_リモートOK×女性管理職在籍の求人特集 | F32: 1.3 | G32: 隔週B | I32: 抽出 | J32: 対象年齢 | K32: 対象現住所 | O32: 部 | P32: 石 | Q32: =IF(G32="隔週A", MOD(INT(('26414_編集版'!$B$1-DATE(2026,4,14))/7), 2)=1, IF(G32="隔週B", MOD(INT(('26414_編集版'!$B$1-DATE(2026,4,14))/7), 2)=0, FALSE)) -> TRUE
A33: 月 | B33: 18 | E33: 四国で働く | F33: 0.1 | G33: 隔週B | I33: 抽出 | O33: 部 | P33: 武 | Q33: =IF(G33="隔週A", MOD(INT(('26414_編集版'!$B$1-DATE(2026,4,14))/7), 2)=1, IF(G33="隔週B", MOD(INT(('26414_編集版'!$B$1-DATE(2026,4,14))/7), 2)=0, FALSE)) -> TRUE
A34: 月 | B34: 18 | E34: 大阪で働く | F34: 1.2 | G34: 隔週B | I34: 抽出 | O34: 部 | P34: 武 | Q34: =IF(G34="隔週A", MOD(INT(('26414_編集版'!$B$1-DATE(2026,4,14))/7), 2)=1, IF(G34="隔週B", MOD(INT(('26414_編集版'!$B$1-DATE(2026,4,14))/7), 2)=0, FALSE)) -> TRUE
A35: 月 | B35: 18 | E35: 東北で働く | F35: 0.4 | G35: 隔週B | I35: 抽出 | O35: 部 | P35: 武 | Q35: =IF(G35="隔週A", MOD(INT(('26414_編集版'!$B$1-DATE(2026,4,14))/7), 2)=1, IF(G35="隔週B", MOD(INT(('26414_編集版'!$B$1-DATE(2026,4,14))/7), 2)=0, FALSE)) -> TRUE
A36: 月 | B36: 18 | E36: 北陸で働く | F36: 0.2 | G36: 隔週B | I36: 抽出 | O36: 部 | P36: 武 | Q36: =IF(G36="隔週A", MOD(INT(('26414_編集版'!$B$1-DATE(2026,4,14))/7), 2)=1, IF(G36="隔週B", MOD(INT(('26414_編集版'!$B$1-DATE(2026,4,14))/7), 2)=0, FALSE)) -> TRUE
A37: 月 | B37: 19 | E37: 埼玉_路線_B | F37: 0.7 | G37: 隔週B | I37: 抽出 | O37: 部 | P37: 内 | Q37: =IF(G37="隔週A", MOD(INT(('26414_編集版'!$B$1-DATE(2026,4,14))/7), 2)=1, IF(G37="隔週B", MOD(INT(('26414_編集版'!$B$1-DATE(2026,4,14))/7), 2)=0, FALSE)) -> TRUE
A38: 月 | B38: 19 | E38: 神奈川_路線_B | F38: 0.9 | G38: 隔週B | I38: 抽出 | O38: 部 | P38: 内 | Q38: =IF(G38="隔週A", MOD(INT(('26414_編集版'!$B$1-DATE(2026,4,14))/7), 2)=1, IF(G38="隔週B", MOD(INT(('26414_編集版'!$B$1-DATE(2026,4,14))/7), 2)=0, FALSE)) -> TRUE
A39: 月 | B39: 19 | E39: 千葉_路線_B | F39: 0.6 | G39: 隔週B | I39: 抽出 | O39: 部 | P39: 内 | Q39: =IF(G39="隔週A", MOD(INT(('26414_編集版'!$B$1-DATE(2026,4,14))/7), 2)=1, IF(G39="隔週B", MOD(INT(('26414_編集版'!$B$1-DATE(2026,4,14))/7), 2)=0, FALSE)) -> TRUE
A40: 月 | B40: 19 | E40: 東京_路線_事務_B | F40: 1 | G40: 隔週B | I40: 抽出 | O40: 部 | P40: 内 | Q40: =IF(G40="隔週A", MOD(INT(('26414_編集版'!$B$1-DATE(2026,4,14))/7), 2)=1, IF(G40="隔週B", MOD(INT(('26414_編集版'!$B$1-DATE(2026,4,14))/7), 2)=0, FALSE)) -> TRUE
A41: 水 | B41: 11 | E41: 外資系企業 | F41: 2.5 | G41: 隔週B | I41: 抽出 | O41: 福 | P41: 部 | Q41: =IF(G41="隔週A", MOD(INT(('26414_編集版'!$B$1-DATE(2026,4,14))/7), 2)=1, IF(G41="隔週B", MOD(INT(('26414_編集版'!$B$1-DATE(2026,4,14))/7), 2)=0, FALSE)) -> TRUE
A42: 水 | B42: 12 | E42: 人気検索KW_営業系希望 | F42: 0.3 | G42: 隔週B | I42: 抽出 | O42: 部 | P42: 石 | Q42: =IF(G42="隔週A", MOD(INT(('26414_編集版'!$B$1-DATE(2026,4,14))/7), 2)=1, IF(G42="隔週B", MOD(INT(('26414_編集版'!$B$1-DATE(2026,4,14))/7), 2)=0, FALSE)) -> TRUE
A43: 水 | B43: 18 | E43: ☆営業_経験_35歳以上_首都圏版 | F43: 0.1 | G43: 隔週B | I43: 抽出 | O43: 部 | P43: 荒 | Q43: =IF(G43="隔週A", MOD(INT(('26414_編集版'!$B$1-DATE(2026,4,14))/7), 2)=1, IF(G43="隔週B", MOD(INT(('26414_編集版'!$B$1-DATE(2026,4,14))/7), 2)=0, FALSE)) -> TRUE
A44: 水 | B44: 18 | E44: ☆営業_未経験_35歳以上_首都圏版 | F44: 0.2 | G44: 隔週B | I44: 抽出 | O44: 部 | P44: 荒 | Q44: =IF(G44="隔週A", MOD(INT(('26414_編集版'!$B$1-DATE(2026,4,14))/7), 2)=1, IF(G44="隔週B", MOD(INT(('26414_編集版'!$B$1-DATE(2026,4,14))/7), 2)=0, FALSE)) -> TRUE
... A59: 木 | B59: 19 | E59: 首都圏‗事務×リモート×フレックス | F59: 2 | G59: 隔週B | I59: 抽出 | O59: 部 | P59: 武 | Q59: =IF(G59="隔週A", MOD(INT(('26414_編集版'!$B$1-DATE(2026,4,14))/7), 2)=1, IF(G59="隔週B", MOD(INT(('26414_編集版'!$B$1-DATE(2026,4,14))/7), 2)=0, FALSE)) -> TRUE
A60: 火 | B60: 8 | E60: 関西_自己PR不要_リモート未経験_事務 | F60: 0.2 | G60: 毎週配信 | I60: 自動求人 | L60: 24376 | M60: https://woman-type.jp/job-office/24376/f/ | O60: R | Q60: =IF(G60="隔週A", MOD(INT(('26414_編集版'!$B$1-DATE(2026,4,14))/7), 2)=1, IF(G60="隔週B", MOD(INT(('26414_編集版'!$B$1-DATE(2026,4,14))/7), 2)=0, FALSE)) -> FALSE
A61: 火 | B61: 8 | E61: 応募から1日_好条件営業ランキング | F61: 0.1 | G61: 毎週配信 | I61: 抽出 | O61: R | Q61: =IF(G61="隔週A", MOD(INT(('26414_編集版'!$B$1-DATE(2026,4,14))/7), 2)=1, IF(G61="隔週B", MOD(INT(('26414_編集版'!$B$1-DATE(2026,4,14))/7), 2)=0, FALSE)) -> FALSE
A62: 火 | B62: 8 | E62: 快適な在宅ワーク | F62: 4.3 | G62: 毎週配信 | I62: 抽出 | O62: 石 | P62: 部 | Q62: =IF(G62="隔週A", MOD(INT(('26414_編集版'!$B$1-DATE(2026,4,14))/7), 2)=1, IF(G62="隔週B", MOD(INT(('26414_編集版'!$B$1-DATE(2026,4,14))/7), 2)=0, FALSE)) -> FALSE
A63: 火 | B63: 8 | E63: 推し活_残業なし_休日120日以上_月給30万以上 | F63: 1.2 | G63: 毎週配信 | I63: 抽出 | O63: R | Q63: =IF(G63="隔週A", MOD(INT(('26414_編集版'!$B$1-DATE(2026,4,14))/7), 2)=1, IF(G63="隔週B", MOD(INT(('26414_編集版'!$B$1-DATE(2026,4,14))/7), 2)=0, FALSE)) -> FALSE
A64: 火 | B64: 9 | E64: ランキング_クリエイティブ（Web）_希望 | F64: 0.5 | G64: 毎週配信 | I64: 抽出 | O64: R | Q64: =IF(G64="隔週A", MOD(INT(('26414_編集版'!$B$1-DATE(2026,4,14))/7), 2)=1, IF(G64="隔週B", MOD(INT(('26414_編集版'!$B$1-DATE(2026,4,14))/7), 2)=0, FALSE)) -> FALSE
A65: 火 | B65: 9 | E65: ランキング_営業（マーケ）_希望 | F65: 0.5 | G65: 毎週配信 | I65: 抽出 | O65: R | Q65: =IF(G65="隔週A", MOD(INT(('26414_編集版'!$B$1-DATE(2026,4,14))/7), 2)=1, IF(G65="隔週B", MOD(INT(('26414_編集版'!$B$1-DATE(2026,4,14))/7), 2)=0, FALSE)) -> FALSE
A66: 火 | B66: 9 | E66: ランキング_事務（一般事務）_希望 | F66: 1.5 | G66: 毎週配信 | I66: 抽出 | O66: R | Q66: =IF(G66="隔週A", MOD(INT(('26414_編集版'!$B$1-DATE(2026,4,14))/7), 2)=1, IF(G66="隔週B", MOD(INT(('26414_編集版'!$B$1-DATE(2026,4,14))/7), 2)=0, FALSE)) -> FALSE
A67: 火 | B67: 10 | E67: 事務_販サ経験者向け_東京 | F67: 0.4 | G67: 毎週配信 | I67: 抽出 | O67: R | Q67: =IF(G67="隔週A", MOD(INT(('26414_編集版'!$B$1-DATE(2026,4,14))/7), 2)=1, IF(G67="隔週B", MOD(INT(('26414_編集版'!$B$1-DATE(2026,4,14))/7), 2)=0, FALSE)) -> FALSE
A68: 火 | B68: 10 | E68: 面接1回 | F68: 1.5 | G68: 毎週配信 | I68: 抽出 | O68: R | Q68: =IF(G68="隔週A", MOD(INT(('26414_編集版'!$B$1-DATE(2026,4,14))/7), 2)=1, IF(G68="隔週B", MOD(INT(('26414_編集版'!$B$1-DATE(2026,4,14))/7), 2)=0, FALSE)) -> FALSE
A69: 火 | B69: 10 | E69: 面接1回_35歳以上 | F69: 1 | G69: 毎週配信 | I69: 抽出 | O69: R | Q69: =IF(G69="隔週A", MOD(INT(('26414_編集版'!$B$1-DATE(2026,4,14))/7), 2)=1, IF(G69="隔週B", MOD(INT(('26414_編集版'!$B$1-DATE(2026,4,14))/7), 2)=0, FALSE)) -> FALSE
A70: 火 | B70: 11 | E70: 事務（経理）_希望 | F70: 0.5 | G70: 毎週配信 | I70: 抽出 | O70: R | Q70: =IF(G70="隔週A", MOD(INT(('26414_編集版'!$B$1-DATE(2026,4,14))/7), 2)=1, IF(G70="隔週B", MOD(INT(('26414_編集版'!$B$1-DATE(2026,4,14))/7), 2)=0, FALSE)) -> FALSE
A71: 火 | B71: 12 | E71: ★新着総合_首都圏 A | F71: 5 | G71: 毎週配信 | I71: 抽出 | O71: 荒 | P71: 平 | Q71: =IF(G71="隔週A", MOD(INT(('26414_編集版'!$B$1-DATE(2026,4,14))/7), 2)=1, IF(G71="隔週B", MOD(INT(('26414_編集版'!$B$1-DATE(2026,4,14))/7), 2)=0, FALSE)) -> FALSE
A72: 火 | B72: 12 | E72: ★新着総合_西日本 A | F72: 2.9 | G72: 毎週配信 | I72: 抽出 | O72: 荒 | P72: 平 | Q72: =IF(G72="隔週A", MOD(INT(('26414_編集版'!$B$1-DATE(2026,4,14))/7), 2)=1, IF(G72="隔週B", MOD(INT(('26414_編集版'!$B$1-DATE(2026,4,14))/7), 2)=0, FALSE)) -> FALSE
A73: 火 | B73: 12 | E73: ★新着総合_東海 A | F73: 1 | G73: 毎週配信 | I73: 抽出 | O73: 荒 | P73: 平 | Q73: =IF(G73="隔週A", MOD(INT(('26414_編集版'!$B$1-DATE(2026,4,14))/7), 2)=1, IF(G73="隔週B", MOD(INT(('26414_編集版'!$B$1-DATE(2026,4,14))/7), 2)=0, FALSE)) -> FALSE
A74: 火 | B74: 12 | E74: ★新着総合_北海道・東北 A | F74: 0.8 | G74: 毎週配信 | I74: 抽出 | O74: 荒 | P74: 平 | Q74: =IF(G74="隔週A", MOD(INT(('26414_編集版'!$B$1-DATE(2026,4,14))/7), 2)=1, IF(G74="隔週B", MOD(INT(('26414_編集版'!$B$1-DATE(2026,4,14))/7), 2)=0, FALSE)) -> FALSE
A75: 火 | B75: 12 | E75: ★新着総合_北関東・甲信越・北陸 A | F75: 0.7 | G75: 毎週配信 | I75: 抽出 | O75: 荒 | P75: 平 | Q75: =IF(G75="隔週A", MOD(INT(('26414_編集版'!$B$1-DATE(2026,4,14))/7), 2)=1, IF(G75="隔週B", MOD(INT(('26414_編集版'!$B$1-DATE(2026,4,14))/7), 2)=0, FALSE)) -> FALSE
A76: 火 | B76: 14 | E76: 福祉事務 | F76: 1.2 | G76: 毎週配信 | I76: 抽出 | O76: R | Q76: =IF(G76="隔週A", MOD(INT(('26414_編集版'!$B$1-DATE(2026,4,14))/7), 2)=1, IF(G76="隔週B", MOD(INT(('26414_編集版'!$B$1-DATE(2026,4,14))/7), 2)=0, FALSE)) -> FALSE
A77: 火 | B77: 14 | E77: 福祉事務_35歳以上 | F77: 1 | G77: 毎週配信 | I77: 抽出 | O77: R | Q77: =IF(G77="隔週A", MOD(INT(('26414_編集版'!$B$1-DATE(2026,4,14))/7), 2)=1, IF(G77="隔週B", MOD(INT(('26414_編集版'!$B$1-DATE(2026,4,14))/7), 2)=0, FALSE)) -> FALSE
A78: 火 | B78: 14 | E78: 未経験向け急募求人_クリエイティブ | F78: 0.5 | G78: 毎週配信 | I78: 抽出 | O78: R | Q78: =IF(G78="隔週A", MOD(INT(('26414_編集版'!$B$1-DATE(2026,4,14))/7), 2)=1, IF(G78="隔週B", MOD(INT(('26414_編集版'!$B$1-DATE(2026,4,14))/7), 2)=0, FALSE)) -> FALSE
A79: 火 | B79: 14 | E79: 未経験向け急募求人_営業 | F79: 0.5 | G79: 毎週配信 | I79: 抽出 | O79: R | Q79: =IF(G79="隔週A", MOD(INT(('26414_編集版'!$B$1-DATE(2026,4,14))/7), 2)=1, IF(G79="隔週B", MOD(INT(('26414_編集版'!$B$1-DATE(2026,4,14))/7), 2)=0, FALSE)) -> FALSE
A80: 火 | B80: 14 | E80: 未経験向け急募求人_事務 | F80: 1 | G80: 毎週配信 | I80: 抽出 | O80: R | Q80: =IF(G80="隔週A", MOD(INT(('26414_編集版'!$B$1-DATE(2026,4,14))/7), 2)=1, IF(G80="隔週B", MOD(INT(('26414_編集版'!$B$1-DATE(2026,4,14))/7), 2)=0, FALSE)) -> FALSE
A81: 火 | B81: 15 | E81: 好条件×業務委託 | F81: 0.4 | G81: 毎週配信 | I81: 抽出 | O81: 部 | P81: 武 | Q81: =IF(G81="隔週A", MOD(INT(('26414_編集版'!$B$1-DATE(2026,4,14))/7), 2)=1, IF(G81="隔週B", MOD(INT(('26414_編集版'!$B$1-DATE(2026,4,14))/7), 2)=0, FALSE)) -> FALSE
A82: 火 | B82: 15 | E82: 好条件×契約社員 | F82: 1.2 | G82: 毎週配信 | I82: 抽出 | O82: R | Q82: =IF(G82="隔週A", MOD(INT(('26414_編集版'!$B$1-DATE(2026,4,14))/7), 2)=1, IF(G82="隔週B", MOD(INT(('26414_編集版'!$B$1-DATE(2026,4,14))/7), 2)=0, FALSE)) -> FALSE
A83: 火 | B83: 16 | E83: 35歳以上向け A | F83: 1 | G83: 毎週配信 | I83: 抽出 | O83: R | Q83: =IF(G83="隔週A", MOD(INT(('26414_編集版'!$B$1-DATE(2026,4,14))/7), 2)=1, IF(G83="隔週B", MOD(INT(('26414_編集版'!$B$1-DATE(2026,4,14))/7), 2)=0, FALSE)) -> FALSE
A84: 火 | B84: 16 | E84: 育児両立_フレックス | F84: 0.6 | G84: 毎週配信 | I84: 抽出 | J84: 対象年齢 | K84: 対象現住所 | O84: R | Q84: =IF(G84="隔週A", MOD(INT(('26414_編集版'!$B$1-DATE(2026,4,14))/7), 2)=1, IF(G84="隔週B", MOD(INT(('26414_編集版'!$B$1-DATE(2026,4,14))/7), 2)=0, FALSE)) -> FALSE
A85: 火 | B85: 17 | E85: ◇応募ランキング A | F85: 0.7 | G85: 毎週配信 | I85: 抽出 | O85: 荒 | P85: 平 | Q85: =IF(G85="隔週A", MOD(INT(('26414_編集版'!$B$1-DATE(2026,4,14))/7), 2)=1, IF(G85="隔週B", MOD(INT(('26414_編集版'!$B$1-DATE(2026,4,14))/7), 2)=0, FALSE)) -> FALSE
A86: 火 | B86: 17 | E86: 仙台_リモートOK_未経験 | F86: 0.2 | G86: 毎週配信 | I86: 抽出 | O86: R | Q86: =IF(G86="隔週A", MOD(INT(('26414_編集版'!$B$1-DATE(2026,4,14))/7), 2)=1, IF(G86="隔週B", MOD(INT(('26414_編集版'!$B$1-DATE(2026,4,14))/7), 2)=0, FALSE)) -> FALSE
A87: 火 | B87: 17 | E87: 大阪_リモートOK_未経験 | F87: 0.7 | G87: 毎週配信 | I87: 抽出 | O87: R | Q87: =IF(G87="隔週A", MOD(INT(('26414_編集版'!$B$1-DATE(2026,4,14))/7), 2)=1, IF(G87="隔週B", MOD(INT(('26414_編集版'!$B$1-DATE(2026,4,14))/7), 2)=0, FALSE)) -> FALSE
A88: 火 | B88: 17 | E88: 単独求人訴求メルマガ_B | F88: 2.9 | G88: 毎週配信 | I88: フリー | O88: 武 | P88: 部 | Q88: =IF(G88="隔週A", MOD(INT(('26414_編集版'!$B$1-DATE(2026,4,14))/7), 2)=1, IF(G88="隔週B", MOD(INT(('26414_編集版'!$B$1-DATE(2026,4,14))/7), 2)=0, FALSE)) -> FALSE
A89: 火 | B89: 17 | E89: 福岡_リモートOK_未経験 | F89: 0.4 | G89: 毎週配信 | I89: 抽出 | O89: R | Q89: =IF(G89="隔週A", MOD(INT(('26414_編集版'!$B$1-DATE(2026,4,14))/7), 2)=1, IF(G89="隔週B", MOD(INT(('26414_編集版'!$B$1-DATE(2026,4,14))/7), 2)=0, FALSE)) -> FALSE
A90: 火 | B90: 18 | E90: ☆エンジニア_経験_首都圏版 | F90: 0.1 | G90: 毎週配信 | I90: 抽出 | O90: 部 | P90: 内 | Q90: =IF(G90="隔週A", MOD(INT(('26414_編集版'!$B$1-DATE(2026,4,14))/7), 2)=1, IF(G90="隔週B", MOD(INT(('26414_編集版'!$B$1-DATE(2026,4,14))/7), 2)=0, FALSE)) -> FALSE
A91: 火 | B91: 18 | E91: ☆エンジニア_未経験_首都圏版 | F91: 0.4 | G91: 毎週配信 | I91: 抽出 | O91: 部 | P91: 内 | Q91: =IF(G91="隔週A", MOD(INT(('26414_編集版'!$B$1-DATE(2026,4,14))/7), 2)=1, IF(G91="隔週B", MOD(INT(('26414_編集版'!$B$1-DATE(2026,4,14))/7), 2)=0, FALSE)) -> FALSE
A92: 火 | B92: 19 | E92: 35歳以上向け_関西 A | F92: 0.3 | G92: 毎週配信 | I92: 抽出 | O92: R | Q92: =IF(G92="隔週A", MOD(INT(('26414_編集版'!$B$1-DATE(2026,4,14))/7), 2)=1, IF(G92="隔週B", MOD(INT(('26414_編集版'!$B$1-DATE(2026,4,14))/7), 2)=0, FALSE)) -> FALSE
A93: 火 | B93: 19 | E93: 40代ラスト転職 | F93: 0.9 | G93: 毎週配信 | I93: 抽出 | O93: R | Q93: =IF(G93="隔週A", MOD(INT(('26414_編集版'!$B$1-DATE(2026,4,14))/7), 2)=1, IF(G93="隔週B", MOD(INT(('26414_編集版'!$B$1-DATE(2026,4,14))/7), 2)=0, FALSE)) -> FALSE
A94: 火 | B94: 19 | E94: TP部_営業_現住所 | F94: 2 | G94: 毎週配信 | I94: 抽出 | O94: R | Q94: =IF(G94="隔週A", MOD(INT(('26414_編集版'!$B$1-DATE(2026,4,14))/7), 2)=1, IF(G94="隔週B", MOD(INT(('26414_編集版'!$B$1-DATE(2026,4,14))/7), 2)=0, FALSE)) -> FALSE
A95: 火 | B95: 19 | E95: フルリモート_全国_エンジニア | F95: 1.3 | G95: 毎週配信 | I95: 抽出 | O95: R | Q95: =IF(G95="隔週A", MOD(INT(('26414_編集版'!$B$1-DATE(2026,4,14))/7), 2)=1, IF(G95="隔週B", MOD(INT(('26414_編集版'!$B$1-DATE(2026,4,14))/7), 2)=0, FALSE)) -> FALSE
A96: 火 | B96: 19 | E96: フルリモート_全国_営業 | F96: 1.8 | G96: 毎週配信 | I96: 抽出 | O96: R | Q96: =IF(G96="隔週A", MOD(INT(('26414_編集版'!$B$1-DATE(2026,4,14))/7), 2)=1, IF(G96="隔週B", MOD(INT(('26414_編集版'!$B$1-DATE(2026,4,14))/7), 2)=0, FALSE)) -> FALSE
A97: 火 | B97: 19 | E97: フルリモート_全国_事務 | F97: 5.5 | G97: 毎週配信 | I97: 抽出 | O97: R | Q97: =IF(G97="隔週A", MOD(INT(('26414_編集版'!$B$1-DATE(2026,4,14))/7), 2)=1, IF(G97="隔週B", MOD(INT(('26414_編集版'!$B$1-DATE(2026,4,14))/7), 2)=0, FALSE)) -> FALSE
A98: 火 | B98: 19 | E98: 未経験_研修・資格_事務系_関西 | F98: 0.3 | G98: 毎週配信 | I98: 抽出 | O98: R | Q98: =IF(G98="隔週A", MOD(INT(('26414_編集版'!$B$1-DATE(2026,4,14))/7), 2)=1, IF(G98="隔週B", MOD(INT(('26414_編集版'!$B$1-DATE(2026,4,14))/7), 2)=0, FALSE)) -> FALSE
A99: 火 | B99: 19 | E99: 未経験_研修・資格_事務系_首都圏 | F99: 1.3 | G99: 毎週配信 | I99: 抽出 | O99: R | Q99: =IF(G99="隔週A", MOD(INT(('26414_編集版'!$B$1-DATE(2026,4,14))/7), 2)=1, IF(G99="隔週B", MOD(INT(('26414_編集版'!$B$1-DATE(2026,4,14))/7), 2)=0, FALSE)) -> FALSE
A100: 火 | B100: 20 | E100: 当日新規会員 | F100: 0.1 | G100: 毎週配信 | I100: 抽出 | O100: 荒 | P100: 内 | Q100: =IF(G100="隔週A", MOD(INT(('26414_編集版'!$B$1-DATE(2026,4,14))/7), 2)=1, IF(G100="隔週B", MOD(INT(('26414_編集版'!$B$1-DATE(2026,4,14))/7), 2)=0, FALSE)) -> FALSE
A101: 火 | B101: 21 | E101: WEB面接・コロナ対策 | F101: 9.3 | G101: 毎週配信 | I101: 抽出 | O101: R | Q101: =IF(G101="隔週A", MOD(INT(('26414_編集版'!$B$1-DATE(2026,4,14))/7), 2)=1, IF(G101="隔週B", MOD(INT(('26414_編集版'!$B$1-DATE(2026,4,14))/7), 2)=0, FALSE)) -> FALSE
A102: 火 | B102: 21 | E102: ランキング_事務（貿易事務）_希望 | F102: 0.4 | G102: 毎週配信 | I102: 抽出 | O102: R | Q102: =IF(G102="隔週A", MOD(INT(('26414_編集版'!$B$1-DATE(2026,4,14))/7), 2)=1, IF(G102="隔週B", MOD(INT(('26414_編集版'!$B$1-DATE(2026,4,14))/7), 2)=0, FALSE)) -> FALSE
A103: 火 | B103: 21 | E103: 応募から1日_好条件事務ランキング | F103: 0.1 | G103: 毎週配信 | I103: 抽出 | O103: R | Q103: =IF(G103="隔週A", MOD(INT(('26414_編集版'!$B$1-DATE(2026,4,14))/7), 2)=1, IF(G103="隔週B", MOD(INT(('26414_編集版'!$B$1-DATE(2026,4,14))/7), 2)=0, FALSE)) -> FALSE
A104: 火 | B104: 21 | E104: 応募から3日会員 | F104: 0.1 | G104: 毎週配信 | I104: フリー | O104: R | Q104: =IF(G104="隔週A", MOD(INT(('26414_編集版'!$B$1-DATE(2026,4,14))/7), 2)=1, IF(G104="隔週B", MOD(INT(('26414_編集版'!$B$1-DATE(2026,4,14))/7), 2)=0, FALSE)) -> FALSE
A105: 金 | B105: 8 | E105: データ入力×リモートOK | F105: 1.8 | G105: 毎週配信 | I105: 抽出 | O105: R | Q105: =IF(G105="隔週A", MOD(INT(('26414_編集版'!$B$1-DATE(2026,4,14))/7), 2)=1, IF(G105="隔週B", MOD(INT(('26414_編集版'!$B$1-DATE(2026,4,14))/7), 2)=0, FALSE)) -> FALSE
A106: 金 | B106: 8 | E106: フルリモート×好条件 | F106: 5.7 | G106: 毎週配信 | I106: 抽出 | O106: 部 | P106: 石 | Q106: =IF(G106="隔週A", MOD(INT(('26414_編集版'!$B$1-DATE(2026,4,14))/7), 2)=1, IF(G106="隔週B", MOD(INT(('26414_編集版'!$B$1-DATE(2026,4,14))/7), 2)=0, FALSE)) -> FALSE
A107: 金 | B107: 8 | E107: 応募から1日_好条件営業ランキング | F107: 0.1 | G107: 毎週配信 | I107: 抽出 | O107: R | Q107: =IF(G107="隔週A", MOD(INT(('26414_編集版'!$B$1-DATE(2026,4,14))/7), 2)=1, IF(G107="隔週B", MOD(INT(('26414_編集版'!$B$1-DATE(2026,4,14))/7), 2)=0, FALSE)) -> FALSE
A108: 金 | B108: 8 | E108: 既婚者 | F108: 0.4 | G108: 毎週配信 | I108: 抽出 | O108: R | Q108: =IF(G108="隔週A", MOD(INT(('26414_編集版'!$B$1-DATE(2026,4,14))/7), 2)=1, IF(G108="隔週B", MOD(INT(('26414_編集版'!$B$1-DATE(2026,4,14))/7), 2)=0, FALSE)) -> FALSE
A109: 金 | B109: 8 | E109: 梅田で働く | F109: 0.8 | G109: 毎週配信 | I109: 抽出 | O109: R | Q109: =IF(G109="隔週A", MOD(INT(('26414_編集版'!$B$1-DATE(2026,4,14))/7), 2)=1, IF(G109="隔週B", MOD(INT(('26414_編集版'!$B$1-DATE(2026,4,14))/7), 2)=0, FALSE)) -> FALSE
A110: 金 | B110: 8 | E110: 未婚者 | F110: 0.4 | G110: 毎週配信 | I110: 抽出 | O110: R | Q110: =IF(G110="隔週A", MOD(INT(('26414_編集版'!$B$1-DATE(2026,4,14))/7), 2)=1, IF(G110="隔週B", MOD(INT(('26414_編集版'!$B$1-DATE(2026,4,14))/7), 2)=0, FALSE)) -> FALSE
A111: 金 | B111: 9 | E111: 40~60代活躍中 | F111: 1.5 | G111: 毎週配信 | I111: 抽出 | O111: 石 | P111: 武 | Q111: =IF(G111="隔週A", MOD(INT(('26414_編集版'!$B$1-DATE(2026,4,14))/7), 2)=1, IF(G111="隔週B", MOD(INT(('26414_編集版'!$B$1-DATE(2026,4,14))/7), 2)=0, FALSE)) -> FALSE
A112: 金 | B112: 9 | E112: ランキング_事務（経理）_希望 | F112: 0.4 | G112: 毎週配信 | I112: 抽出 | O112: R | Q112: =IF(G112="隔週A", MOD(INT(('26414_編集版'!$B$1-DATE(2026,4,14))/7), 2)=1, IF(G112="隔週B", MOD(INT(('26414_編集版'!$B$1-DATE(2026,4,14))/7), 2)=0, FALSE)) -> FALSE
A113: 金 | B113: 10 | E113: 子育手当 | F113: 0.6 | G113: 毎週配信 | I113: 抽出 | O113: R | Q113: =IF(G113="隔週A", MOD(INT(('26414_編集版'!$B$1-DATE(2026,4,14))/7), 2)=1, IF(G113="隔週B", MOD(INT(('26414_編集版'!$B$1-DATE(2026,4,14))/7), 2)=0, FALSE)) -> FALSE
A114: 金 | B114: 11 | E114: クリエイティブ（その他）_希望 | F114: 0.3 | G114: 毎週配信 | I114: 抽出 | O114: R | Q114: =IF(G114="隔週A", MOD(INT(('26414_編集版'!$B$1-DATE(2026,4,14))/7), 2)=1, IF(G114="隔週B", MOD(INT(('26414_編集版'!$B$1-DATE(2026,4,14))/7), 2)=0, FALSE)) -> FALSE
A115: 金 | B115: 11 | E115: 今週の人気求人ランキング | F115: 5.7 | G115: 毎週配信 | I115: 抽出 | O115: R | Q115: =IF(G115="隔週A", MOD(INT(('26414_編集版'!$B$1-DATE(2026,4,14))/7), 2)=1, IF(G115="隔週B", MOD(INT(('26414_編集版'!$B$1-DATE(2026,4,14))/7), 2)=0, FALSE)) -> FALSE
A116: 金 | B116: 11 | E116: 事務（広報）_希望 | F116: 0.5 | G116: 毎週配信 | I116: 抽出 | O116: R | Q116: =IF(G116="隔週A", MOD(INT(('26414_編集版'!$B$1-DATE(2026,4,14))/7), 2)=1, IF(G116="隔週B", MOD(INT(('26414_編集版'!$B$1-DATE(2026,4,14))/7), 2)=0, FALSE)) -> FALSE
A117: 金 | B117: 12 | E117: ★新着総合_首都圏 B | F117: 5 | G117: 毎週配信 | I117: 抽出 | O117: 荒 | P117: 平 | Q117: =IF(G117="隔週A", MOD(INT(('26414_編集版'!$B$1-DATE(2026,4,14))/7), 2)=1, IF(G117="隔週B", MOD(INT(('26414_編集版'!$B$1-DATE(2026,4,14))/7), 2)=0, FALSE)) -> FALSE
A118: 金 | B118: 12 | E118: ★新着総合_西日本 B | F118: 2.9 | G118: 毎週配信 | I118: 抽出 | O118: 荒 | P118: 平 | Q118: =IF(G118="隔週A", MOD(INT(('26414_編集版'!$B$1-DATE(2026,4,14))/7), 2)=1, IF(G118="隔週B", MOD(INT(('26414_編集版'!$B$1-DATE(2026,4,14))/7), 2)=0, FALSE)) -> FALSE
A119: 金 | B119: 12 | E119: ★新着総合_東海 B | F119: 1 | G119: 毎週配信 | I119: 抽出 | O119: 荒 | P119: 平 | Q119: =IF(G119="隔週A", MOD(INT(('26414_編集版'!$B$1-DATE(2026,4,14))/7), 2)=1, IF(G119="隔週B", MOD(INT(('26414_編集版'!$B$1-DATE(2026,4,14))/7), 2)=0, FALSE)) -> FALSE
A120: 金 | B120: 12 | E120: ★新着総合_北海道・東北 B | F120: 0.8 | G120: 毎週配信 | I120: 抽出 | O120: 荒 | P120: 平 | Q120: =IF(G120="隔週A", MOD(INT(('26414_編集版'!$B$1-DATE(2026,4,14))/7), 2)=1, IF(G120="隔週B", MOD(INT(('26414_編集版'!$B$1-DATE(2026,4,14))/7), 2)=0, FALSE)) -> FALSE
A121: 金 | B121: 12 | E121: ★新着総合_北関東・甲信越・北陸 B | F121: 0.7 | G121: 毎週配信 | I121: 抽出 | O121: 荒 | P121: 平 | Q121: =IF(G121="隔週A", MOD(INT(('26414_編集版'!$B$1-DATE(2026,4,14))/7), 2)=1, IF(G121="隔週B", MOD(INT(('26414_編集版'!$B$1-DATE(2026,4,14))/7), 2)=0, FALSE)) -> FALSE
A122: 金 | B122: 14 | E122: フルリモート_全国 | F122: 3.7 | G122: 毎週配信 | I122: 抽出 | O122: R | Q122: =IF(G122="隔週A", MOD(INT(('26414_編集版'!$B$1-DATE(2026,4,14))/7), 2)=1, IF(G122="隔週B", MOD(INT(('26414_編集版'!$B$1-DATE(2026,4,14))/7), 2)=0, FALSE)) -> FALSE
A123: 金 | B123: 15 | E123: リモート手当あり | F123: 4.7 | G123: 毎週配信 | I123: 抽出 | O123: R | Q123: =IF(G123="隔週A", MOD(INT(('26414_編集版'!$B$1-DATE(2026,4,14))/7), 2)=1, IF(G123="隔週B", MOD(INT(('26414_編集版'!$B$1-DATE(2026,4,14))/7), 2)=0, FALSE)) -> FALSE
A124: 金 | B124: 15 | E124: 営業（その他）_希望 | F124: 0.3 | G124: 毎週配信 | I124: 抽出 | O124: R | Q124: =IF(G124="隔週A", MOD(INT(('26414_編集版'!$B$1-DATE(2026,4,14))/7), 2)=1, IF(G124="隔週B", MOD(INT(('26414_編集版'!$B$1-DATE(2026,4,14))/7), 2)=0, FALSE)) -> FALSE
A125: 金 | B125: 15 | E125: 事務（医療事務）_希望 | F125: 0.5 | G125: 毎週配信 | I125: 抽出 | O125: R | Q125: =IF(G125="隔週A", MOD(INT(('26414_編集版'!$B$1-DATE(2026,4,14))/7), 2)=1, IF(G125="隔週B", MOD(INT(('26414_編集版'!$B$1-DATE(2026,4,14))/7), 2)=0, FALSE)) -> FALSE
A126: 金 | B126: 17 | E126: ☆Womantype[全] | F126: 5 | G126: 毎週配信 | I126: フリー | O126: 内 | P126: 平 | Q126: =IF(G126="隔週A", MOD(INT(('26414_編集版'!$B$1-DATE(2026,4,14))/7), 2)=1, IF(G126="隔週B", MOD(INT(('26414_編集版'!$B$1-DATE(2026,4,14))/7), 2)=0, FALSE)) -> FALSE
A127: 金 | B127: 19 | E127: 経験_アパレル・コスメ | F127: 0.2 | G127: 毎週配信 | I127: 抽出 | O127: R | Q127: =IF(G127="隔週A", MOD(INT(('26414_編集版'!$B$1-DATE(2026,4,14))/7), 2)=1, IF(G127="隔週B", MOD(INT(('26414_編集版'!$B$1-DATE(2026,4,14))/7), 2)=0, FALSE)) -> FALSE
A128: 金 | B128: 19 | E128: 経験_一般事務 | F128: 0.7 | G128: 毎週配信 | I128: 抽出 | O128: R | Q128: =IF(G128="隔週A", MOD(INT(('26414_編集版'!$B$1-DATE(2026,4,14))/7), 2)=1, IF(G128="隔週B", MOD(INT(('26414_編集版'!$B$1-DATE(2026,4,14))/7), 2)=0, FALSE)) -> FALSE
A129: 金 | B129: 19 | E129: 経験_営業 | F129: 0.6 | G129: 毎週配信 | I129: 抽出 | O129: R | Q129: =IF(G129="隔週A", MOD(INT(('26414_編集版'!$B$1-DATE(2026,4,14))/7), 2)=1, IF(G129="隔週B", MOD(INT(('26414_編集版'!$B$1-DATE(2026,4,14))/7), 2)=0, FALSE)) -> FALSE
A130: 金 | B130: 20 | E130: 残業したくない | F130: 2.1 | G130: 毎週配信 | I130: 抽出 | O130: R | Q130: =IF(G130="隔週A", MOD(INT(('26414_編集版'!$B$1-DATE(2026,4,14))/7), 2)=1, IF(G130="隔週B", MOD(INT(('26414_編集版'!$B$1-DATE(2026,4,14))/7), 2)=0, FALSE)) -> FALSE
...

Sheet 特殊配信マスタ
A1: 46126 | B1: ='26414_編集版'!B1 -> 46126
A2: 曜日 | B2: 時間 | C2: 開始 | D2: 終了 | E2: メルマガ内容 | F2: 通数 | G2: 種別 | H2: PR | I2: 形式 | J2: 対象年齢 | K2: 対象現住所 | L2: 自動求人特集ID | M2: 備考 | N2: 新規 | O2: 設定者 | P2: 確認者 | Q2: 今週非配信(内部) | R2: サイクル | S2: 今週サイクル(内部) | T2: 配信停止
A3: 火 | B3: 8 | E3: ◇ポジションマッチ A1 | F3: 2.5 | G3: 特殊配信 | I3: フリー | O3: 内 | P3: 平 | Q3: {=IF($A$3:$A16="","",N($R$3:$R16)<>N($S$3:$S16))} -> FALSE | R3: 1 | S3: {=IF($A$3:$A16="","",MOD(INT(($B$1-$A$1)/7),3)+1)} -> 1 | T3: FALSE
A4: 金 | B4: 16 | E4: ◇ポジションマッチ B1 | F4: 2.5 | G4: 特殊配信 | I4: フリー | O4: 荒 | P4: 平 | Q4: FALSE | R4: 1 | S4: 1 | T4: FALSE
A5: 火 | B5: 8 | E5: ◇ポジションマッチ_36歳以上 A1 | F5: 2.5 | G5: 特殊配信 | I5: フリー | O5: 内 | P5: 平 | Q5: FALSE | R5: 1 | S5: 1 | T5: FALSE
A6: 金 | B6: 16 | E6: ◇ポジションマッチ_36歳以上 B1 | F6: 2.5 | G6: 特殊配信 | I6: フリー | O6: 荒 | P6: 平 | Q6: FALSE | R6: 1 | S6: 1 | T6: FALSE
A7: 火 | B7: 8 | E7: ◇ポジションマッチ A2 | F7: 2.5 | G7: 特殊配信 | I7: フリー | O7: 内 | P7: 平 | Q7: TRUE | R7: 2 | S7: 1 | T7: FALSE
A8: 金 | B8: 16 | E8: ◇ポジションマッチ B2 | F8: 2.5 | G8: 特殊配信 | I8: フリー | O8: 荒 | P8: 平 | Q8: TRUE | R8: 2 | S8: 1 | T8: FALSE
A9: 火 | B9: 8 | E9: ◇ポジションマッチ_36歳以上 A2 | F9: 2.5 | G9: 特殊配信 | I9: フリー | O9: 内 | P9: 平 | Q9: TRUE | R9: 2 | S9: 1 | T9: FALSE
A10: 金 | B10: 16 | E10: ◇ポジションマッチ_36歳以上 B2 | F10: 2.5 | G10: 特殊配信 | I10: フリー | O10: 荒 | P10: 平 | Q10: TRUE | R10: 2 | S10: 1 | T10: FALSE
A11: 火 | B11: 8 | E11: ◇ポジションマッチ A3 | F11: 2.5 | G11: 特殊配信 | I11: フリー | O11: 内 | P11: 平 | Q11: TRUE | R11: 3 | S11: 1 | T11: FALSE
A12: 金 | B12: 16 | E12: ◇ポジションマッチ B3 | F12: 2.5 | G12: 特殊配信 | I12: フリー | O12: 荒 | P12: 平 | Q12: TRUE | R12: 3 | S12: 1 | T12: FALSE
A13: 火 | B13: 8 | E13: ◇ポジションマッチ_36歳以上 A3 | F13: 2.5 | G13: 特殊配信 | I13: フリー | O13: 内 | P13: 平 | Q13: TRUE | R13: 3 | S13: 1 | T13: FALSE
A14: 金 | B14: 16 | E14: ◇ポジションマッチ_36歳以上 B3 | F14: 2.5 | G14: 特殊配信 | I14: フリー | O14: 荒 | P14: 平 | Q14: TRUE | R14: 3 | S14: 1 | T14: FALSE
A15: 火 | B15: 8 | E15: ◇ポジションマッチ 関西 | F15: 2.5 | G15: 特殊配信 | I15: フリー | O15: 内 | P15: 平 | Q15: TRUE | R15: 3 | S15: 1 | T15: FALSE
A16: 金 | B16: 16 | E16: ◇ポジションマッチ 関西 | F16: 2.5 | G16: 特殊配信 | I16: フリー | O16: 荒 | P16: 平 | Q16: TRUE | R16: 3 | S16: 1 | T16: FALSE
T17: FALSE
T18: FALSE
T19: FALSE
T20: FALSE
T21: FALSE
T22: FALSE
T23: FALSE
T24: FALSE
T25: FALSE
T26: FALSE

Sheet 自動求人特集
A1: 自動求人特集 | P1: 700件以上は配信停止
A2: 曜日 | B2: 時間 | C2: メルマガ内容 | D2: 通数 | E2: 種別 | F2: PR | G2: 形式 | H2: 対象年齢 | I2: 対象現住所 | J2: 自動求人特集ID | K2: 備考 | L2: 新規 | M2: 設定者 | N2: 確認者 | O2: 配信停止 | P2: 求人数
A3: =IFERROR(__xludf.DUMMYFUNCTION("FILTER({'リスト'!A3:B22, 'リスト'!E3:Q22}, 'リスト'!I3:I22=""自動求人"")"),"火") -> 火 | B3: =IFERROR(__xludf.DUMMYFUNCTION("""COMPUTED_VALUE"""),8.0) -> 8 | C3: =IFERROR(__xludf.DUMMYFUNCTION("""COMPUTED_VALUE"""),"関西_自己PR不要_リモート未経験_事務") -> 関西_自己PR不要_リモート未経験_事務 | D3: =IFERROR(__xludf.DUMMYFUNCTION("""COMPUTED_VALUE"""),0.2) -> 0.2 | E3: =IFERROR(__xludf.DUMMYFUNCTION("""COMPUTED_VALUE"""),"毎週配信") -> 毎週配信 | G3: =IFERROR(__xludf.DUMMYFUNCTION("""COMPUTED_VALUE"""),"自動求人") -> 自動求人 | J3: =IFERROR(__xludf.DUMMYFUNCTION("""COMPUTED_VALUE"""),24376.0) -> 24376 | K3: =IFERROR(__xludf.DUMMYFUNCTION("""COMPUTED_VALUE"""),"https://woman-type.jp/job-office/24376/f/") -> https://woman-type.jp/job-office/24376/f/ | M3: =IFERROR(__xludf.DUMMYFUNCTION("""COMPUTED_VALUE"""),"R") -> R | O3: =IFERROR(__xludf.DUMMYFUNCTION("""COMPUTED_VALUE"""),FALSE) -> FALSE | P3: =IFERROR(__xludf.DUMMYFUNCTION("IFERROR(IMPORTXML(K3, ""/html/body/form/div[1]/div[3]/main/div/div/div[2]/div/span[1]""))"),75.0) -> 75
A4: =IFERROR(__xludf.DUMMYFUNCTION("""COMPUTED_VALUE"""),"月") -> 月 | B4: =IFERROR(__xludf.DUMMYFUNCTION("""COMPUTED_VALUE"""),9.0) -> 9 | C4: =IFERROR(__xludf.DUMMYFUNCTION("""COMPUTED_VALUE"""),"年収600万円以上") -> 年収600万円以上 | D4: =IFERROR(__xludf.DUMMYFUNCTION("""COMPUTED_VALUE"""),0.3) -> 0.3 | E4: =IFERROR(__xludf.DUMMYFUNCTION("""COMPUTED_VALUE"""),"毎週配信") -> 毎週配信 | G4: =IFERROR(__xludf.DUMMYFUNCTION("""COMPUTED_VALUE"""),"自動求人") -> 自動求人 | J4: =IFERROR(__xludf.DUMMYFUNCTION("""COMPUTED_VALUE"""),3317.0) -> 3317 | K4: =IFERROR(__xludf.DUMMYFUNCTION("""COMPUTED_VALUE"""),"https://woman-type.jp/job-condition/46/3317/f/") -> https://woman-type.jp/job-condition/46/3317/f/ | M4: =IFERROR(__xludf.DUMMYFUNCTION("""COMPUTED_VALUE"""),"R") -> R | O4: =IFERROR(__xludf.DUMMYFUNCTION("""COMPUTED_VALUE"""),FALSE) -> FALSE | P4: =IFERROR(__xludf.DUMMYFUNCTION("IFERROR(IMPORTXML(K4, ""/html/body/form/div[1]/div[3]/main/div/div/div[2]/div/span[1]""))"),48.0) -> 48
A5: =IFERROR(__xludf.DUMMYFUNCTION("""COMPUTED_VALUE"""),"月") -> 月 | B5: =IFERROR(__xludf.DUMMYFUNCTION("""COMPUTED_VALUE"""),18.0) -> 18 | C5: =IFERROR(__xludf.DUMMYFUNCTION("""COMPUTED_VALUE"""),"自己PR不要_フルリモート") -> 自己PR不要_フルリモート | D5: =IFERROR(__xludf.DUMMYFUNCTION("""COMPUTED_VALUE"""),2.2) -> 2.2 | E5: =IFERROR(__xludf.DUMMYFUNCTION("""COMPUTED_VALUE"""),"毎週配信") -> 毎週配信 | G5: =IFERROR(__xludf.DUMMYFUNCTION("""COMPUTED_VALUE"""),"自動求人") -> 自動求人 | J5: =IFERROR(__xludf.DUMMYFUNCTION("""COMPUTED_VALUE"""),24436.0) -> 24436 | K5: =IFERROR(__xludf.DUMMYFUNCTION("""COMPUTED_VALUE"""),"https://woman-type.jp/job-area/district3/24436/f/") -> https://woman-type.jp/job-area/district3/24436/f/ | M5: =IFERROR(__xludf.DUMMYFUNCTION("""COMPUTED_VALUE"""),"R") -> R | O5: =IFERROR(__xludf.DUMMYFUNCTION("""COMPUTED_VALUE"""),FALSE) -> FALSE | P5: =IFERROR(__xludf.DUMMYFUNCTION("IFERROR(IMPORTXML(K5, ""/html/body/form/div[1]/div[3]/main/div/div/div[2]/div/span[1]""))"),140.0) -> 140
A6: =IFERROR(__xludf.DUMMYFUNCTION("""COMPUTED_VALUE"""),"月") -> 月 | B6: =IFERROR(__xludf.DUMMYFUNCTION("""COMPUTED_VALUE"""),19.0) -> 19 | C6: =IFERROR(__xludf.DUMMYFUNCTION("""COMPUTED_VALUE"""),"自己PR不要_35歳以上") -> 自己PR不要_35歳以上 | D6: =IFERROR(__xludf.DUMMYFUNCTION("""COMPUTED_VALUE"""),0.4) -> 0.4 | E6: =IFERROR(__xludf.DUMMYFUNCTION("""COMPUTED_VALUE"""),"毎週配信") -> 毎週配信 | G6: =IFERROR(__xludf.DUMMYFUNCTION("""COMPUTED_VALUE"""),"自動求人") -> 自動求人 | J6: =IFERROR(__xludf.DUMMYFUNCTION("""COMPUTED_VALUE"""),24936.0) -> 24936 | K6: =IFERROR(__xludf.DUMMYFUNCTION("""COMPUTED_VALUE"""),"https://woman-type.jp/job-area/24936/f/") -> https://woman-type.jp/job-area/24936/f/ | M6: =IFERROR(__xludf.DUMMYFUNCTION("""COMPUTED_VALUE"""),"R") -> R | O6: =IFERROR(__xludf.DUMMYFUNCTION("""COMPUTED_VALUE"""),FALSE) -> FALSE | P6: =IFERROR(__xludf.DUMMYFUNCTION("IFERROR(IMPORTXML(K6, ""/html/body/form/div[1]/div[3]/main/div/div/div[2]/div/span[1]""))"),218.0) -> 218
A7: =IFERROR(__xludf.DUMMYFUNCTION("""COMPUTED_VALUE"""),"水") -> 水 | B7: =IFERROR(__xludf.DUMMYFUNCTION("""COMPUTED_VALUE"""),10.0) -> 10 | C7: =IFERROR(__xludf.DUMMYFUNCTION("""COMPUTED_VALUE"""),"40代未経験_正社員") -> 40代未経験_正社員 | D7: =IFERROR(__xludf.DUMMYFUNCTION("""COMPUTED_VALUE"""),2.3) -> 2.3 | E7: =IFERROR(__xludf.DUMMYFUNCTION("""COMPUTED_VALUE"""),"毎週配信") -> 毎週配信 | G7: =IFERROR(__xludf.DUMMYFUNCTION("""COMPUTED_VALUE"""),"自動求人") -> 自動求人 | J7: =IFERROR(__xludf.DUMMYFUNCTION("""COMPUTED_VALUE"""),24298.0) -> 24298 | K7: =IFERROR(__xludf.DUMMYFUNCTION("""COMPUTED_VALUE"""),"https://woman-type.jp/job-condition/10/24298/f/") -> https://woman-type.jp/job-condition/10/24298/f/ | M7: =IFERROR(__xludf.DUMMYFUNCTION("""COMPUTED_VALUE"""),"R") -> R | O7: =IFERROR(__xludf.DUMMYFUNCTION("""COMPUTED_VALUE"""),FALSE) -> FALSE | P7: =IFERROR(__xludf.DUMMYFUNCTION("IFERROR(IMPORTXML(K7, ""/html/body/form/div[1]/div[3]/main/div/div/div[2]/div/span[1]""))"),222.0) -> 222
A8: =IFERROR(__xludf.DUMMYFUNCTION("""COMPUTED_VALUE"""),"水") -> 水 | B8: =IFERROR(__xludf.DUMMYFUNCTION("""COMPUTED_VALUE"""),12.0) -> 12 | C8: =IFERROR(__xludf.DUMMYFUNCTION("""COMPUTED_VALUE"""),"自己PR不要_リモート未経験_事務") -> 自己PR不要_リモート未経験_事務 | D8: =IFERROR(__xludf.DUMMYFUNCTION("""COMPUTED_VALUE"""),2.5) -> 2.5 | E8: =IFERROR(__xludf.DUMMYFUNCTION("""COMPUTED_VALUE"""),"毎週配信") -> 毎週配信 | G8: =IFERROR(__xludf.DUMMYFUNCTION("""COMPUTED_VALUE"""),"自動求人") -> 自動求人 | J8: =IFERROR(__xludf.DUMMYFUNCTION("""COMPUTED_VALUE"""),24336.0) -> 24336 | K8: =IFERROR(__xludf.DUMMYFUNCTION("""COMPUTED_VALUE"""),"https://woman-type.jp/job-office/24336/f/") -> https://woman-type.jp/job-office/24336/f/ | M8: =IFERROR(__xludf.DUMMYFUNCTION("""COMPUTED_VALUE"""),"R") -> R | O8: =IFERROR(__xludf.DUMMYFUNCTION("""COMPUTED_VALUE"""),FALSE) -> FALSE | P8: =IFERROR(__xludf.DUMMYFUNCTION("IFERROR(IMPORTXML(K8, ""/html/body/form/div[1]/div[3]/main/div/div/div[2]/div/span[1]""))"),174.0) -> 174
A9: =IFERROR(__xludf.DUMMYFUNCTION("""COMPUTED_VALUE"""),"水") -> 水 | B9: =IFERROR(__xludf.DUMMYFUNCTION("""COMPUTED_VALUE"""),12.0) -> 12 | C9: =IFERROR(__xludf.DUMMYFUNCTION("""COMPUTED_VALUE"""),"自己PR不要_リモート未経験_営業") -> 自己PR不要_リモート未経験_営業 | D9: =IFERROR(__xludf.DUMMYFUNCTION("""COMPUTED_VALUE"""),0.3) -> 0.3 | E9: =IFERROR(__xludf.DUMMYFUNCTION("""COMPUTED_VALUE"""),"毎週配信") -> 毎週配信 | G9: =IFERROR(__xludf.DUMMYFUNCTION("""COMPUTED_VALUE"""),"自動求人") -> 自動求人 | J9: =IFERROR(__xludf.DUMMYFUNCTION("""COMPUTED_VALUE"""),24356.0) -> 24356 | K9: =IFERROR(__xludf.DUMMYFUNCTION("""COMPUTED_VALUE"""),"https://woman-type.jp/job-sales/24356/f/") -> https://woman-type.jp/job-sales/24356/f/ | M9: =IFERROR(__xludf.DUMMYFUNCTION("""COMPUTED_VALUE"""),"R") -> R | O9: =IFERROR(__xludf.DUMMYFUNCTION("""COMPUTED_VALUE"""),FALSE) -> FALSE | P9: =IFERROR(__xludf.DUMMYFUNCTION("IFERROR(IMPORTXML(K9, ""/html/body/form/div[1]/div[3]/main/div/div/div[2]/div/span[1]""))"),104.0) -> 104
A10: =IFERROR(__xludf.DUMMYFUNCTION("""COMPUTED_VALUE"""),"水") -> 水 | B10: =IFERROR(__xludf.DUMMYFUNCTION("""COMPUTED_VALUE"""),12.0) -> 12 | C10: =IFERROR(__xludf.DUMMYFUNCTION("""COMPUTED_VALUE"""),"自己PR不要_残業無_未経験_販サ") -> 自己PR不要_残業無_未経験_販サ | D10: =IFERROR(__xludf.DUMMYFUNCTION("""COMPUTED_VALUE"""),0.3) -> 0.3 | E10: =IFERROR(__xludf.DUMMYFUNCTION("""COMPUTED_VALUE"""),"毎週配信") -> 毎週配信 | G10: =IFERROR(__xludf.DUMMYFUNCTION("""COMPUTED_VALUE"""),"自動求人") -> 自動求人 | J10: =IFERROR(__xludf.DUMMYFUNCTION("""COMPUTED_VALUE"""),24358.0) -> 24358 | K10: =IFERROR(__xludf.DUMMYFUNCTION("""COMPUTED_VALUE"""),"https://woman-type.jp/job-service/24358/f/") -> https://woman-type.jp/job-service/24358/f/ | M10: =IFERROR(__xludf.DUMMYFUNCTION("""COMPUTED_VALUE"""),"R") -> R | O10: =IFERROR(__xludf.DUMMYFUNCTION("""COMPUTED_VALUE"""),FALSE) -> FALSE | P10: =IFERROR(__xludf.DUMMYFUNCTION("IFERROR(IMPORTXML(K10, ""/html/body/form/div[1]/div[3]/main/div/div/div[2]/div/span[1]""))"),116.0) -> 116
